Workbook

Sheet Costs
A2: Costs Incurred Breakdown
A3: Item Cost | B3: 35255.88
A4: Freight | B4: 11749.98
A5: Duty Charges | B5: 1352.57 | C5: 0.05
A6: GST | B6: - | C6: 0.08
A7: Broker Charges | B7: 1814.4
A8: Claude Sub | B8: 2420
A9: Chatgpt Sub | B9: 440
A10: Grok Sub | B10: 660
A11: Business Card | B11: 2200
A12: Bags | B12: 3300 | F12: Total cost | G12: 69267.83 | J12: =(43.12/G14)*G12 -> 294.85275
A13: Box | B13: 3300 | F13: No. Quantity | G13: 420
A14: Packaging Compliments | B14: 1540 | F14: Per Unit CNF | G14: 10129.9
A15: Sample Bottles | B15: 1100 | C15: =SUM(B10:B15) -> 12100
A16: GoDaddy 1 Year Sub | B16: 755
A17: Logo Sub 6 months | B17: 300
A18: Partnership Registration | B18: 2000
A19: Business Name Registration | B19: 200
A20: Business Activity Registration | B20: 150
A21: Stamp Registration and Making | B21: 430
A22: Dhiraagu Domain | B22: 300
A23: Total | B23: =SUM(B3:B22) -> 69267.83 | C23: =B23/420 -> 164.9234
C24: =((B23/420)/2.5) -> 65.969362
A26: TOTAL REALIZED | B26: =B23-C15 -> 57167.83

Sheet Pricing WorkSheet
A1: Product Name (as invoiced) | B1: Category | C1: Qty (NOS) | D1: CNF / Unit (invoiced USD) | E1: CNF / Total Units (invoiced USD) | F1: CNF / Unit (MVR) | G1: CNF / Total Units (MVR) | H1: Lebelage Price w/o Shipping (MVR) | I1: Yesstyle Prices w/o Shipping (MVR) | J1: Base Profit / Unit (MVR) | K1: Weighted max expense (MVR) | L1: Selling price w/o GST (MVR) | M1: GST 8% (MVR) | N1: Total Selling Price / Unit (MVR) | O1: Total Selling Price / Total Units (MVR) | P1: Proposed New Selling Price / Unit (MVR) | Q1: Lebelage Retail Price as per Kim's Catalogue (USD) | R1: Lebelage Retail Price as per Kim's Catalogue (MVR) | S1: Lebelage Price w/o Shipping (MVR)2 | T1: Lebelage Retail Price (USD) | U1: CNF / Unit (invoiced USD)2 | V1: CNF / Unit (MVR)2 | W1: Yesstyle Prices w/o Shipping (MVR)2 | X1: Total Selling Price / Unit (MVR)2 | Y1: Minimum Selling Price w/o GST (MVR) | Z1: Minimum Selling Price w/ GST (MVR) | AA1: Minimum Selling Price w/ GST for Total Units (MVR) | AB1: Alt 1 Median Selling Price w/o GST (MVR) | AC1: Alt 1 Median Selling Price w/ GST (MVR) | AD1: Alt 1 Median Selling Price w/ GST for Total Units (MVR) | AE1: Alt 2 Median Selling Price w/o GST (MVR)2 | AF1: Alt 2 Median Selling Price w/ GST (MVR)2 | AG1: Alt 2 Median Selling Price w/ GST for Total Units (MVR) | AH1: Maximum Selling Price w/o GST (MVR) | AI1: Maximum Selling Price w/ GST (MVR) | AJ1: Maximum Selling Price w/ GST for Total Units (MVR)2 | AK1: Revenue to CNF ratio (%) | AL1: Profit / Unit (MVR) | AM1: Total Profit (MVR)
N2: Current Price | O2: Current Expected Revenue on 100% sales | P2: Final Price | R2: Kim's Lebelage Catalogue | S2: Lebelage Website Price w/o Shipping | V2: CNF | W2: Yesstyle Price w/o Shipping | Y2: (Lebelage selling price)*15.42 | Z2: Per Product | AA2: "Minimum Selling Price" Revenue on 100% sales | AB2: (Lebelage selling price + 9 usd shipping)*15.42 | AC2: Per Product | AD2: "Alt 1 Median Selling Price" Revenue on 100% sales | AE2: (Lebelage selling price)*22 | AF2: Per Product | AG2: "Alt 2 Median Selling Price" Revenue on 100% sales | AH2: (Lebelage selling price + 9usd shipping)*22 | AI2: Per Product | AJ2: "Maximum Selling Price" Revenue on 100% sales
A3: Aloe Bubble Chewy Foam 200ml | B3: Cleansing & Peeling | C3: 4 | D3: 7.06 | E3: 28.24 | F3: =D3*22 -> 155.32 | G3: =SUM(F3*C3) -> 621.28 | H3: 487.52 | I3: 322.74 | J3: =L3-K3 -> 140.65438 | K3: =(F3/$G$92)*Costs!$B$23 -> 229.71599 | L3: =N3/1.08 -> 370.37037 | M3: =L3*0.08 -> 29.62963 | N3: 400 | O3: =Table1[[#This Row],[Total Selling Price / Unit (MVR)]]*Table1[[#This Row],[Qty (NOS)]] -> 1600 | Q3: 21.36 | R3: =Q3*22 -> 469.92 | S3: 487.52 | T3: 22.16 | U3: 7.06 | V3: 155.32 | W3: 322.74 | X3: 400 | Y3: =T3*15.42 -> 341.7072 | Z3: =Y3*1.08 -> 369.04378 | AA3: =C3*Z3 -> 1476.1751 | AB3: =(T3+9)*15.42 -> 480.4872 | AC3: =AB3*1.08 -> 518.92618 | AD3: =C3*AC3 -> 2075.7047 | AE3: =T3*22 -> 487.52 | AF3: =AE3*1.08 -> 526.5216 | AG3: =C3*AF3 -> 2106.0864 | AH3: =(T3+9)*22 -> 685.52 | AI3: =AH3*1.08 -> 740.3616 | AJ3: =C3*AI3 -> 2961.4464 | AK3: =Table1[[#This Row],[Total Selling Price / Unit (MVR)]]/Table1[[#This Row],[CNF / Unit (MVR)]] -> 2.5753284 | AL3: =Table1[[#This Row],[Total Selling Price / Unit (MVR)]]-(Table1[[#This Row],[GST 8% (MVR)]]+Table1[[#This Row],[Weighted max expense (MVR)]]) -> 140.65438 | AM3: =Table1[[#This Row],[Profit / Unit (MVR)]]*Table1[[#This Row],[Qty (NOS)]] -> 562.61753
A4: AVOCADO REVITAL CLEANSING FOAM 180ml | B4: Cleansing & Peeling | C4: 4 | D4: 3.9 | E4: 15.6 | F4: =D4*22 -> 85.8 | G4: =SUM(F4*C4) -> 343.2 | H4: 119.02 | I4: 176.22 | J4: =L4-K4 -> 39.769733 | K4: =(F4/$G$92)*Costs!$B$23 -> 126.89693 | L4: =N4/1.08 -> 166.66667 | M4: =L4*0.08 -> 13.333333 | N4: 180 | O4: =Table1[[#This Row],[Total Selling Price / Unit (MVR)]]*Table1[[#This Row],[Qty (NOS)]] -> 720 | Q4: 5.21 | R4: =Q4*22 -> 114.62 | S4: 119.02 | T4: 5.41 | U4: 3.9 | V4: 85.8 | W4: 176.22 | X4: 180 | Y4: =T4*15.42 -> 83.4222 | Z4: =Y4*1.08 -> 90.095976 | AA4: =C4*Z4 -> 360.3839 | AB4: =(T4+9)*15.42 -> 222.2022 | AC4: =AB4*1.08 -> 239.97838 | AD4: =C4*AC4 -> 959.9135 | AE4: =T4*22 -> 119.02 | AF4: =AE4*1.08 -> 128.5416 | AG4: =C4*AF4 -> 514.1664 | AH4: =(T4+9)*22 -> 317.02 | AI4: =AH4*1.08 -> 342.3816 | AJ4: =C4*AI4 -> 1369.5264 | AK4: =Table1[[#This Row],[Total Selling Price / Unit (MVR)]]/Table1[[#This Row],[CNF / Unit (MVR)]] -> 2.0979021 | AL4: =Table1[[#This Row],[Total Selling Price / Unit (MVR)]]-(Table1[[#This Row],[GST 8% (MVR)]]+Table1[[#This Row],[Weighted max expense (MVR)]]) -> 39.769733 | AM4: =Table1[[#This Row],[Profit / Unit (MVR)]]*Table1[[#This Row],[Qty (NOS)]] -> 159.07893 | AO4: Total Revenue | AP4: =O92 -> 136161
A5: Centella Bubble Chewy Foam 200ml | B5: Cleansing & Peeling | C5: 7 | D5: 7.06 | E5: 49.42 | F5: =D5*22 -> 155.32 | G5: =SUM(F5*C5) -> 1087.24 | H5: 487.52 | I5: 322.74 | J5: =L5-K5 -> 140.65438 | K5: =(F5/$G$92)*Costs!$B$23 -> 229.71599 | L5: =N5/1.08 -> 370.37037 | M5: =L5*0.08 -> 29.62963 | N5: 400 | O5: =Table1[[#This Row],[Total Selling Price / Unit (MVR)]]*Table1[[#This Row],[Qty (NOS)]] -> 2800 | Q5: 21.36 | R5: =Q5*22 -> 469.92 | S5: 487.52 | T5: 22.16 | U5: 7.06 | V5: 155.32 | W5: 322.74 | X5: 400 | Y5: =T5*15.42 -> 341.7072 | Z5: =Y5*1.08 -> 369.04378 | AA5: =C5*Z5 -> 2583.3064 | AB5: =(T5+9)*15.42 -> 480.4872 | AC5: =AB5*1.08 -> 518.92618 | AD5: =C5*AC5 -> 3632.4832 | AE5: =T5*22 -> 487.52 | AF5: =AE5*1.08 -> 526.5216 | AG5: =C5*AF5 -> 3685.6512 | AH5: =(T5+9)*22 -> 685.52 | AI5: =AH5*1.08 -> 740.3616 | AJ5: =C5*AI5 -> 5182.5312 | AK5: =Table1[[#This Row],[Total Selling Price / Unit (MVR)]]/Table1[[#This Row],[CNF / Unit (MVR)]] -> 2.5753284 | AL5: =Table1[[#This Row],[Total Selling Price / Unit (MVR)]]-(Table1[[#This Row],[GST 8% (MVR)]]+Table1[[#This Row],[Weighted max expense (MVR)]]) -> 140.65438 | AM5: =Table1[[#This Row],[Profit / Unit (MVR)]]*Table1[[#This Row],[Qty (NOS)]] -> 984.58068 | AO5: Total Cost | AP5: =Costs!B23 -> 69267.83
A6: Charcoal Clay 2in1 Pack Foam 120ml | B6: Cleansing & Peeling | C6: 7 | D6: 4.24 | E6: 29.68 | F6: =D6*22 -> 93.28 | G6: =SUM(F6*C6) -> 652.96 | H6: 407.66 | I6: 162.36 | J6: =L6-K6 -> 186.11433 | K6: =(F6/$G$92)*Costs!$B$23 -> 137.95974 | L6: =N6/1.08 -> 324.07407 | M6: =L6*0.08 -> 25.925926 | N6: 350 | O6: =Table1[[#This Row],[Total Selling Price / Unit (MVR)]]*Table1[[#This Row],[Qty (NOS)]] -> 2450 | Q6: 17.86 | R6: =Q6*22 -> 392.92 | S6: 407.66 | T6: 18.53 | U6: 4.24 | V6: 93.28 | W6: 162.36 | X6: 350 | Y6: =T6*15.42 -> 285.7326 | Z6: =Y6*1.08 -> 308.59121 | AA6: =C6*Z6 -> 2160.1385 | AB6: =(T6+9)*15.42 -> 424.5126 | AC6: =AB6*1.08 -> 458.47361 | AD6: =C6*AC6 -> 3209.3153 | AE6: =T6*22 -> 407.66 | AF6: =AE6*1.08 -> 440.2728 | AG6: =C6*AF6 -> 3081.9096 | AH6: =(T6+9)*22 -> 605.66 | AI6: =AH6*1.08 -> 654.1128 | AJ6: =C6*AI6 -> 4578.7896 | AK6: =Table1[[#This Row],[Total Selling Price / Unit (MVR)]]/Table1[[#This Row],[CNF / Unit (MVR)]] -> 3.7521441 | AL6: =Table1[[#This Row],[Total Selling Price / Unit (MVR)]]-(Table1[[#This Row],[GST 8% (MVR)]]+Table1[[#This Row],[Weighted max expense (MVR)]]) -> 186.11433 | AM6: =Table1[[#This Row],[Profit / Unit (MVR)]]*Table1[[#This Row],[Qty (NOS)]] -> 1302.8003 | AO6: Total Profit | AP6: =AP4-AP5 -> 66893.17
A7: Charcoal Pore Clay Cleansing Foam 180ml | B7: Cleansing & Peeling | C7: 7 | D7: 3.9 | E7: 27.3 | F7: =D7*22 -> 85.8 | G7: =SUM(F7*C7) -> 600.6 | H7: 119.02 | I7: 176.22 | J7: =L7-K7 -> 39.769733 | K7: =(F7/$G$92)*Costs!$B$23 -> 126.89693 | L7: =N7/1.08 -> 166.66667 | M7: =L7*0.08 -> 13.333333 | N7: 180 | O7: =Table1[[#This Row],[Total Selling Price / Unit (MVR)]]*Table1[[#This Row],[Qty (NOS)]] -> 1260 | Q7: 5.21 | R7: =Q7*22 -> 114.62 | S7: 119.02 | T7: 5.41 | U7: 3.9 | V7: 85.8 | W7: 176.22 | X7: 180 | Y7: =T7*15.42 -> 83.4222 | Z7: =Y7*1.08 -> 90.095976 | AA7: =C7*Z7 -> 630.67183 | AB7: =(T7+9)*15.42 -> 222.2022 | AC7: =AB7*1.08 -> 239.97838 | AD7: =C7*AC7 -> 1679.8486 | AE7: =T7*22 -> 119.02 | AF7: =AE7*1.08 -> 128.5416 | AG7: =C7*AF7 -> 899.7912 | AH7: =(T7+9)*22 -> 317.02 | AI7: =AH7*1.08 -> 342.3816 | AJ7: =C7*AI7 -> 2396.6712 | AK7: =Table1[[#This Row],[Total Selling Price / Unit (MVR)]]/Table1[[#This Row],[CNF / Unit (MVR)]] -> 2.0979021 | AL7: =Table1[[#This Row],[Total Selling Price / Unit (MVR)]]-(Table1[[#This Row],[GST 8% (MVR)]]+Table1[[#This Row],[Weighted max expense (MVR)]]) -> 39.769733 | AM7: =Table1[[#This Row],[Profit / Unit (MVR)]]*Table1[[#This Row],[Qty (NOS)]] -> 278.38813 | AO7: Shipment Target Sales 60% | AP7: =AP4*60% -> 81696.6
A8: FRUIT PEACH&APPLE MANGO CLEANSING FOAM 100ml | B8: Cleansing & Peeling | C8: 8 | D8: 2.02 | E8: 16.16 | F8: =D8*22 -> 44.44 | G8: =SUM(F8*C8) -> 355.52 | H8: 63.58 | I8: 161.7 | J8: =L8-K8 -> 54.644266 | K8: =(F8/$G$92)*Costs!$B$23 -> 65.726104 | L8: =N8/1.08 -> 120.37037 | M8: =L8*0.08 -> 9.6296296 | N8: 130 | O8: =Table1[[#This Row],[Total Selling Price / Unit (MVR)]]*Table1[[#This Row],[Qty (NOS)]] -> 1040 | Q8: 2.79 | R8: =Q8*22 -> 61.38 | S8: 63.58 | T8: 2.89 | U8: 2.02 | V8: 44.44 | W8: 161.7 | X8: 130 | Y8: =T8*15.42 -> 44.5638 | Z8: =Y8*1.08 -> 48.128904 | AA8: =C8*Z8 -> 385.03123 | AB8: =(T8+9)*15.42 -> 183.3438 | AC8: =AB8*1.08 -> 198.0113 | AD8: =C8*AC8 -> 1584.0904 | AE8: =T8*22 -> 63.58 | AF8: =AE8*1.08 -> 68.6664 | AG8: =C8*AF8 -> 549.3312 | AH8: =(T8+9)*22 -> 261.58 | AI8: =AH8*1.08 -> 282.5064 | AJ8: =C8*AI8 -> 2260.0512 | AK8: =Table1[[#This Row],[Total Selling Price / Unit (MVR)]]/Table1[[#This Row],[CNF / Unit (MVR)]] -> 2.9252925 | AL8: =Table1[[#This Row],[Total Selling Price / Unit (MVR)]]-(Table1[[#This Row],[GST 8% (MVR)]]+Table1[[#This Row],[Weighted max expense (MVR)]]) -> 54.644266 | AM8: =Table1[[#This Row],[Profit / Unit (MVR)]]*Table1[[#This Row],[Qty (NOS)]] -> 437.15413
A9: Glutathione Bubble Chewy Foam 200ml | B9: Cleansing & Peeling | C9: 4 | D9: 7.06 | E9: 28.24 | F9: =D9*22 -> 155.32 | G9: =SUM(F9*C9) -> 621.28 | H9: 487.52 | I9: 322.74 | J9: =L9-K9 -> 140.65438 | K9: =(F9/$G$92)*Costs!$B$23 -> 229.71599 | L9: =N9/1.08 -> 370.37037 | M9: =L9*0.08 -> 29.62963 | N9: 400 | O9: =Table1[[#This Row],[Total Selling Price / Unit (MVR)]]*Table1[[#This Row],[Qty (NOS)]] -> 1600 | Q9: 21.36 | R9: =Q9*22 -> 469.92 | S9: 487.52 | T9: 22.16 | U9: 7.06 | V9: 155.32 | W9: 322.74 | X9: 400 | Y9: =T9*15.42 -> 341.7072 | Z9: =Y9*1.08 -> 369.04378 | AA9: =C9*Z9 -> 1476.1751 | AB9: =(T9+9)*15.42 -> 480.4872 | AC9: =AB9*1.08 -> 518.92618 | AD9: =C9*AC9 -> 2075.7047 | AE9: =T9*22 -> 487.52 | AF9: =AE9*1.08 -> 526.5216 | AG9: =C9*AF9 -> 2106.0864 | AH9: =(T9+9)*22 -> 685.52 | AI9: =AH9*1.08 -> 740.3616 | AJ9: =C9*AI9 -> 2961.4464 | AK9: =Table1[[#This Row],[Total Selling Price / Unit (MVR)]]/Table1[[#This Row],[CNF / Unit (MVR)]] -> 2.5753284 | AL9: =Table1[[#This Row],[Total Selling Price / Unit (MVR)]]-(Table1[[#This Row],[GST 8% (MVR)]]+Table1[[#This Row],[Weighted max expense (MVR)]]) -> 140.65438 | AM9: =Table1[[#This Row],[Profit / Unit (MVR)]]*Table1[[#This Row],[Qty (NOS)]] -> 562.61753
A10: Glutinous Rice Clay 2in1 Pack Foam 120ml | B10: Cleansing & Peeling | C10: 4 | D10: 4.24 | E10: 16.96 | F10: =D10*22 -> 93.28 | G10: =SUM(F10*C10) -> 373.12 | H10: 407.66 | I10: 162.36 | J10: =L10-K10 -> 186.11433 | K10: =(F10/$G$92)*Costs!$B$23 -> 137.95974 | L10: =N10/1.08 -> 324.07407 | M10: =L10*0.08 -> 25.925926 | N10: 350 | O10: =Table1[[#This Row],[Total Selling Price / Unit (MVR)]]*Table1[[#This Row],[Qty (NOS)]] -> 1400 | Q10: 17.86 | R10: =Q10*22 -> 392.92 | S10: 407.66 | T10: 18.53 | U10: 4.24 | V10: 93.28 | W10: 162.36 | X10: 350 | Y10: =T10*15.42 -> 285.7326 | Z10: =Y10*1.08 -> 308.59121 | AA10: =C10*Z10 -> 1234.3648 | AB10: =(T10+9)*15.42 -> 424.5126 | AC10: =AB10*1.08 -> 458.47361 | AD10: =C10*AC10 -> 1833.8944 | AE10: =T10*22 -> 407.66 | AF10: =AE10*1.08 -> 440.2728 | AG10: =C10*AF10 -> 1761.0912 | AH10: =(T10+9)*22 -> 605.66 | AI10: =AH10*1.08 -> 654.1128 | AJ10: =C10*AI10 -> 2616.4512 | AK10: =Table1[[#This Row],[Total Selling Price / Unit (MVR)]]/Table1[[#This Row],[CNF / Unit (MVR)]] -> 3.7521441 | AL10: =Table1[[#This Row],[Total Selling Price / Unit (MVR)]]-(Table1[[#This Row],[GST 8% (MVR)]]+Table1[[#This Row],[Weighted max expense (MVR)]]) -> 186.11433 | AM10: =Table1[[#This Row],[Profit / Unit (MVR)]]*Table1[[#This Row],[Qty (NOS)]] -> 744.45732
A11: Lemon Brightening Cleansing Foam 180ml | B11: Cleansing & Peeling | C11: 4 | D11: 3.9 | E11: 15.6 | F11: =D11*22 -> 85.8 | G11: =SUM(F11*C11) -> 343.2 | H11: 119.02 | I11: 176.22 | J11: =L11-K11 -> 39.769733 | K11: =(F11/$G$92)*Costs!$B$23 -> 126.89693 | L11: =N11/1.08 -> 166.66667 | M11: =L11*0.08 -> 13.333333 | N11: 180 | O11: =Table1[[#This Row],[Total Selling Price / Unit (MVR)]]*Table1[[#This Row],[Qty (NOS)]] -> 720 | Q11: 5.21 | R11: =Q11*22 -> 114.62 | S11: 119.02 | T11: 5.41 | U11: 3.9 | V11: 85.8 | W11: 176.22 | X11: 180 | Y11: =T11*15.42 -> 83.4222 | Z11: =Y11*1.08 -> 90.095976 | AA11: =C11*Z11 -> 360.3839 | AB11: =(T11+9)*15.42 -> 222.2022 | AC11: =AB11*1.08 -> 239.97838 | AD11: =C11*AC11 -> 959.9135 | AE11: =T11*22 -> 119.02 | AF11: =AE11*1.08 -> 128.5416 | AG11: =C11*AF11 -> 514.1664 | AH11: =(T11+9)*22 -> 317.02 | AI11: =AH11*1.08 -> 342.3816 | AJ11: =C11*AI11 -> 1369.5264 | AK11: =Table1[[#This Row],[Total Selling Price / Unit (MVR)]]/Table1[[#This Row],[CNF / Unit (MVR)]] -> 2.0979021 | AL11: =Table1[[#This Row],[Total Selling Price / Unit (MVR)]]-(Table1[[#This Row],[GST 8% (MVR)]]+Table1[[#This Row],[Weighted max expense (MVR)]]) -> 39.769733 | AM11: =Table1[[#This Row],[Profit / Unit (MVR)]]*Table1[[#This Row],[Qty (NOS)]] -> 159.07893
A12: Panthenol Bubble Chewy Foam 200ml | B12: Cleansing & Peeling | C12: 4 | D12: 7.06 | E12: 28.24 | F12: =D12*22 -> 155.32 | G12: =SUM(F12*C12) -> 621.28 | H12: 487.52 | I12: 322.74 | J12: =L12-K12 -> 140.65438 | K12: =(F12/$G$92)*Costs!$B$23 -> 229.71599 | L12: =N12/1.08 -> 370.37037 | M12: =L12*0.08 -> 29.62963 | N12: 400 | O12: =Table1[[#This Row],[Total Selling Price / Unit (MVR)]]*Table1[[#This Row],[Qty (NOS)]] -> 1600 | Q12: 21.36 | R12: =Q12*22 -> 469.92 | S12: 487.52 | T12: 22.16 | U12: 7.06 | V12: 155.32 | W12: 322.74 | X12: 400 | Y12: =T12*15.42 -> 341.7072 | Z12: =Y12*1.08 -> 369.04378 | AA12: =C12*Z12 -> 1476.1751 | AB12: =(T12+9)*15.42 -> 480.4872 | AC12: =AB12*1.08 -> 518.92618 | AD12: =C12*AC12 -> 2075.7047 | AE12: =T12*22 -> 487.52 | AF12: =AE12*1.08 -> 526.5216 | AG12: =C12*AF12 -> 2106.0864 | AH12: =(T12+9)*22 -> 685.52 | AI12: =AH12*1.08 -> 740.3616 | AJ12: =C12*AI12 -> 2961.4464 | AK12: =Table1[[#This Row],[Total Selling Price / Unit (MVR)]]/Table1[[#This Row],[CNF / Unit (MVR)]] -> 2.5753284 | AL12: =Table1[[#This Row],[Total Selling Price / Unit (MVR)]]-(Table1[[#This Row],[GST 8% (MVR)]]+Table1[[#This Row],[Weighted max expense (MVR)]]) -> 140.65438 | AM12: =Table1[[#This Row],[Profit / Unit (MVR)]]*Table1[[#This Row],[Qty (NOS)]] -> 562.61753
A13: PDRN Bubble Chewy Foam 200ml | B13: Cleansing & Peeling | C13: 4 | D13: 7.06 | E13: 28.24 | F13: =D13*22 -> 155.32 | G13: =SUM(F13*C13) -> 621.28 | H13: 487.52 | I13: 322.74 | J13: =L13-K13 -> 140.65438 | K13: =(F13/$G$92)*Costs!$B$23 -> 229.71599 | L13: =N13/1.08 -> 370.37037 | M13: =L13*0.08 -> 29.62963 | N13: 400 | O13: =Table1[[#This Row],[Total Selling Price / Unit (MVR)]]*Table1[[#This Row],[Qty (NOS)]] -> 1600 | Q13: 21.36 | R13: =Q13*22 -> 469.92 | S13: 487.52 | T13: 22.16 | U13: 7.06 | V13: 155.32 | W13: 322.74 | X13: 400 | Y13: =T13*15.42 -> 341.7072 | Z13: =Y13*1.08 -> 369.04378 | AA13: =C13*Z13 -> 1476.1751 | AB13: =(T13+9)*15.42 -> 480.4872 | AC13: =AB13*1.08 -> 518.92618 | AD13: =C13*AC13 -> 2075.7047 | AE13: =T13*22 -> 487.52 | AF13: =AE13*1.08 -> 526.5216 | AG13: =C13*AF13 -> 2106.0864 | AH13: =(T13+9)*22 -> 685.52 | AI13: =AH13*1.08 -> 740.3616 | AJ13: =C13*AI13 -> 2961.4464 | AK13: =Table1[[#This Row],[Total Selling Price / Unit (MVR)]]/Table1[[#This Row],[CNF / Unit (MVR)]] -> 2.5753284 | AL13: =Table1[[#This Row],[Total Selling Price / Unit (MVR)]]-(Table1[[#This Row],[GST 8% (MVR)]]+Table1[[#This Row],[Weighted max expense (MVR)]]) -> 140.65438 | AM13: =Table1[[#This Row],[Profit / Unit (MVR)]]*Table1[[#This Row],[Qty (NOS)]] -> 562.61753
A14: Real Sensation Blemish Cleansing Foam 1+1 150ml x 2 | B14: Cleansing & Peeling | C14: 8 | D14: 6.84 | E14: 54.72 | F14: =D14*22 -> 150.48 | G14: =SUM(F14*C14) -> 1203.84 | H14: N/A | I14: 403.04 | J14: =L14-K14 -> 180.22008 | K14: =(F14/$G$92)*Costs!$B$23 -> 222.5577 | L14: =N14/1.08 -> 402.77778 | M14: =L14*0.08 -> 32.222222 | N14: 435 | O14: =Table1[[#This Row],[Total Selling Price / Unit (MVR)]]*Table1[[#This Row],[Qty (NOS)]] -> 3480 | Q14: 21.36 | R14: =Q14*22 -> 469.92 | S14: N/A | T14: 22.16 | U14: 6.84 | V14: 150.48 | W14: 403.04 | X14: 435 | Y14: =T14*15.42 -> 341.7072 | Z14: =Y14*1.08 -> 369.04378 | AA14: =C14*Z14 -> 2952.3502 | AB14: =(T14+9)*15.42 -> 480.4872 | AC14: =AB14*1.08 -> 518.92618 | AD14: =C14*AC14 -> 4151.4094 | AE14: =T14*22 -> 487.52 | AF14: =AE14*1.08 -> 526.5216 | AG14: =C14*AF14 -> 4212.1728 | AH14: =(T14+9)*22 -> 685.52 | AI14: =AH14*1.08 -> 740.3616 | AJ14: =C14*AI14 -> 5922.8928 | AK14: =Table1[[#This Row],[Total Selling Price / Unit (MVR)]]/Table1[[#This Row],[CNF / Unit (MVR)]] -> 2.8907496 | AL14: =Table1[[#This Row],[Total Selling Price / Unit (MVR)]]-(Table1[[#This Row],[GST 8% (MVR)]]+Table1[[#This Row],[Weighted max expense (MVR)]]) -> 180.22008 | AM14: =Table1[[#This Row],[Profit / Unit (MVR)]]*Table1[[#This Row],[Qty (NOS)]] -> 1441.7606
A15: Real Sensation Pore Cleansing Foam 1+1 150ml x 2 | B15: Cleansing & Peeling | C15: 6 | D15: 6.84 | E15: 41.04 | F15: =D15*22 -> 150.48 | G15: =SUM(F15*C15) -> 902.88 | H15: N/A | I15: 403.04 | J15: =L15-K15 -> 180.22008 | K15: =(F15/$G$92)*Costs!$B$23 -> 222.5577 | L15: =N15/1.08 -> 402.77778 | M15: =L15*0.08 -> 32.222222 | N15: 435 | O15: =Table1[[#This Row],[Total Selling Price / Unit (MVR)]]*Table1[[#This Row],[Qty (NOS)]] -> 2610 | Q15: 21.36 | R15: =Q15*22 -> 469.92 | S15: N/A | T15: 22.16 | U15: 6.84 | V15: 150.48 | W15: 403.04 | X15: 435 | Y15: =T15*15.42 -> 341.7072 | Z15: =Y15*1.08 -> 369.04378 | AA15: =C15*Z15 -> 2214.2627 | AB15: =(T15+9)*15.42 -> 480.4872 | AC15: =AB15*1.08 -> 518.92618 | AD15: =C15*AC15 -> 3113.5571 | AE15: =T15*22 -> 487.52 | AF15: =AE15*1.08 -> 526.5216 | AG15: =C15*AF15 -> 3159.1296 | AH15: =(T15+9)*22 -> 685.52 | AI15: =AH15*1.08 -> 740.3616 | AJ15: =C15*AI15 -> 4442.1696 | AK15: =Table1[[#This Row],[Total Selling Price / Unit (MVR)]]/Table1[[#This Row],[CNF / Unit (MVR)]] -> 2.8907496 | AL15: =Table1[[#This Row],[Total Selling Price / Unit (MVR)]]-(Table1[[#This Row],[GST 8% (MVR)]]+Table1[[#This Row],[Weighted max expense (MVR)]]) -> 180.22008 | AM15: =Table1[[#This Row],[Profit / Unit (MVR)]]*Table1[[#This Row],[Qty (NOS)]] -> 1081.3205
A16: Retinol Bubble Chewy Foam 200ml | B16: Cleansing & Peeling | C16: 4 | D16: 7.06 | E16: 28.24 | F16: =D16*22 -> 155.32 | G16: =SUM(F16*C16) -> 621.28 | H16: 487.52 | I16: 322.74 | J16: =L16-K16 -> 140.65438 | K16: =(F16/$G$92)*Costs!$B$23 -> 229.71599 | L16: =N16/1.08 -> 370.37037 | M16: =L16*0.08 -> 29.62963 | N16: 400 | O16: =Table1[[#This Row],[Total Selling Price / Unit (MVR)]]*Table1[[#This Row],[Qty (NOS)]] -> 1600 | Q16: 21.36 | R16: =Q16*22 -> 469.92 | S16: 487.52 | T16: 22.16 | U16: 7.06 | V16: 155.32 | W16: 322.74 | X16: 400 | Y16: =T16*15.42 -> 341.7072 | Z16: =Y16*1.08 -> 369.04378 | AA16: =C16*Z16 -> 1476.1751 | AB16: =(T16+9)*15.42 -> 480.4872 | AC16: =AB16*1.08 -> 518.92618 | AD16: =C16*AC16 -> 2075.7047 | AE16: =T16*22 -> 487.52 | AF16: =AE16*1.08 -> 526.5216 | AG16: =C16*AF16 -> 2106.0864 | AH16: =(T16+9)*22 -> 685.52 | AI16: =AH16*1.08 -> 740.3616 | AJ16: =C16*AI16 -> 2961.4464 | AK16: =Table1[[#This Row],[Total Selling Price / Unit (MVR)]]/Table1[[#This Row],[CNF / Unit (MVR)]] -> 2.5753284 | AL16: =Table1[[#This Row],[Total Selling Price / Unit (MVR)]]-(Table1[[#This Row],[GST 8% (MVR)]]+Table1[[#This Row],[Weighted max expense (MVR)]]) -> 140.65438 | AM16: =Table1[[#This Row],[Profit / Unit (MVR)]]*Table1[[#This Row],[Qty (NOS)]] -> 562.61753
A17: Soybean Clay 2in1 Pack Foam 120ml | B17: Cleansing & Peeling | C17: 4 | D17: 4.24 | E17: 16.96 | F17: =D17*22 -> 93.28 | G17: =SUM(F17*C17) -> 373.12 | H17: 407.66 | I17: 162.36 | J17: =L17-K17 -> 186.11433 | K17: =(F17/$G$92)*Costs!$B$23 -> 137.95974 | L17: =N17/1.08 -> 324.07407 | M17: =L17*0.08 -> 25.925926 | N17: 350 | O17: =Table1[[#This Row],[Total Selling Price / Unit (MVR)]]*Table1[[#This Row],[Qty (NOS)]] -> 1400 | Q17: 17.86 | R17: =Q17*22 -> 392.92 | S17: 407.66 | T17: 18.53 | U17: 4.24 | V17: 93.28 | W17: 162.36 | X17: 350 | Y17: =T17*15.42 -> 285.7326 | Z17: =Y17*1.08 -> 308.59121 | AA17: =C17*Z17 -> 1234.3648 | AB17: =(T17+9)*15.42 -> 424.5126 | AC17: =AB17*1.08 -> 458.47361 | AD17: =C17*AC17 -> 1833.8944 | AE17: =T17*22 -> 407.66 | AF17: =AE17*1.08 -> 440.2728 | AG17: =C17*AF17 -> 1761.0912 | AH17: =(T17+9)*22 -> 605.66 | AI17: =AH17*1.08 -> 654.1128 | AJ17: =C17*AI17 -> 2616.4512 | AK17: =Table1[[#This Row],[Total Selling Price / Unit (MVR)]]/Table1[[#This Row],[CNF / Unit (MVR)]] -> 3.7521441 | AL17: =Table1[[#This Row],[Total Selling Price / Unit (MVR)]]-(Table1[[#This Row],[GST 8% (MVR)]]+Table1[[#This Row],[Weighted max expense (MVR)]]) -> 186.11433 | AM17: =Table1[[#This Row],[Profit / Unit (MVR)]]*Table1[[#This Row],[Qty (NOS)]] -> 744.45732
A18: Ssook/Mugwort Clay 2in1 Pack Foam 120ml | B18: Cleansing & Peeling | C18: 4 | D18: 4.24 | E18: 16.96 | F18: =D18*22 -> 93.28 | G18: =SUM(F18*C18) -> 373.12 | H18: 407.66 | I18: 162.36 | J18: =L18-K18 -> 186.11433 | K18: =(F18/$G$92)*Costs!$B$23 -> 137.95974 | L18: =N18/1.08 -> 324.07407 | M18: =L18*0.08 -> 25.925926 | N18: 350 | O18: =Table1[[#This Row],[Total Selling Price / Unit (MVR)]]*Table1[[#This Row],[Qty (NOS)]] -> 1400 | Q18: 17.86 | R18: =Q18*22 -> 392.92 | S18: 407.66 | T18: 18.53 | U18: 4.24 | V18: 93.28 | W18: 162.36 | X18: 350 | Y18: =T18*15.42 -> 285.7326 | Z18: =Y18*1.08 -> 308.59121 | AA18: =C18*Z18 -> 1234.3648 | AB18: =(T18+9)*15.42 -> 424.5126 | AC18: =AB18*1.08 -> 458.47361 | AD18: =C18*AC18 -> 1833.8944 | AE18: =T18*22 -> 407.66 | AF18: =AE18*1.08 -> 440.2728 | AG18: =C18*AF18 -> 1761.0912 | AH18: =(T18+9)*22 -> 605.66 | AI18: =AH18*1.08 -> 654.1128 | AJ18: =C18*AI18 -> 2616.4512 | AK18: =Table1[[#This Row],[Total Selling Price / Unit (MVR)]]/Table1[[#This Row],[CNF / Unit (MVR)]] -> 3.7521441 | AL18: =Table1[[#This Row],[Total Selling Price / Unit (MVR)]]-(Table1[[#This Row],[GST 8% (MVR)]]+Table1[[#This Row],[Weighted max expense (MVR)]]) -> 186.11433 | AM18: =Table1[[#This Row],[Profit / Unit (MVR)]]*Table1[[#This Row],[Qty (NOS)]] -> 744.45732
A19: Vitamin C + Turmeric Bubble Chewy Foam 200ml | B19: Cleansing & Peeling | C19: 4 | D19: 7.06 | E19: 28.24 | F19: =D19*22 -> 155.32 | G19: =SUM(F19*C19) -> 621.28 | H19: 487.52 | I19: 322.74 | J19: =L19-K19 -> 140.65438 | K19: =(F19/$G$92)*Costs!$B$23 -> 229.71599 | L19: =N19/1.08 -> 370.37037 | M19: =L19*0.08 -> 29.62963 | N19: 400 | O19: =Table1[[#This Row],[Total Selling Price / Unit (MVR)]]*Table1[[#This Row],[Qty (NOS)]] -> 1600 | Q19: 21.36 | R19: =Q19*22 -> 469.92 | S19: 487.52 | T19: 22.16 | U19: 7.06 | V19: 155.32 | W19: 322.74 | X19: 400 | Y19: =T19*15.42 -> 341.7072 | Z19: =Y19*1.08 -> 369.04378 | AA19: =C19*Z19 -> 1476.1751 | AB19: =(T19+9)*15.42 -> 480.4872 | AC19: =AB19*1.08 -> 518.92618 | AD19: =C19*AC19 -> 2075.7047 | AE19: =T19*22 -> 487.52 | AF19: =AE19*1.08 -> 526.5216 | AG19: =C19*AF19 -> 2106.0864 | AH19: =(T19+9)*22 -> 685.52 | AI19: =AH19*1.08 -> 740.3616 | AJ19: =C19*AI19 -> 2961.4464 | AK19: =Table1[[#This Row],[Total Selling Price / Unit (MVR)]]/Table1[[#This Row],[CNF / Unit (MVR)]] -> 2.5753284 | AL19: =Table1[[#This Row],[Total Selling Price / Unit (MVR)]]-(Table1[[#This Row],[GST 8% (MVR)]]+Table1[[#This Row],[Weighted max expense (MVR)]]) -> 140.65438 | AM19: =Table1[[#This Row],[Profit / Unit (MVR)]]*Table1[[#This Row],[Qty (NOS)]] -> 562.61753
A20: Collagen + Green Tea Moisture Cream 70ml | B20: Creams & Moisturizers | C20: 4 | D20: 4.57 | E20: 18.28 | F20: =D20*22 -> 100.54 | G20: =SUM(F20*C20) -> 402.16 | H20: 407.66 | I20: 275 | J20: =L20-K20 -> 156.85838 | K20: =(F20/$G$92)*Costs!$B$23 -> 148.69718 | L20: =N20/1.08 -> 305.55556 | M20: =L20*0.08 -> 24.444444 | N20: 330 | O20: =Table1[[#This Row],[Total Selling Price / Unit (MVR)]]*Table1[[#This Row],[Qty (NOS)]] -> 1320 | Q20: 7.14 | R20: =Q20*22 -> 157.08 | S20: 407.66 | T20: 18.53 | U20: 4.57 | V20: 100.54 | W20: 275 | X20: 330 | Y20: =T20*15.42 -> 285.7326 | Z20: =Y20*1.08 -> 308.59121 | AA20: =C20*Z20 -> 1234.3648 | AB20: =(T20+9)*15.42 -> 424.5126 | AC20: =AB20*1.08 -> 458.47361 | AD20: =C20*AC20 -> 1833.8944 | AE20: =T20*22 -> 407.66 | AF20: =AE20*1.08 -> 440.2728 | AG20: =C20*AF20 -> 1761.0912 | AH20: =(T20+9)*22 -> 605.66 | AI20: =AH20*1.08 -> 654.1128 | AJ20: =C20*AI20 -> 2616.4512 | AK20: =Table1[[#This Row],[Total Selling Price / Unit (MVR)]]/Table1[[#This Row],[CNF / Unit (MVR)]] -> 3.2822757 | AL20: =Table1[[#This Row],[Total Selling Price / Unit (MVR)]]-(Table1[[#This Row],[GST 8% (MVR)]]+Table1[[#This Row],[Weighted max expense (MVR)]]) -> 156.85838 | AM20: =Table1[[#This Row],[Profit / Unit (MVR)]]*Table1[[#This Row],[Qty (NOS)]] -> 627.43352
A21: Dr. AQUA CURE CREAM 70ml | B21: Creams & Moisturizers | C21: 4 | D21: 4.66 | E21: 18.64 | F21: =D21*22 -> 102.52 | G21: =SUM(F21*C21) -> 410.08 | H21: 211.86 | I21: 242.44 | J21: =L21-K21 -> 56.707767 | K21: =(F21/$G$92)*Costs!$B$23 -> 151.62557 | L21: =N21/1.08 -> 208.33333 | M21: =L21*0.08 -> 16.666667 | N21: 225 | O21: =Table1[[#This Row],[Total Selling Price / Unit (MVR)]]*Table1[[#This Row],[Qty (NOS)]] -> 900 | Q21: 17.86 | R21: =Q21*22 -> 392.92 | S21: 211.86 | T21: 9.63 | U21: 4.66 | V21: 102.52 | W21: 242.44 | X21: 225 | Y21: =T21*15.42 -> 148.4946 | Z21: =Y21*1.08 -> 160.37417 | AA21: =C21*Z21 -> 641.49667 | AB21: =(T21+9)*15.42 -> 287.2746 | AC21: =AB21*1.08 -> 310.25657 | AD21: =C21*AC21 -> 1241.0263 | AE21: =T21*22 -> 211.86 | AF21: =AE21*1.08 -> 228.8088 | AG21: =C21*AF21 -> 915.2352 | AH21: =(T21+9)*22 -> 409.86 | AI21: =AH21*1.08 -> 442.6488 | AJ21: =C21*AI21 -> 1770.5952 | AK21: =Table1[[#This Row],[Total Selling Price / Unit (MVR)]]/Table1[[#This Row],[CNF / Unit (MVR)]] -> 2.1946937 | AL21: =Table1[[#This Row],[Total Selling Price / Unit (MVR)]]-(Table1[[#This Row],[GST 8% (MVR)]]+Table1[[#This Row],[Weighted max expense (MVR)]]) -> 56.707767 | AM21: =Table1[[#This Row],[Profit / Unit (MVR)]]*Table1[[#This Row],[Qty (NOS)]] -> 226.83107
A22: Dr. Madecassoside Cure Cream 70ml | B22: Creams & Moisturizers | C22: 7 | D22: 4.66 | E22: 32.62 | F22: =D22*22 -> 102.52 | G22: =SUM(F22*C22) -> 717.64 | H22: 211.86 | I22: 242.44 | J22: =L22-K22 -> 56.707767 | K22: =(F22/$G$92)*Costs!$B$23 -> 151.62557 | L22: =N22/1.08 -> 208.33333 | M22: =L22*0.08 -> 16.666667 | N22: 225 | O22: =Table1[[#This Row],[Total Selling Price / Unit (MVR)]]*Table1[[#This Row],[Qty (NOS)]] -> 1575 | Q22: 17.86 | R22: =Q22*22 -> 392.92 | S22: 211.86 | T22: 9.63 | U22: 4.66 | V22: 102.52 | W22: 242.44 | X22: 225 | Y22: =T22*15.42 -> 148.4946 | Z22: =Y22*1.08 -> 160.37417 | AA22: =C22*Z22 -> 1122.6192 | AB22: =(T22+9)*15.42 -> 287.2746 | AC22: =AB22*1.08 -> 310.25657 | AD22: =C22*AC22 -> 2171.796 | AE22: =T22*22 -> 211.86 | AF22: =AE22*1.08 -> 228.8088 | AG22: =C22*AF22 -> 1601.6616 | AH22: =(T22+9)*22 -> 409.86 | AI22: =AH22*1.08 -> 442.6488 | AJ22: =C22*AI22 -> 3098.5416 | AK22: =Table1[[#This Row],[Total Selling Price / Unit (MVR)]]/Table1[[#This Row],[CNF / Unit (MVR)]] -> 2.1946937 | AL22: =Table1[[#This Row],[Total Selling Price / Unit (MVR)]]-(Table1[[#This Row],[GST 8% (MVR)]]+Table1[[#This Row],[Weighted max expense (MVR)]]) -> 56.707767 | AM22: =Table1[[#This Row],[Profit / Unit (MVR)]]*Table1[[#This Row],[Qty (NOS)]] -> 396.95437
A23: Dr. Peptide Cure Cream 70ml | B23: Creams & Moisturizers | C23: 4 | D23: 4.66 | E23: 18.64 | F23: =D23*22 -> 102.52 | G23: =SUM(F23*C23) -> 410.08 | H23: 211.86 | I23: 242.44 | J23: =L23-K23 -> 56.707767 | K23: =(F23/$G$92)*Costs!$B$23 -> 151.62557 | L23: =N23/1.08 -> 208.33333 | M23: =L23*0.08 -> 16.666667 | N23: 225 | O23: =Table1[[#This Row],[Total Selling Price / Unit (MVR)]]*Table1[[#This Row],[Qty (NOS)]] -> 900 | Q23: 17.86 | R23: =Q23*22 -> 392.92 | S23: 211.86 | T23: 9.63 | U23: 4.66 | V23: 102.52 | W23: 242.44 | X23: 225 | Y23: =T23*15.42 -> 148.4946 | Z23: =Y23*1.08 -> 160.37417 | AA23: =C23*Z23 -> 641.49667 | AB23: =(T23+9)*15.42 -> 287.2746 | AC23: =AB23*1.08 -> 310.25657 | AD23: =C23*AC23 -> 1241.0263 | AE23: =T23*22 -> 211.86 | AF23: =AE23*1.08 -> 228.8088 | AG23: =C23*AF23 -> 915.2352 | AH23: =(T23+9)*22 -> 409.86 | AI23: =AH23*1.08 -> 442.6488 | AJ23: =C23*AI23 -> 1770.5952 | AK23: =Table1[[#This Row],[Total Selling Price / Unit (MVR)]]/Table1[[#This Row],[CNF / Unit (MVR)]] -> 2.1946937 | AL23: =Table1[[#This Row],[Total Selling Price / Unit (MVR)]]-(Table1[[#This Row],[GST 8% (MVR)]]+Table1[[#This Row],[Weighted max expense (MVR)]]) -> 56.707767 | AM23: =Table1[[#This Row],[Profit / Unit (MVR)]]*Table1[[#This Row],[Qty (NOS)]] -> 226.83107
A24: Dr. Vitamin C Cure Cream 70ml | B24: Creams & Moisturizers | C24: 4 | D24: 4.66 | E24: 18.64 | F24: =D24*22 -> 102.52 | G24: =SUM(F24*C24) -> 410.08 | H24: 211.86 | I24: 242.44 | J24: =L24-K24 -> 56.707767 | K24: =(F24/$G$92)*Costs!$B$23 -> 151.62557 | L24: =N24/1.08 -> 208.33333 | M24: =L24*0.08 -> 16.666667 | N24: 225 | O24: =Table1[[#This Row],[Total Selling Price / Unit (MVR)]]*Table1[[#This Row],[Qty (NOS)]] -> 900 | Q24: 17.86 | R24: =Q24*22 -> 392.92 | S24: 211.86 | T24: 9.63 | U24: 4.66 | V24: 102.52 | W24: 242.44 | X24: 225 | Y24: =T24*15.42 -> 148.4946 | Z24: =Y24*1.08 -> 160.37417 | AA24: =C24*Z24 -> 641.49667 | AB24: =(T24+9)*15.42 -> 287.2746 | AC24: =AB24*1.08 -> 310.25657 | AD24: =C24*AC24 -> 1241.0263 | AE24: =T24*22 -> 211.86 | AF24: =AE24*1.08 -> 228.8088 | AG24: =C24*AF24 -> 915.2352 | AH24: =(T24+9)*22 -> 409.86 | AI24: =AH24*1.08 -> 442.6488 | AJ24: =C24*AI24 -> 1770.5952 | AK24: =Table1[[#This Row],[Total Selling Price / Unit (MVR)]]/Table1[[#This Row],[CNF / Unit (MVR)]] -> 2.1946937 | AL24: =Table1[[#This Row],[Total Selling Price / Unit (MVR)]]-(Table1[[#This Row],[GST 8% (MVR)]]+Table1[[#This Row],[Weighted max expense (MVR)]]) -> 56.707767 | AM24: =Table1[[#This Row],[Profit / Unit (MVR)]]*Table1[[#This Row],[Qty (NOS)]] -> 226.83107
A25: Gold Caviar Ampoule Cream 70ml | B25: Creams & Moisturizers | C25: 3 | D25: 4.82 | E25: 14.46 | F25: =D25*22 -> 106.04 | G25: =SUM(F25*C25) -> 318.12 | H25: 407.66 | I25: 272.8 | J25: =L25-K25 -> 167.24248 | K25: =(F25/$G$92)*Costs!$B$23 -> 156.83159 | L25: =N25/1.08 -> 324.07407 | M25: =L25*0.08 -> 25.925926 | N25: 350 | O25: =Table1[[#This Row],[Total Selling Price / Unit (MVR)]]*Table1[[#This Row],[Qty (NOS)]] -> 1050 | Q25: 17.86 | R25: =Q25*22 -> 392.92 | S25: 407.66 | T25: 18.53 | U25: 4.82 | V25: 106.04 | W25: 272.8 | X25: 350 | Y25: =T25*15.42 -> 285.7326 | Z25: =Y25*1.08 -> 308.59121 | AA25: =C25*Z25 -> 925.77362 | AB25: =(T25+9)*15.42 -> 424.5126 | AC25: =AB25*1.08 -> 458.47361 | AD25: =C25*AC25 -> 1375.4208 | AE25: =T25*22 -> 407.66 | AF25: =AE25*1.08 -> 440.2728 | AG25: =C25*AF25 -> 1320.8184 | AH25: =(T25+9)*22 -> 605.66 | AI25: =AH25*1.08 -> 654.1128 | AJ25: =C25*AI25 -> 1962.3384 | AK25: =Table1[[#This Row],[Total Selling Price / Unit (MVR)]]/Table1[[#This Row],[CNF / Unit (MVR)]] -> 3.3006413 | AL25: =Table1[[#This Row],[Total Selling Price / Unit (MVR)]]-(Table1[[#This Row],[GST 8% (MVR)]]+Table1[[#This Row],[Weighted max expense (MVR)]]) -> 167.24248 | AM25: =Table1[[#This Row],[Profit / Unit (MVR)]]*Table1[[#This Row],[Qty (NOS)]] -> 501.72744
A26: Real Sensation Blemish Cream 55g | B26: Creams & Moisturizers | C26: 4 | D26: 11 | E26: 44 | F26: =D26*22 -> 242 | G26: =SUM(F26*C26) -> 968 | H26: 1613.92 | I26: 436.48 | J26: =L26-K26 -> 86.530016 | K26: =(F26/$G$92)*Costs!$B$23 -> 357.91443 | L26: =N26/1.08 -> 444.44444 | M26: =L26*0.08 -> 35.555556 | N26: 480 | O26: =Table1[[#This Row],[Total Selling Price / Unit (MVR)]]*Table1[[#This Row],[Qty (NOS)]] -> 1920 | Q26: 70.71 | R26: =Q26*22 -> 1555.62 | S26: 1613.92 | T26: 73.36 | U26: 11 | V26: 242 | W26: 436.48 | X26: 480 | Y26: =T26*15.42 -> 1131.2112 | Z26: =Y26*1.08 -> 1221.7081 | AA26: =C26*Z26 -> 4886.8324 | AB26: =(T26+9)*15.42 -> 1269.9912 | AC26: =AB26*1.08 -> 1371.5905 | AD26: =C26*AC26 -> 5486.362 | AE26: =T26*22 -> 1613.92 | AF26: =AE26*1.08 -> 1743.0336 | AG26: =C26*AF26 -> 6972.1344 | AH26: =(T26+9)*22 -> 1811.92 | AI26: =AH26*1.08 -> 1956.8736 | AJ26: =C26*AI26 -> 7827.4944 | AK26: =Table1[[#This Row],[Total Selling Price / Unit (MVR)]]/Table1[[#This Row],[CNF / Unit (MVR)]] -> 1.9834711 | AL26: =Table1[[#This Row],[Total Selling Price / Unit (MVR)]]-(Table1[[#This Row],[GST 8% (MVR)]]+Table1[[#This Row],[Weighted max expense (MVR)]]) -> 86.530016 | AM26: =Table1[[#This Row],[Profit / Unit (MVR)]]*Table1[[#This Row],[Qty (NOS)]] -> 346.12007
A27: Real Sensation Pore Cream 55g | B27: Creams & Moisturizers | C27: 4 | D27: 11 | E27: 44 | F27: =D27*22 -> 242 | G27: =SUM(F27*C27) -> 968 | H27: 1613.92 | I27: 436.48 | J27: =L27-K27 -> 86.530016 | K27: =(F27/$G$92)*Costs!$B$23 -> 357.91443 | L27: =N27/1.08 -> 444.44444 | M27: =L27*0.08 -> 35.555556 | N27: 480 | O27: =Table1[[#This Row],[Total Selling Price / Unit (MVR)]]*Table1[[#This Row],[Qty (NOS)]] -> 1920 | Q27: 70.71 | R27: =Q27*22 -> 1555.62 | S27: 1613.92 | T27: 73.36 | U27: 11 | V27: 242 | W27: 436.48 | X27: 480 | Y27: =T27*15.42 -> 1131.2112 | Z27: =Y27*1.08 -> 1221.7081 | AA27: =C27*Z27 -> 4886.8324 | AB27: =(T27+9)*15.42 -> 1269.9912 | AC27: =AB27*1.08 -> 1371.5905 | AD27: =C27*AC27 -> 5486.362 | AE27: =T27*22 -> 1613.92 | AF27: =AE27*1.08 -> 1743.0336 | AG27: =C27*AF27 -> 6972.1344 | AH27: =(T27+9)*22 -> 1811.92 | AI27: =AH27*1.08 -> 1956.8736 | AJ27: =C27*AI27 -> 7827.4944 | AK27: =Table1[[#This Row],[Total Selling Price / Unit (MVR)]]/Table1[[#This Row],[CNF / Unit (MVR)]] -> 1.9834711 | AL27: =Table1[[#This Row],[Total Selling Price / Unit (MVR)]]-(Table1[[#This Row],[GST 8% (MVR)]]+Table1[[#This Row],[Weighted max expense (MVR)]]) -> 86.530016 | AM27: =Table1[[#This Row],[Profit / Unit (MVR)]]*Table1[[#This Row],[Qty (NOS)]] -> 346.12007
... A29: Wrinkle Collagen Ampoule Cream 70ml | B29: Creams & Moisturizers | C29: 4 | D29: 4.82 | E29: 19.28 | F29: =D29*22 -> 106.04 | G29: =SUM(F29*C29) -> 424.16 | H29: 407.66 | I29: 272.8 | J29: =L29-K29 -> 157.98322 | K29: =(F29/$G$92)*Costs!$B$23 -> 156.83159 | L29: =N29/1.08 -> 314.81481 | M29: =L29*0.08 -> 25.185185 | N29: 340 | O29: =Table1[[#This Row],[Total Selling Price / Unit (MVR)]]*Table1[[#This Row],[Qty (NOS)]] -> 1360 | Q29: 17.86 | R29: =Q29*22 -> 392.92 | S29: 407.66 | T29: 18.53 | U29: 4.82 | V29: 106.04 | W29: 272.8 | X29: 340 | Y29: =T29*15.42 -> 285.7326 | Z29: =Y29*1.08 -> 308.59121 | AA29: =C29*Z29 -> 1234.3648 | AB29: =(T29+9)*15.42 -> 424.5126 | AC29: =AB29*1.08 -> 458.47361 | AD29: =C29*AC29 -> 1833.8944 | AE29: =T29*22 -> 407.66 | AF29: =AE29*1.08 -> 440.2728 | AG29: =C29*AF29 -> 1761.0912 | AH29: =(T29+9)*22 -> 605.66 | AI29: =AH29*1.08 -> 654.1128 | AJ29: =C29*AI29 -> 2616.4512 | AK29: =Table1[[#This Row],[Total Selling Price / Unit (MVR)]]/Table1[[#This Row],[CNF / Unit (MVR)]] -> 3.2063372 | AL29: =Table1[[#This Row],[Total Selling Price / Unit (MVR)]]-(Table1[[#This Row],[GST 8% (MVR)]]+Table1[[#This Row],[Weighted max expense (MVR)]]) -> 157.98322 | AM29: =Table1[[#This Row],[Profit / Unit (MVR)]]*Table1[[#This Row],[Qty (NOS)]] -> 631.93288
A30: YUJA DERMA CREAM 50ml | B30: Creams & Moisturizers | C30: 4 | D30: 5.84 | E30: 23.36 | F30: =D30*22 -> 128.48 | G30: =SUM(F30*C30) -> 513.92 | H30: N/A | I30: 240.68 | J30: =L30-K30 -> 32.202199 | K30: =(F30/$G$92)*Costs!$B$23 -> 190.02002 | L30: =N30/1.08 -> 222.22222 | M30: =L30*0.08 -> 17.777778 | N30: 240 | O30: =Table1[[#This Row],[Total Selling Price / Unit (MVR)]]*Table1[[#This Row],[Qty (NOS)]] -> 960 | Q30: 55.71 | R30: =Q30*22 -> 1225.62 | S30: N/A | T30: 57.8 | U30: 5.84 | V30: 128.48 | W30: 240.68 | X30: 240 | Y30: =T30*15.42 -> 891.276 | Z30: =Y30*1.08 -> 962.57808 | AA30: =C30*Z30 -> 3850.3123 | AB30: =(T30+9)*15.42 -> 1030.056 | AC30: =AB30*1.08 -> 1112.4605 | AD30: =C30*AC30 -> 4449.8419 | AE30: =T30*22 -> 1271.6 | AF30: =AE30*1.08 -> 1373.328 | AG30: =C30*AF30 -> 5493.312 | AH30: =(T30+9)*22 -> 1469.6 | AI30: =AH30*1.08 -> 1587.168 | AJ30: =C30*AI30 -> 6348.672 | AK30: =Table1[[#This Row],[Total Selling Price / Unit (MVR)]]/Table1[[#This Row],[CNF / Unit (MVR)]] -> 1.867995 | AL30: =Table1[[#This Row],[Total Selling Price / Unit (MVR)]]-(Table1[[#This Row],[GST 8% (MVR)]]+Table1[[#This Row],[Weighted max expense (MVR)]]) -> 32.202199 | AM30: =Table1[[#This Row],[Profit / Unit (MVR)]]*Table1[[#This Row],[Qty (NOS)]] -> 128.80879
A31: YUJA DERMA CREAM 50ml | B31: Creams & Moisturizers | C31: 4 | D31: 5.84 | E31: 23.36 | F31: =D31*22 -> 128.48 | G31: =SUM(F31*C31) -> 513.92 | H31: N/A | I31: 240.68 | J31: =L31-K31 -> 32.202199 | K31: =(F31/$G$92)*Costs!$B$23 -> 190.02002 | L31: =N31/1.08 -> 222.22222 | M31: =L31*0.08 -> 17.777778 | N31: 240 | O31: =Table1[[#This Row],[Total Selling Price / Unit (MVR)]]*Table1[[#This Row],[Qty (NOS)]] -> 960 | Q31: 55.71 | R31: =Q31*22 -> 1225.62 | S31: N/A | T31: 57.8 | U31: 5.84 | V31: 128.48 | W31: 240.68 | X31: 240 | Y31: =T31*15.42 -> 891.276 | Z31: =Y31*1.08 -> 962.57808 | AA31: =C31*Z31 -> 3850.3123 | AB31: =(T31+9)*15.42 -> 1030.056 | AC31: =AB31*1.08 -> 1112.4605 | AD31: =C31*AC31 -> 4449.8419 | AE31: =T31*22 -> 1271.6 | AF31: =AE31*1.08 -> 1373.328 | AG31: =C31*AF31 -> 5493.312 | AH31: =(T31+9)*22 -> 1469.6 | AI31: =AH31*1.08 -> 1587.168 | AJ31: =C31*AI31 -> 6348.672 | AK31: =Table1[[#This Row],[Total Selling Price / Unit (MVR)]]/Table1[[#This Row],[CNF / Unit (MVR)]] -> 1.867995 | AL31: =Table1[[#This Row],[Total Selling Price / Unit (MVR)]]-(Table1[[#This Row],[GST 8% (MVR)]]+Table1[[#This Row],[Weighted max expense (MVR)]]) -> 32.202199 | AM31: =Table1[[#This Row],[Profit / Unit (MVR)]]*Table1[[#This Row],[Qty (NOS)]] -> 128.80879
A32: Black Snail Eye Cream EX 40ml | B32: Eye Care | C32: 4 | D32: 1.96 | E32: 7.84 | F32: =D32*22 -> 43.12 | G32: =SUM(F32*C32) -> 172.48 | H32: 407.66 | I32: 134.42 | J32: =L32-K32 -> 241.78171 | K32: =(F32/$G$92)*Costs!$B$23 -> 63.773844 | L32: =N32/1.08 -> 305.55556 | M32: =L32*0.08 -> 24.444444 | N32: 330 | O32: =Table1[[#This Row],[Total Selling Price / Unit (MVR)]]*Table1[[#This Row],[Qty (NOS)]] -> 1320 | Q32: 17.86 | R32: =Q32*22 -> 392.92 | S32: 407.66 | T32: 18.53 | U32: 1.96 | V32: 43.12 | W32: 134.42 | X32: 330 | Y32: =T32*15.42 -> 285.7326 | Z32: =Y32*1.08 -> 308.59121 | AA32: =C32*Z32 -> 1234.3648 | AB32: =(T32+9)*15.42 -> 424.5126 | AC32: =AB32*1.08 -> 458.47361 | AD32: =C32*AC32 -> 1833.8944 | AE32: =T32*22 -> 407.66 | AF32: =AE32*1.08 -> 440.2728 | AG32: =C32*AF32 -> 1761.0912 | AH32: =(T32+9)*22 -> 605.66 | AI32: =AH32*1.08 -> 654.1128 | AJ32: =C32*AI32 -> 2616.4512 | AK32: =Table1[[#This Row],[Total Selling Price / Unit (MVR)]]/Table1[[#This Row],[CNF / Unit (MVR)]] -> 7.6530612 | AL32: =Table1[[#This Row],[Total Selling Price / Unit (MVR)]]-(Table1[[#This Row],[GST 8% (MVR)]]+Table1[[#This Row],[Weighted max expense (MVR)]]) -> 241.78171 | AM32: =Table1[[#This Row],[Profit / Unit (MVR)]]*Table1[[#This Row],[Qty (NOS)]] -> 967.12685
A33: Collagen Hydrogel Eye Patch 90g / 60 sheets | B33: Eye Care | C33: 4 | D33: 6.33 | E33: 25.32 | F33: =D33*22 -> 139.26 | G33: =SUM(F33*C33) -> 557.04 | H33: 407.66 | I33: 298.1 | J33: =L33-K33 -> 71.814293 | K33: =(F33/$G$92)*Costs!$B$23 -> 205.96348 | L33: =N33/1.08 -> 277.77778 | M33: =L33*0.08 -> 22.222222 | N33: 300 | O33: =Table1[[#This Row],[Total Selling Price / Unit (MVR)]]*Table1[[#This Row],[Qty (NOS)]] -> 1200 | Q33: 17.86 | R33: =Q33*22 -> 392.92 | S33: 407.66 | T33: 18.53 | U33: 6.33 | V33: 139.26 | W33: 298.1 | X33: 300 | Y33: =T33*15.42 -> 285.7326 | Z33: =Y33*1.08 -> 308.59121 | AA33: =C33*Z33 -> 1234.3648 | AB33: =(T33+9)*15.42 -> 424.5126 | AC33: =AB33*1.08 -> 458.47361 | AD33: =C33*AC33 -> 1833.8944 | AE33: =T33*22 -> 407.66 | AF33: =AE33*1.08 -> 440.2728 | AG33: =C33*AF33 -> 1761.0912 | AH33: =(T33+9)*22 -> 605.66 | AI33: =AH33*1.08 -> 654.1128 | AJ33: =C33*AI33 -> 2616.4512 | AK33: =Table1[[#This Row],[Total Selling Price / Unit (MVR)]]/Table1[[#This Row],[CNF / Unit (MVR)]] -> 2.1542439 | AL33: =Table1[[#This Row],[Total Selling Price / Unit (MVR)]]-(Table1[[#This Row],[GST 8% (MVR)]]+Table1[[#This Row],[Weighted max expense (MVR)]]) -> 71.814293 | AM33: =Table1[[#This Row],[Profit / Unit (MVR)]]*Table1[[#This Row],[Qty (NOS)]] -> 287.25717
A34: Heeyul 24K Gold Eye Cream 40ml | B34: Eye Care | C34: 4 | D34: 1.96 | E34: 7.84 | F34: =D34*22 -> 43.12 | G34: =SUM(F34*C34) -> 172.48 | H34: 407.66 | I34: 300 | J34: =L34-K34 -> 241.78171 | K34: =(F34/$G$92)*Costs!$B$23 -> 63.773844 | L34: =N34/1.08 -> 305.55556 | M34: =L34*0.08 -> 24.444444 | N34: 330 | O34: =Table1[[#This Row],[Total Selling Price / Unit (MVR)]]*Table1[[#This Row],[Qty (NOS)]] -> 1320 | Q34: 17.86 | R34: =Q34*22 -> 392.92 | S34: 407.66 | T34: 18.53 | U34: 1.96 | V34: 43.12 | W34: 300 | X34: 330 | Y34: =T34*15.42 -> 285.7326 | Z34: =Y34*1.08 -> 308.59121 | AA34: =C34*Z34 -> 1234.3648 | AB34: =(T34+9)*15.42 -> 424.5126 | AC34: =AB34*1.08 -> 458.47361 | AD34: =C34*AC34 -> 1833.8944 | AE34: =T34*22 -> 407.66 | AF34: =AE34*1.08 -> 440.2728 | AG34: =C34*AF34 -> 1761.0912 | AH34: =(T34+9)*22 -> 605.66 | AI34: =AH34*1.08 -> 654.1128 | AJ34: =C34*AI34 -> 2616.4512 | AK34: =Table1[[#This Row],[Total Selling Price / Unit (MVR)]]/Table1[[#This Row],[CNF / Unit (MVR)]] -> 7.6530612 | AL34: =Table1[[#This Row],[Total Selling Price / Unit (MVR)]]-(Table1[[#This Row],[GST 8% (MVR)]]+Table1[[#This Row],[Weighted max expense (MVR)]]) -> 241.78171 | AM34: =Table1[[#This Row],[Profit / Unit (MVR)]]*Table1[[#This Row],[Qty (NOS)]] -> 967.12685
A35: Vitamin Hydrogel Eye Patch 90g / 60 sheets | B35: Eye Care | C35: 4 | D35: 6.33 | E35: 25.32 | F35: =D35*22 -> 139.26 | G35: =SUM(F35*C35) -> 557.04 | H35: N/A | I35: 298.1 | J35: =L35-K35 -> 71.814293 | K35: =(F35/$G$92)*Costs!$B$23 -> 205.96348 | L35: =N35/1.08 -> 277.77778 | M35: =L35*0.08 -> 22.222222 | N35: 300 | O35: =Table1[[#This Row],[Total Selling Price / Unit (MVR)]]*Table1[[#This Row],[Qty (NOS)]] -> 1200 | Q35: 17.86 | R35: =Q35*22 -> 392.92 | S35: N/A | T35: 18.53 | U35: 6.33 | V35: 139.26 | W35: 298.1 | X35: 300 | Y35: =T35*15.42 -> 285.7326 | Z35: =Y35*1.08 -> 308.59121 | AA35: =C35*Z35 -> 1234.3648 | AB35: =(T35+9)*15.42 -> 424.5126 | AC35: =AB35*1.08 -> 458.47361 | AD35: =C35*AC35 -> 1833.8944 | AE35: =T35*22 -> 407.66 | AF35: =AE35*1.08 -> 440.2728 | AG35: =C35*AF35 -> 1761.0912 | AH35: =(T35+9)*22 -> 605.66 | AI35: =AH35*1.08 -> 654.1128 | AJ35: =C35*AI35 -> 2616.4512 | AK35: =Table1[[#This Row],[Total Selling Price / Unit (MVR)]]/Table1[[#This Row],[CNF / Unit (MVR)]] -> 2.1542439 | AL35: =Table1[[#This Row],[Total Selling Price / Unit (MVR)]]-(Table1[[#This Row],[GST 8% (MVR)]]+Table1[[#This Row],[Weighted max expense (MVR)]]) -> 71.814293 | AM35: =Table1[[#This Row],[Profit / Unit (MVR)]]*Table1[[#This Row],[Qty (NOS)]] -> 287.25717
A36: The Glow Color Lip Balm #102 Smoothie Pink 3.6g | B36: Lips & Makeup | C36: 4 | D36: 3.34 | E36: 13.36 | F36: =D36*22 -> 73.48 | G36: =SUM(F36*C36) -> 293.92 | H36: N/A | I36: 125.84 | J36: =L36-K36 -> 67.250091 | K36: =(F36/$G$92)*Costs!$B$23 -> 108.67584 | L36: =N36/1.08 -> 175.92593 | M36: =L36*0.08 -> 14.074074 | N36: 190 | O36: =Table1[[#This Row],[Total Selling Price / Unit (MVR)]]*Table1[[#This Row],[Qty (NOS)]] -> 760 | Q36: 10.71 | R36: =Q36*22 -> 235.62 | S36: N/A | T36: 10 | U36: 3.34 | V36: 73.48 | W36: 125.84 | X36: 190 | Y36: =T36*15.42 -> 154.2 | Z36: =Y36*1.08 -> 166.536 | AA36: =C36*Z36 -> 666.144 | AB36: =(T36+9)*15.42 -> 292.98 | AC36: =AB36*1.08 -> 316.4184 | AD36: =C36*AC36 -> 1265.6736 | AE36: =T36*22 -> 220 | AF36: =AE36*1.08 -> 237.6 | AG36: =C36*AF36 -> 950.4 | AH36: =(T36+9)*22 -> 418 | AI36: =AH36*1.08 -> 451.44 | AJ36: =C36*AI36 -> 1805.76 | AK36: =Table1[[#This Row],[Total Selling Price / Unit (MVR)]]/Table1[[#This Row],[CNF / Unit (MVR)]] -> 2.5857376 | AL36: =Table1[[#This Row],[Total Selling Price / Unit (MVR)]]-(Table1[[#This Row],[GST 8% (MVR)]]+Table1[[#This Row],[Weighted max expense (MVR)]]) -> 67.250091 | AM36: =Table1[[#This Row],[Profit / Unit (MVR)]]*Table1[[#This Row],[Qty (NOS)]] -> 269.00036
A37: The Glow Color Lip Balm #103 Raspberry 3.6g | B37: Lips & Makeup | C37: 4 | D37: 3.34 | E37: 13.36 | F37: =D37*22 -> 73.48 | G37: =SUM(F37*C37) -> 293.92 | H37: N/A | I37: 125.84 | J37: =L37-K37 -> 67.250091 | K37: =(F37/$G$92)*Costs!$B$23 -> 108.67584 | L37: =N37/1.08 -> 175.92593 | M37: =L37*0.08 -> 14.074074 | N37: 190 | O37: =Table1[[#This Row],[Total Selling Price / Unit (MVR)]]*Table1[[#This Row],[Qty (NOS)]] -> 760 | Q37: 10.71 | R37: =Q37*22 -> 235.62 | S37: N/A | T37: 10 | U37: 3.34 | V37: 73.48 | W37: 125.84 | X37: 190 | Y37: =T37*15.42 -> 154.2 | Z37: =Y37*1.08 -> 166.536 | AA37: =C37*Z37 -> 666.144 | AB37: =(T37+9)*15.42 -> 292.98 | AC37: =AB37*1.08 -> 316.4184 | AD37: =C37*AC37 -> 1265.6736 | AE37: =T37*22 -> 220 | AF37: =AE37*1.08 -> 237.6 | AG37: =C37*AF37 -> 950.4 | AH37: =(T37+9)*22 -> 418 | AI37: =AH37*1.08 -> 451.44 | AJ37: =C37*AI37 -> 1805.76 | AK37: =Table1[[#This Row],[Total Selling Price / Unit (MVR)]]/Table1[[#This Row],[CNF / Unit (MVR)]] -> 2.5857376 | AL37: =Table1[[#This Row],[Total Selling Price / Unit (MVR)]]-(Table1[[#This Row],[GST 8% (MVR)]]+Table1[[#This Row],[Weighted max expense (MVR)]]) -> 67.250091 | AM37: =Table1[[#This Row],[Profit / Unit (MVR)]]*Table1[[#This Row],[Qty (NOS)]] -> 269.00036
A38: The Glow Color Lip Balm #104 Rosewood 3.6g | B38: Lips & Makeup | C38: 4 | D38: 3.34 | E38: 13.36 | F38: =D38*22 -> 73.48 | G38: =SUM(F38*C38) -> 293.92 | H38: N/A | I38: 125.84 | J38: =L38-K38 -> 67.250091 | K38: =(F38/$G$92)*Costs!$B$23 -> 108.67584 | L38: =N38/1.08 -> 175.92593 | M38: =L38*0.08 -> 14.074074 | N38: 190 | O38: =Table1[[#This Row],[Total Selling Price / Unit (MVR)]]*Table1[[#This Row],[Qty (NOS)]] -> 760 | Q38: 10.71 | R38: =Q38*22 -> 235.62 | S38: N/A | T38: 10 | U38: 3.34 | V38: 73.48 | W38: 125.84 | X38: 190 | Y38: =T38*15.42 -> 154.2 | Z38: =Y38*1.08 -> 166.536 | AA38: =C38*Z38 -> 666.144 | AB38: =(T38+9)*15.42 -> 292.98 | AC38: =AB38*1.08 -> 316.4184 | AD38: =C38*AC38 -> 1265.6736 | AE38: =T38*22 -> 220 | AF38: =AE38*1.08 -> 237.6 | AG38: =C38*AF38 -> 950.4 | AH38: =(T38+9)*22 -> 418 | AI38: =AH38*1.08 -> 451.44 | AJ38: =C38*AI38 -> 1805.76 | AK38: =Table1[[#This Row],[Total Selling Price / Unit (MVR)]]/Table1[[#This Row],[CNF / Unit (MVR)]] -> 2.5857376 | AL38: =Table1[[#This Row],[Total Selling Price / Unit (MVR)]]-(Table1[[#This Row],[GST 8% (MVR)]]+Table1[[#This Row],[Weighted max expense (MVR)]]) -> 67.250091 | AM38: =Table1[[#This Row],[Profit / Unit (MVR)]]*Table1[[#This Row],[Qty (NOS)]] -> 269.00036
A39: Aloe Solution Mask Pack 25g x 10pcs | B39: Mask Packs | C39: 4 | D39: 2.13 | E39: 8.52 | F39: =D39*22 -> 46.86 | G39: =SUM(F39*C39) -> 187.44 | H39: 440 | I39: 47.74 | J39: =L39-K39 -> 143.65771 | K39: =(F39/$G$92)*Costs!$B$23 -> 69.305248 | L39: =N39/1.08 -> 212.96296 | M39: =L39*0.08 -> 17.037037 | N39: 230 | O39: =Table1[[#This Row],[Total Selling Price / Unit (MVR)]]*Table1[[#This Row],[Qty (NOS)]] -> 920 | Q39: 7.14 | R39: =Q39*22 -> 157.08 | S39: 440 | T39: 20 | U39: 2.13 | V39: 46.86 | W39: 47.74 | X39: 230 | Y39: =T39*15.42 -> 308.4 | Z39: =Y39*1.08 -> 333.072 | AA39: =C39*Z39 -> 1332.288 | AB39: =(T39+9)*15.42 -> 447.18 | AC39: =AB39*1.08 -> 482.9544 | AD39: =C39*AC39 -> 1931.8176 | AE39: =T39*22 -> 440 | AF39: =AE39*1.08 -> 475.2 | AG39: =C39*AF39 -> 1900.8 | AH39: =(T39+9)*22 -> 638 | AI39: =AH39*1.08 -> 689.04 | AJ39: =C39*AI39 -> 2756.16 | AK39: =Table1[[#This Row],[Total Selling Price / Unit (MVR)]]/Table1[[#This Row],[CNF / Unit (MVR)]] -> 4.9082373 | AL39: =Table1[[#This Row],[Total Selling Price / Unit (MVR)]]-(Table1[[#This Row],[GST 8% (MVR)]]+Table1[[#This Row],[Weighted max expense (MVR)]]) -> 143.65771 | AM39: =Table1[[#This Row],[Profit / Unit (MVR)]]*Table1[[#This Row],[Qty (NOS)]] -> 574.63086
A40: Cica Solution Mask Pack 25g x 10pcs | B40: Mask Packs | C40: 4 | D40: 2.13 | E40: 8.52 | F40: =D40*22 -> 46.86 | G40: =SUM(F40*C40) -> 187.44 | H40: 440 | I40: 47.74 | J40: =L40-K40 -> 143.65771 | K40: =(F40/$G$92)*Costs!$B$23 -> 69.305248 | L40: =N40/1.08 -> 212.96296 | M40: =L40*0.08 -> 17.037037 | N40: 230 | O40: =Table1[[#This Row],[Total Selling Price / Unit (MVR)]]*Table1[[#This Row],[Qty (NOS)]] -> 920 | Q40: 7.14 | R40: =Q40*22 -> 157.08 | S40: 440 | T40: 20 | U40: 2.13 | V40: 46.86 | W40: 47.74 | X40: 230 | Y40: =T40*15.42 -> 308.4 | Z40: =Y40*1.08 -> 333.072 | AA40: =C40*Z40 -> 1332.288 | AB40: =(T40+9)*15.42 -> 447.18 | AC40: =AB40*1.08 -> 482.9544 | AD40: =C40*AC40 -> 1931.8176 | AE40: =T40*22 -> 440 | AF40: =AE40*1.08 -> 475.2 | AG40: =C40*AF40 -> 1900.8 | AH40: =(T40+9)*22 -> 638 | AI40: =AH40*1.08 -> 689.04 | AJ40: =C40*AI40 -> 2756.16 | AK40: =Table1[[#This Row],[Total Selling Price / Unit (MVR)]]/Table1[[#This Row],[CNF / Unit (MVR)]] -> 4.9082373 | AL40: =Table1[[#This Row],[Total Selling Price / Unit (MVR)]]-(Table1[[#This Row],[GST 8% (MVR)]]+Table1[[#This Row],[Weighted max expense (MVR)]]) -> 143.65771 | AM40: =Table1[[#This Row],[Profit / Unit (MVR)]]*Table1[[#This Row],[Qty (NOS)]] -> 574.63086
A41: Hyaluronic Collagen Solution Mask Pack 25g x 10pcs | B41: Mask Packs | C41: 4 | D41: 2.13 | E41: 8.52 | F41: =D41*22 -> 46.86 | G41: =SUM(F41*C41) -> 187.44 | H41: 440 | I41: 47.74 | J41: =L41-K41 -> 143.65771 | K41: =(F41/$G$92)*Costs!$B$23 -> 69.305248 | L41: =N41/1.08 -> 212.96296 | M41: =L41*0.08 -> 17.037037 | N41: 230 | O41: =Table1[[#This Row],[Total Selling Price / Unit (MVR)]]*Table1[[#This Row],[Qty (NOS)]] -> 920 | Q41: 7.14 | R41: =Q41*22 -> 157.08 | S41: 440 | T41: 20 | U41: 2.13 | V41: 46.86 | W41: 47.74 | X41: 230 | Y41: =T41*15.42 -> 308.4 | Z41: =Y41*1.08 -> 333.072 | AA41: =C41*Z41 -> 1332.288 | AB41: =(T41+9)*15.42 -> 447.18 | AC41: =AB41*1.08 -> 482.9544 | AD41: =C41*AC41 -> 1931.8176 | AE41: =T41*22 -> 440 | AF41: =AE41*1.08 -> 475.2 | AG41: =C41*AF41 -> 1900.8 | AH41: =(T41+9)*22 -> 638 | AI41: =AH41*1.08 -> 689.04 | AJ41: =C41*AI41 -> 2756.16 | AK41: =Table1[[#This Row],[Total Selling Price / Unit (MVR)]]/Table1[[#This Row],[CNF / Unit (MVR)]] -> 4.9082373 | AL41: =Table1[[#This Row],[Total Selling Price / Unit (MVR)]]-(Table1[[#This Row],[GST 8% (MVR)]]+Table1[[#This Row],[Weighted max expense (MVR)]]) -> 143.65771 | AM41: =Table1[[#This Row],[Profit / Unit (MVR)]]*Table1[[#This Row],[Qty (NOS)]] -> 574.63086
A42: Snail Solution Mask Pack 25g x 10pcs | B42: Mask Packs | C42: 4 | D42: 2.13 | E42: 8.52 | F42: =D42*22 -> 46.86 | G42: =SUM(F42*C42) -> 187.44 | H42: 440 | I42: 47.74 | J42: =L42-K42 -> 143.65771 | K42: =(F42/$G$92)*Costs!$B$23 -> 69.305248 | L42: =N42/1.08 -> 212.96296 | M42: =L42*0.08 -> 17.037037 | N42: 230 | O42: =Table1[[#This Row],[Total Selling Price / Unit (MVR)]]*Table1[[#This Row],[Qty (NOS)]] -> 920 | Q42: 7.14 | R42: =Q42*22 -> 157.08 | S42: 440 | T42: 20 | U42: 2.13 | V42: 46.86 | W42: 47.74 | X42: 230 | Y42: =T42*15.42 -> 308.4 | Z42: =Y42*1.08 -> 333.072 | AA42: =C42*Z42 -> 1332.288 | AB42: =(T42+9)*15.42 -> 447.18 | AC42: =AB42*1.08 -> 482.9544 | AD42: =C42*AC42 -> 1931.8176 | AE42: =T42*22 -> 440 | AF42: =AE42*1.08 -> 475.2 | AG42: =C42*AF42 -> 1900.8 | AH42: =(T42+9)*22 -> 638 | AI42: =AH42*1.08 -> 689.04 | AJ42: =C42*AI42 -> 2756.16 | AK42: =Table1[[#This Row],[Total Selling Price / Unit (MVR)]]/Table1[[#This Row],[CNF / Unit (MVR)]] -> 4.9082373 | AL42: =Table1[[#This Row],[Total Selling Price / Unit (MVR)]]-(Table1[[#This Row],[GST 8% (MVR)]]+Table1[[#This Row],[Weighted max expense (MVR)]]) -> 143.65771 | AM42: =Table1[[#This Row],[Profit / Unit (MVR)]]*Table1[[#This Row],[Qty (NOS)]] -> 574.63086
A43: Vitamin Solution Mask Pack 25g x 10pcs | B43: Mask Packs | C43: 4 | D43: 2.13 | E43: 8.52 | F43: =D43*22 -> 46.86 | G43: =SUM(F43*C43) -> 187.44 | H43: 440 | I43: 47.74 | J43: =L43-K43 -> 143.65771 | K43: =(F43/$G$92)*Costs!$B$23 -> 69.305248 | L43: =N43/1.08 -> 212.96296 | M43: =L43*0.08 -> 17.037037 | N43: 230 | O43: =Table1[[#This Row],[Total Selling Price / Unit (MVR)]]*Table1[[#This Row],[Qty (NOS)]] -> 920 | Q43: 7.14 | R43: =Q43*22 -> 157.08 | S43: 440 | T43: 20 | U43: 2.13 | V43: 46.86 | W43: 47.74 | X43: 230 | Y43: =T43*15.42 -> 308.4 | Z43: =Y43*1.08 -> 333.072 | AA43: =C43*Z43 -> 1332.288 | AB43: =(T43+9)*15.42 -> 447.18 | AC43: =AB43*1.08 -> 482.9544 | AD43: =C43*AC43 -> 1931.8176 | AE43: =T43*22 -> 440 | AF43: =AE43*1.08 -> 475.2 | AG43: =C43*AF43 -> 1900.8 | AH43: =(T43+9)*22 -> 638 | AI43: =AH43*1.08 -> 689.04 | AJ43: =C43*AI43 -> 2756.16 | AK43: =Table1[[#This Row],[Total Selling Price / Unit (MVR)]]/Table1[[#This Row],[CNF / Unit (MVR)]] -> 4.9082373 | AL43: =Table1[[#This Row],[Total Selling Price / Unit (MVR)]]-(Table1[[#This Row],[GST 8% (MVR)]]+Table1[[#This Row],[Weighted max expense (MVR)]]) -> 143.65771 | AM43: =Table1[[#This Row],[Profit / Unit (MVR)]]*Table1[[#This Row],[Qty (NOS)]] -> 574.63086
A44: 24K Gold Perfect Ampoule 50g | B44: Serums & Ampoules | C44: 4 | D44: 12.18 | E44: 48.72 | F44: =D44*22 -> 267.96 | G44: =SUM(F44*C44) -> 1071.84 | H44: 1956.24 | I44: 459.58 | J44: =L44-K44 -> 85.172597 | K44: =(F44/$G$92)*Costs!$B$23 -> 396.30888 | L44: =N44/1.08 -> 481.48148 | M44: =L44*0.08 -> 38.518519 | N44: 520 | O44: =Table1[[#This Row],[Total Selling Price / Unit (MVR)]]*Table1[[#This Row],[Qty (NOS)]] -> 2080 | Q44: 53.57 | R44: =Q44*22 -> 1178.54 | S44: 1956.24 | T44: 88.92 | U44: 12.18 | V44: 267.96 | W44: 459.58 | X44: 520 | Y44: =T44*15.42 -> 1371.1464 | Z44: =Y44*1.08 -> 1480.8381 | AA44: =C44*Z44 -> 5923.3524 | AB44: =(T44+9)*15.42 -> 1509.9264 | AC44: =AB44*1.08 -> 1630.7205 | AD44: =C44*AC44 -> 6522.882 | AE44: =T44*22 -> 1956.24 | AF44: =AE44*1.08 -> 2112.7392 | AG44: =C44*AF44 -> 8450.9568 | AH44: =(T44+9)*22 -> 2154.24 | AI44: =AH44*1.08 -> 2326.5792 | AJ44: =C44*AI44 -> 9306.3168 | AK44: =Table1[[#This Row],[Total Selling Price / Unit (MVR)]]/Table1[[#This Row],[CNF / Unit (MVR)]] -> 1.9405881 | AL44: =Table1[[#This Row],[Total Selling Price / Unit (MVR)]]-(Table1[[#This Row],[GST 8% (MVR)]]+Table1[[#This Row],[Weighted max expense (MVR)]]) -> 85.172597 | AM44: =Table1[[#This Row],[Profit / Unit (MVR)]]*Table1[[#This Row],[Qty (NOS)]] -> 340.69039
A45: Cica Propolis Myrrh Ampoule 15ml | B45: Serums & Ampoules | C45: 4 | D45: 2.58 | E45: 10.32 | F45: =D45*22 -> 56.76 | G45: =SUM(F45*C45) -> 227.04 | H45: 391.16 | I45: 153.12 | J45: =L45-K45 -> 192.90465 | K45: =(F45/$G$92)*Costs!$B$23 -> 83.947202 | L45: =N45/1.08 -> 276.85185 | M45: =L45*0.08 -> 22.148148 | N45: 299 | O45: =Table1[[#This Row],[Total Selling Price / Unit (MVR)]]*Table1[[#This Row],[Qty (NOS)]] -> 1196 | Q45: 17.14 | R45: =Q45*22 -> 377.08 | S45: 391.16 | T45: 17.78 | U45: 2.58 | V45: 56.76 | W45: 153.12 | X45: 299 | Y45: =T45*15.42 -> 274.1676 | Z45: =Y45*1.08 -> 296.10101 | AA45: =C45*Z45 -> 1184.404 | AB45: =(T45+9)*15.42 -> 412.9476 | AC45: =AB45*1.08 -> 445.98341 | AD45: =C45*AC45 -> 1783.9336 | AE45: =T45*22 -> 391.16 | AF45: =AE45*1.08 -> 422.4528 | AG45: =C45*AF45 -> 1689.8112 | AH45: =(T45+9)*22 -> 589.16 | AI45: =AH45*1.08 -> 636.2928 | AJ45: =C45*AI45 -> 2545.1712 | AK45: =Table1[[#This Row],[Total Selling Price / Unit (MVR)]]/Table1[[#This Row],[CNF / Unit (MVR)]] -> 5.2677942 | AL45: =Table1[[#This Row],[Total Selling Price / Unit (MVR)]]-(Table1[[#This Row],[GST 8% (MVR)]]+Table1[[#This Row],[Weighted max expense (MVR)]]) -> 192.90465 | AM45: =Table1[[#This Row],[Profit / Unit (MVR)]]*Table1[[#This Row],[Qty (NOS)]] -> 771.6186
A46: Dr. Ceramide Derma Ampoule 30ml | B46: Serums & Ampoules | C46: 4 | D46: 3.89 | E46: 15.56 | F46: =D46*22 -> 85.58 | G46: =SUM(F46*C46) -> 342.32 | H46: 619.52 | I46: 181.06 | J46: =L46-K46 -> 243.79881 | K46: =(F46/$G$92)*Costs!$B$23 -> 126.57156 | L46: =N46/1.08 -> 370.37037 | M46: =L46*0.08 -> 29.62963 | N46: 400 | O46: =Table1[[#This Row],[Total Selling Price / Unit (MVR)]]*Table1[[#This Row],[Qty (NOS)]] -> 1600 | Q46: 27.14 | R46: =Q46*22 -> 597.08 | S46: 619.52 | T46: 28.16 | U46: 3.89 | V46: 85.58 | W46: 181.06 | X46: 400 | Y46: =T46*15.42 -> 434.2272 | Z46: =Y46*1.08 -> 468.96538 | AA46: =C46*Z46 -> 1875.8615 | AB46: =(T46+9)*15.42 -> 573.0072 | AC46: =AB46*1.08 -> 618.84778 | AD46: =C46*AC46 -> 2475.3911 | AE46: =T46*22 -> 619.52 | AF46: =AE46*1.08 -> 669.0816 | AG46: =C46*AF46 -> 2676.3264 | AH46: =(T46+9)*22 -> 817.52 | AI46: =AH46*1.08 -> 882.9216 | AJ46: =C46*AI46 -> 3531.6864 | AK46: =Table1[[#This Row],[Total Selling Price / Unit (MVR)]]/Table1[[#This Row],[CNF / Unit (MVR)]] -> 4.6739892 | AL46: =Table1[[#This Row],[Total Selling Price / Unit (MVR)]]-(Table1[[#This Row],[GST 8% (MVR)]]+Table1[[#This Row],[Weighted max expense (MVR)]]) -> 243.79881 | AM46: =Table1[[#This Row],[Profit / Unit (MVR)]]*Table1[[#This Row],[Qty (NOS)]] -> 975.19525
A47: Dr. Cica Derma Ampoule 30ml | B47: Serums & Ampoules | C47: 5 | D47: 3.89 | E47: 27.23 | F47: =D47*22 -> 85.58 | G47: =SUM(F47*C47) -> 427.9 | H47: 619.52 | I47: 181.06 | J47: =L47-K47 -> 206.76178 | K47: =(F47/$G$92)*Costs!$B$23 -> 126.57156 | L47: =N47/1.08 -> 333.33333 | M47: =L47*0.08 -> 26.666667 | N47: 360 | O47: =Table1[[#This Row],[Total Selling Price / Unit (MVR)]]*Table1[[#This Row],[Qty (NOS)]] -> 1800 | Q47: 27.14 | R47: =Q47*22 -> 597.08 | S47: 619.52 | T47: 28.16 | U47: 3.89 | V47: 85.58 | W47: 181.06 | X47: 360 | Y47: =T47*15.42 -> 434.2272 | Z47: =Y47*1.08 -> 468.96538 | AA47: =C47*Z47 -> 2344.8269 | AB47: =(T47+9)*15.42 -> 573.0072 | AC47: =AB47*1.08 -> 618.84778 | AD47: =C47*AC47 -> 3094.2389 | AE47: =T47*22 -> 619.52 | AF47: =AE47*1.08 -> 669.0816 | AG47: =C47*AF47 -> 3345.408 | AH47: =(T47+9)*22 -> 817.52 | AI47: =AH47*1.08 -> 882.9216 | AJ47: =C47*AI47 -> 4414.608 | AK47: =Table1[[#This Row],[Total Selling Price / Unit (MVR)]]/Table1[[#This Row],[CNF / Unit (MVR)]] -> 4.2065903 | AL47: =Table1[[#This Row],[Total Selling Price / Unit (MVR)]]-(Table1[[#This Row],[GST 8% (MVR)]]+Table1[[#This Row],[Weighted max expense (MVR)]]) -> 206.76178 | AM47: =Table1[[#This Row],[Profit / Unit (MVR)]]*Table1[[#This Row],[Qty (NOS)]] -> 1033.8089
A48: Dr. Collagen Derma Ampoule 30ml | B48: Serums & Ampoules | C48: 4 | D48: 3.89 | E48: 15.56 | F48: =D48*22 -> 85.58 | G48: =SUM(F48*C48) -> 342.32 | H48: 619.52 | I48: 181.06 | J48: =L48-K48 -> 294.72474 | K48: =(F48/$G$92)*Costs!$B$23 -> 126.57156 | L48: =N48/1.08 -> 421.2963 | M48: =L48*0.08 -> 33.703704 | N48: 455 | O48: =Table1[[#This Row],[Total Selling Price / Unit (MVR)]]*Table1[[#This Row],[Qty (NOS)]] -> 1820 | Q48: 27.14 | R48: =Q48*22 -> 597.08 | S48: 619.52 | T48: 28.16 | U48: 3.89 | V48: 85.58 | W48: 181.06 | X48: 455 | Y48: =T48*15.42 -> 434.2272 | Z48: =Y48*1.08 -> 468.96538 | AA48: =C48*Z48 -> 1875.8615 | AB48: =(T48+9)*15.42 -> 573.0072 | AC48: =AB48*1.08 -> 618.84778 | AD48: =C48*AC48 -> 2475.3911 | AE48: =T48*22 -> 619.52 | AF48: =AE48*1.08 -> 669.0816 | AG48: =C48*AF48 -> 2676.3264 | AH48: =(T48+9)*22 -> 817.52 | AI48: =AH48*1.08 -> 882.9216 | AJ48: =C48*AI48 -> 3531.6864 | AK48: =Table1[[#This Row],[Total Selling Price / Unit (MVR)]]/Table1[[#This Row],[CNF / Unit (MVR)]] -> 5.3166628 | AL48: =Table1[[#This Row],[Total Selling Price / Unit (MVR)]]-(Table1[[#This Row],[GST 8% (MVR)]]+Table1[[#This Row],[Weighted max expense (MVR)]]) -> 294.72474 | AM48: =Table1[[#This Row],[Profit / Unit (MVR)]]*Table1[[#This Row],[Qty (NOS)]] -> 1178.899
A49: Dr. Vitamin C Derma Ampoule 30ml | B49: Serums & Ampoules | C49: 7 | D49: 3.89 | E49: 27.23 | F49: =D49*22 -> 85.58 | G49: =SUM(F49*C49) -> 599.06 | H49: 619.52 | I49: 181.06 | J49: =L49-K49 -> 206.76178 | K49: =(F49/$G$92)*Costs!$B$23 -> 126.57156 | L49: =N49/1.08 -> 333.33333 | M49: =L49*0.08 -> 26.666667 | N49: 360 | O49: =Table1[[#This Row],[Total Selling Price / Unit (MVR)]]*Table1[[#This Row],[Qty (NOS)]] -> 2520 | Q49: 27.14 | R49: =Q49*22 -> 597.08 | S49: 619.52 | T49: 28.16 | U49: 3.89 | V49: 85.58 | W49: 181.06 | X49: 360 | Y49: =T49*15.42 -> 434.2272 | Z49: =Y49*1.08 -> 468.96538 | AA49: =C49*Z49 -> 3282.7576 | AB49: =(T49+9)*15.42 -> 573.0072 | AC49: =AB49*1.08 -> 618.84778 | AD49: =C49*AC49 -> 4331.9344 | AE49: =T49*22 -> 619.52 | AF49: =AE49*1.08 -> 669.0816 | AG49: =C49*AF49 -> 4683.5712 | AH49: =(T49+9)*22 -> 817.52 | AI49: =AH49*1.08 -> 882.9216 | AJ49: =C49*AI49 -> 6180.4512 | AK49: =Table1[[#This Row],[Total Selling Price / Unit (MVR)]]/Table1[[#This Row],[CNF / Unit (MVR)]] -> 4.2065903 | AL49: =Table1[[#This Row],[Total Selling Price / Unit (MVR)]]-(Table1[[#This Row],[GST 8% (MVR)]]+Table1[[#This Row],[Weighted max expense (MVR)]]) -> 206.76178 | AM49: =Table1[[#This Row],[Profit / Unit (MVR)]]*Table1[[#This Row],[Qty (NOS)]] -> 1447.3324
A50: Heeyul Premium 24K Gold Essence 130ml | B50: Serums & Ampoules | C50: 4 | D50: 9.04 | E50: 36.16 | F50: =D50*22 -> 198.88 | G50: =SUM(F50*C50) -> 795.52 | H50: 570.68 | I50: 453.42 | J50: =L50-K50 -> 150.30386 | K50: =(F50/$G$92)*Costs!$B$23 -> 294.14058 | L50: =N50/1.08 -> 444.44444 | M50: =L50*0.08 -> 35.555556 | N50: 480 | O50: =Table1[[#This Row],[Total Selling Price / Unit (MVR)]]*Table1[[#This Row],[Qty (NOS)]] -> 1920 | Q50: 25 | R50: =Q50*22 -> 550 | S50: 570.68 | T50: 25.94 | U50: 9.04 | V50: 198.88 | W50: 453.42 | X50: 480 | Y50: =T50*15.42 -> 399.9948 | Z50: =Y50*1.08 -> 431.99438 | AA50: =C50*Z50 -> 1727.9775 | AB50: =(T50+9)*15.42 -> 538.7748 | AC50: =AB50*1.08 -> 581.87678 | AD50: =C50*AC50 -> 2327.5071 | AE50: =T50*22 -> 570.68 | AF50: =AE50*1.08 -> 616.3344 | AG50: =C50*AF50 -> 2465.3376 | AH50: =(T50+9)*22 -> 768.68 | AI50: =AH50*1.08 -> 830.1744 | AJ50: =C50*AI50 -> 3320.6976 | AK50: =Table1[[#This Row],[Total Selling Price / Unit (MVR)]]/Table1[[#This Row],[CNF / Unit (MVR)]] -> 2.4135157 | AL50: =Table1[[#This Row],[Total Selling Price / Unit (MVR)]]-(Table1[[#This Row],[GST 8% (MVR)]]+Table1[[#This Row],[Weighted max expense (MVR)]]) -> 150.30386 | AM50: =Table1[[#This Row],[Profit / Unit (MVR)]]*Table1[[#This Row],[Qty (NOS)]] -> 601.21544
... A75: UV Sun Ultra Shield Sun Stick 20g | B75: Sun Care | C75: 4 | D75: 6.85 | E75: 27.4 | F75: =D75*22 -> 150.7 | G75: =SUM(F75*C75) -> 602.8 | H75: 652.08 | I75: 247.72 | J75: =L75-K75 -> 100.26507 | K75: =(F75/$G$92)*Costs!$B$23 -> 222.88308 | L75: =N75/1.08 -> 323.14815 | M75: =L75*0.08 -> 25.851852 | N75: 349 | O75: =Table1[[#This Row],[Total Selling Price / Unit (MVR)]]*Table1[[#This Row],[Qty (NOS)]] -> 1396 | Q75: 28.57 | R75: =Q75*22 -> 628.54 | S75: 652.08 | T75: 29.64 | U75: 6.85 | V75: 150.7 | W75: 247.72 | X75: 349 | Y75: =T75*15.42 -> 457.0488 | Z75: =Y75*1.08 -> 493.6127 | AA75: =C75*Z75 -> 1974.4508 | AB75: =(T75+9)*15.42 -> 595.8288 | AC75: =AB75*1.08 -> 643.4951 | AD75: =C75*AC75 -> 2573.9804 | AE75: =T75*22 -> 652.08 | AF75: =AE75*1.08 -> 704.2464 | AG75: =C75*AF75 -> 2816.9856 | AH75: =(T75+9)*22 -> 850.08 | AI75: =AH75*1.08 -> 918.0864 | AJ75: =C75*AI75 -> 3672.3456 | AK75: =Table1[[#This Row],[Total Selling Price / Unit (MVR)]]/Table1[[#This Row],[CNF / Unit (MVR)]] -> 2.3158593 | AL75: =Table1[[#This Row],[Total Selling Price / Unit (MVR)]]-(Table1[[#This Row],[GST 8% (MVR)]]+Table1[[#This Row],[Weighted max expense (MVR)]]) -> 100.26507 | AM75: =Table1[[#This Row],[Profit / Unit (MVR)]]*Table1[[#This Row],[Qty (NOS)]] -> 401.06029
A76: Pore Peeling Pad 60pads | B76: Toner / Peeling Pads | C76: 4 | D76: 4.74 | E76: 18.96 | F76: =D76*22 -> 104.28 | G76: =SUM(F76*C76) -> 417.12 | H76: N/A | I76: 222.42 | J76: =L76-K76 -> 122.62327 | K76: =(F76/$G$92)*Costs!$B$23 -> 154.22858 | L76: =N76/1.08 -> 276.85185 | M76: =L76*0.08 -> 22.148148 | N76: 299 | O76: =Table1[[#This Row],[Total Selling Price / Unit (MVR)]]*Table1[[#This Row],[Qty (NOS)]] -> 1196 | Q76: 14.29 | R76: =Q76*22 -> 314.38 | S76: N/A | T76: 14.8 | U76: 4.74 | V76: 104.28 | W76: 222.42 | X76: 299 | Y76: =T76*15.42 -> 228.216 | Z76: =Y76*1.08 -> 246.47328 | AA76: =C76*Z76 -> 985.89312 | AB76: =(T76+9)*15.42 -> 366.996 | AC76: =AB76*1.08 -> 396.35568 | AD76: =C76*AC76 -> 1585.4227 | AE76: =T76*22 -> 325.6 | AF76: =AE76*1.08 -> 351.648 | AG76: =C76*AF76 -> 1406.592 | AH76: =(T76+9)*22 -> 523.6 | AI76: =AH76*1.08 -> 565.488 | AJ76: =C76*AI76 -> 2261.952 | AK76: =Table1[[#This Row],[Total Selling Price / Unit (MVR)]]/Table1[[#This Row],[CNF / Unit (MVR)]] -> 2.8672804 | AL76: =Table1[[#This Row],[Total Selling Price / Unit (MVR)]]-(Table1[[#This Row],[GST 8% (MVR)]]+Table1[[#This Row],[Weighted max expense (MVR)]]) -> 122.62327 | AM76: =Table1[[#This Row],[Profit / Unit (MVR)]]*Table1[[#This Row],[Qty (NOS)]] -> 490.49308
A77: Truly Centella Toner Pad 60pads | B77: Toner / Peeling Pads | C77: 7 | D77: 6.92 | E77: 48.44 | F77: =D77*22 -> 152.24 | G77: =SUM(F77*C77) -> 1065.68 | H77: 407.66 | I77: 356.84 | J77: =L77-K77 -> 135.02447 | K77: =(F77/$G$92)*Costs!$B$23 -> 225.16071 | L77: =N77/1.08 -> 360.18519 | M77: =L77*0.08 -> 28.814815 | N77: 389 | O77: =Table1[[#This Row],[Total Selling Price / Unit (MVR)]]*Table1[[#This Row],[Qty (NOS)]] -> 2723 | Q77: 17.86 | R77: =Q77*22 -> 392.92 | S77: 407.66 | T77: 18.53 | U77: 6.92 | V77: 152.24 | W77: 356.84 | X77: 389 | Y77: =T77*15.42 -> 285.7326 | Z77: =Y77*1.08 -> 308.59121 | AA77: =C77*Z77 -> 2160.1385 | AB77: =(T77+9)*15.42 -> 424.5126 | AC77: =AB77*1.08 -> 458.47361 | AD77: =C77*AC77 -> 3209.3153 | AE77: =T77*22 -> 407.66 | AF77: =AE77*1.08 -> 440.2728 | AG77: =C77*AF77 -> 3081.9096 | AH77: =(T77+9)*22 -> 605.66 | AI77: =AH77*1.08 -> 654.1128 | AJ77: =C77*AI77 -> 4578.7896 | AK77: =Table1[[#This Row],[Total Selling Price / Unit (MVR)]]/Table1[[#This Row],[CNF / Unit (MVR)]] -> 2.555176 | AL77: =Table1[[#This Row],[Total Selling Price / Unit (MVR)]]-(Table1[[#This Row],[GST 8% (MVR)]]+Table1[[#This Row],[Weighted max expense (MVR)]]) -> 135.02447 | AM77: =Table1[[#This Row],[Profit / Unit (MVR)]]*Table1[[#This Row],[Qty (NOS)]] -> 945.17131
A78: Truly Glutathione Toner Pad 60pads | B78: Toner / Peeling Pads | C78: 7 | D78: 6.92 | E78: 48.44 | F78: =D78*22 -> 152.24 | G78: =SUM(F78*C78) -> 1065.68 | H78: 407.66 | I78: 356.84 | J78: =L78-K78 -> 135.02447 | K78: =(F78/$G$92)*Costs!$B$23 -> 225.16071 | L78: =N78/1.08 -> 360.18519 | M78: =L78*0.08 -> 28.814815 | N78: 389 | O78: =Table1[[#This Row],[Total Selling Price / Unit (MVR)]]*Table1[[#This Row],[Qty (NOS)]] -> 2723 | Q78: 17.86 | R78: =Q78*22 -> 392.92 | S78: 407.66 | T78: 18.53 | U78: 6.92 | V78: 152.24 | W78: 356.84 | X78: 389 | Y78: =T78*15.42 -> 285.7326 | Z78: =Y78*1.08 -> 308.59121 | AA78: =C78*Z78 -> 2160.1385 | AB78: =(T78+9)*15.42 -> 424.5126 | AC78: =AB78*1.08 -> 458.47361 | AD78: =C78*AC78 -> 3209.3153 | AE78: =T78*22 -> 407.66 | AF78: =AE78*1.08 -> 440.2728 | AG78: =C78*AF78 -> 3081.9096 | AH78: =(T78+9)*22 -> 605.66 | AI78: =AH78*1.08 -> 654.1128 | AJ78: =C78*AI78 -> 4578.7896 | AK78: =Table1[[#This Row],[Total Selling Price / Unit (MVR)]]/Table1[[#This Row],[CNF / Unit (MVR)]] -> 2.555176 | AL78: =Table1[[#This Row],[Total Selling Price / Unit (MVR)]]-(Table1[[#This Row],[GST 8% (MVR)]]+Table1[[#This Row],[Weighted max expense (MVR)]]) -> 135.02447 | AM78: =Table1[[#This Row],[Profit / Unit (MVR)]]*Table1[[#This Row],[Qty (NOS)]] -> 945.17131
A79: Truly PDRN Toner Pad 60pads | B79: Toner / Peeling Pads | C79: 4 | D79: 6.92 | E79: 27.68 | F79: =D79*22 -> 152.24 | G79: =SUM(F79*C79) -> 608.96 | H79: 407.66 | I79: 356.84 | J79: =L79-K79 -> 135.02447 | K79: =(F79/$G$92)*Costs!$B$23 -> 225.16071 | L79: =N79/1.08 -> 360.18519 | M79: =L79*0.08 -> 28.814815 | N79: 389 | O79: =Table1[[#This Row],[Total Selling Price / Unit (MVR)]]*Table1[[#This Row],[Qty (NOS)]] -> 1556 | Q79: 17.86 | R79: =Q79*22 -> 392.92 | S79: 407.66 | T79: 18.53 | U79: 6.92 | V79: 152.24 | W79: 356.84 | X79: 389 | Y79: =T79*15.42 -> 285.7326 | Z79: =Y79*1.08 -> 308.59121 | AA79: =C79*Z79 -> 1234.3648 | AB79: =(T79+9)*15.42 -> 424.5126 | AC79: =AB79*1.08 -> 458.47361 | AD79: =C79*AC79 -> 1833.8944 | AE79: =T79*22 -> 407.66 | AF79: =AE79*1.08 -> 440.2728 | AG79: =C79*AF79 -> 1761.0912 | AH79: =(T79+9)*22 -> 605.66 | AI79: =AH79*1.08 -> 654.1128 | AJ79: =C79*AI79 -> 2616.4512 | AK79: =Table1[[#This Row],[Total Selling Price / Unit (MVR)]]/Table1[[#This Row],[CNF / Unit (MVR)]] -> 2.555176 | AL79: =Table1[[#This Row],[Total Selling Price / Unit (MVR)]]-(Table1[[#This Row],[GST 8% (MVR)]]+Table1[[#This Row],[Weighted max expense (MVR)]]) -> 135.02447 | AM79: =Table1[[#This Row],[Profit / Unit (MVR)]]*Table1[[#This Row],[Qty (NOS)]] -> 540.09789
A80: Truly Retinol Toner Pad 60pads | B80: Toner / Peeling Pads | C80: 4 | D80: 6.92 | E80: 27.68 | F80: =D80*22 -> 152.24 | G80: =SUM(F80*C80) -> 608.96 | H80: 407.66 | I80: 356.84 | J80: =L80-K80 -> 135.02447 | K80: =(F80/$G$92)*Costs!$B$23 -> 225.16071 | L80: =N80/1.08 -> 360.18519 | M80: =L80*0.08 -> 28.814815 | N80: 389 | O80: =Table1[[#This Row],[Total Selling Price / Unit (MVR)]]*Table1[[#This Row],[Qty (NOS)]] -> 1556 | Q80: 17.86 | R80: =Q80*22 -> 392.92 | S80: 407.66 | T80: 18.53 | U80: 6.92 | V80: 152.24 | W80: 356.84 | X80: 389 | Y80: =T80*15.42 -> 285.7326 | Z80: =Y80*1.08 -> 308.59121 | AA80: =C80*Z80 -> 1234.3648 | AB80: =(T80+9)*15.42 -> 424.5126 | AC80: =AB80*1.08 -> 458.47361 | AD80: =C80*AC80 -> 1833.8944 | AE80: =T80*22 -> 407.66 | AF80: =AE80*1.08 -> 440.2728 | AG80: =C80*AF80 -> 1761.0912 | AH80: =(T80+9)*22 -> 605.66 | AI80: =AH80*1.08 -> 654.1128 | AJ80: =C80*AI80 -> 2616.4512 | AK80: =Table1[[#This Row],[Total Selling Price / Unit (MVR)]]/Table1[[#This Row],[CNF / Unit (MVR)]] -> 2.555176 | AL80: =Table1[[#This Row],[Total Selling Price / Unit (MVR)]]-(Table1[[#This Row],[GST 8% (MVR)]]+Table1[[#This Row],[Weighted max expense (MVR)]]) -> 135.02447 | AM80: =Table1[[#This Row],[Profit / Unit (MVR)]]*Table1[[#This Row],[Qty (NOS)]] -> 540.09789
A81: Centella Moisture Skin 150ml | B81: Toners & Emulsions | C81: 4 | D81: 5.8 | E81: 23.2 | F81: =D81*22 -> 127.6 | G81: =SUM(F81*C81) -> 510.4 | H81: 407.66 | I81: 292.16 | J81: =L81-K81 -> 135.35556 | K81: =(F81/$G$92)*Costs!$B$23 -> 188.71852 | L81: =N81/1.08 -> 324.07407 | M81: =L81*0.08 -> 25.925926 | N81: 350 | O81: =Table1[[#This Row],[Total Selling Price / Unit (MVR)]]*Table1[[#This Row],[Qty (NOS)]] -> 1400 | Q81: 7.14 | R81: =Q81*22 -> 157.08 | S81: 407.66 | T81: 18.53 | U81: 5.8 | V81: 127.6 | W81: 292.16 | X81: 350 | Y81: =T81*15.42 -> 285.7326 | Z81: =Y81*1.08 -> 308.59121 | AA81: =C81*Z81 -> 1234.3648 | AB81: =(T81+9)*15.42 -> 424.5126 | AC81: =AB81*1.08 -> 458.47361 | AD81: =C81*AC81 -> 1833.8944 | AE81: =T81*22 -> 407.66 | AF81: =AE81*1.08 -> 440.2728 | AG81: =C81*AF81 -> 1761.0912 | AH81: =(T81+9)*22 -> 605.66 | AI81: =AH81*1.08 -> 654.1128 | AJ81: =C81*AI81 -> 2616.4512 | AK81: =Table1[[#This Row],[Total Selling Price / Unit (MVR)]]/Table1[[#This Row],[CNF / Unit (MVR)]] -> 2.7429467 | AL81: =Table1[[#This Row],[Total Selling Price / Unit (MVR)]]-(Table1[[#This Row],[GST 8% (MVR)]]+Table1[[#This Row],[Weighted max expense (MVR)]]) -> 135.35556 | AM81: =Table1[[#This Row],[Profit / Unit (MVR)]]*Table1[[#This Row],[Qty (NOS)]] -> 541.42223
A82: Collagen + Green Tea Moisture Lotion 150ml | B82: Toners & Emulsions | C82: 4 | D82: 5.94 | E82: 23.76 | F82: =D82*22 -> 130.68 | G82: =SUM(F82*C82) -> 522.72 | H82: 407.66 | I82: 375.76 | J82: =L82-K82 -> 130.80028 | K82: =(F82/$G$92)*Costs!$B$23 -> 193.27379 | L82: =N82/1.08 -> 324.07407 | M82: =L82*0.08 -> 25.925926 | N82: 350 | O82: =Table1[[#This Row],[Total Selling Price / Unit (MVR)]]*Table1[[#This Row],[Qty (NOS)]] -> 1400 | Q82: 7.14 | R82: =Q82*22 -> 157.08 | S82: 407.66 | T82: 18.53 | U82: 5.94 | V82: 130.68 | W82: 375.76 | X82: 350 | Y82: =T82*15.42 -> 285.7326 | Z82: =Y82*1.08 -> 308.59121 | AA82: =C82*Z82 -> 1234.3648 | AB82: =(T82+9)*15.42 -> 424.5126 | AC82: =AB82*1.08 -> 458.47361 | AD82: =C82*AC82 -> 1833.8944 | AE82: =T82*22 -> 407.66 | AF82: =AE82*1.08 -> 440.2728 | AG82: =C82*AF82 -> 1761.0912 | AH82: =(T82+9)*22 -> 605.66 | AI82: =AH82*1.08 -> 654.1128 | AJ82: =C82*AI82 -> 2616.4512 | AK82: =Table1[[#This Row],[Total Selling Price / Unit (MVR)]]/Table1[[#This Row],[CNF / Unit (MVR)]] -> 2.6782981 | AL82: =Table1[[#This Row],[Total Selling Price / Unit (MVR)]]-(Table1[[#This Row],[GST 8% (MVR)]]+Table1[[#This Row],[Weighted max expense (MVR)]]) -> 130.80028 | AM82: =Table1[[#This Row],[Profit / Unit (MVR)]]*Table1[[#This Row],[Qty (NOS)]] -> 523.20113
A83: Collagen + Green Tea Moisture Skin 150ml | B83: Toners & Emulsions | C83: 4 | D83: 5.94 | E83: 23.76 | F83: =D83*22 -> 130.68 | G83: =SUM(F83*C83) -> 522.72 | H83: 407.66 | I83: 375.76 | J83: =L83-K83 -> 148.39288 | K83: =(F83/$G$92)*Costs!$B$23 -> 193.27379 | L83: =N83/1.08 -> 341.66667 | M83: =L83*0.08 -> 27.333333 | N83: 369 | O83: =Table1[[#This Row],[Total Selling Price / Unit (MVR)]]*Table1[[#This Row],[Qty (NOS)]] -> 1476 | Q83: 7.14 | R83: =Q83*22 -> 157.08 | S83: 407.66 | T83: 18.53 | U83: 5.94 | V83: 130.68 | W83: 375.76 | X83: 369 | Y83: =T83*15.42 -> 285.7326 | Z83: =Y83*1.08 -> 308.59121 | AA83: =C83*Z83 -> 1234.3648 | AB83: =(T83+9)*15.42 -> 424.5126 | AC83: =AB83*1.08 -> 458.47361 | AD83: =C83*AC83 -> 1833.8944 | AE83: =T83*22 -> 407.66 | AF83: =AE83*1.08 -> 440.2728 | AG83: =C83*AF83 -> 1761.0912 | AH83: =(T83+9)*22 -> 605.66 | AI83: =AH83*1.08 -> 654.1128 | AJ83: =C83*AI83 -> 2616.4512 | AK83: =Table1[[#This Row],[Total Selling Price / Unit (MVR)]]/Table1[[#This Row],[CNF / Unit (MVR)]] -> 2.8236915 | AL83: =Table1[[#This Row],[Total Selling Price / Unit (MVR)]]-(Table1[[#This Row],[GST 8% (MVR)]]+Table1[[#This Row],[Weighted max expense (MVR)]]) -> 148.39288 | AM83: =Table1[[#This Row],[Profit / Unit (MVR)]]*Table1[[#This Row],[Qty (NOS)]] -> 593.5715
A84: Collagen Derma Skin 200ml | B84: Toners & Emulsions | C84: 4 | D84: 6.64 | E84: 26.56 | F84: =D84*22 -> 146.08 | G84: =SUM(F84*C84) -> 584.32 | H84: 1271.6 | I84: 339.9 | J84: =L84-K84 -> 339.50539 | K84: =(F84/$G$92)*Costs!$B$23 -> 216.05016 | L84: =N84/1.08 -> 555.55556 | M84: =L84*0.08 -> 44.444444 | N84: 600 | O84: =Table1[[#This Row],[Total Selling Price / Unit (MVR)]]*Table1[[#This Row],[Qty (NOS)]] -> 2400 | Q84: 55.71 | R84: =Q84*22 -> 1225.62 | S84: 1271.6 | T84: 57.8 | U84: 6.64 | V84: 146.08 | W84: 339.9 | X84: 600 | Y84: =T84*15.42 -> 891.276 | Z84: =Y84*1.08 -> 962.57808 | AA84: =C84*Z84 -> 3850.3123 | AB84: =(T84+9)*15.42 -> 1030.056 | AC84: =AB84*1.08 -> 1112.4605 | AD84: =C84*AC84 -> 4449.8419 | AE84: =T84*22 -> 1271.6 | AF84: =AE84*1.08 -> 1373.328 | AG84: =C84*AF84 -> 5493.312 | AH84: =(T84+9)*22 -> 1469.6 | AI84: =AH84*1.08 -> 1587.168 | AJ84: =C84*AI84 -> 6348.672 | AK84: =Table1[[#This Row],[Total Selling Price / Unit (MVR)]]/Table1[[#This Row],[CNF / Unit (MVR)]] -> 4.1073384 | AL84: =Table1[[#This Row],[Total Selling Price / Unit (MVR)]]-(Table1[[#This Row],[GST 8% (MVR)]]+Table1[[#This Row],[Weighted max expense (MVR)]]) -> 339.50539 | AM84: =Table1[[#This Row],[Profit / Unit (MVR)]]*Table1[[#This Row],[Qty (NOS)]] -> 1358.0216
A85: Collagen Hyaluronic Toner 300ml | B85: Toners & Emulsions | C85: 4 | D85: 8.3 | E85: 33.2 | F85: =D85*22 -> 182.6 | G85: =SUM(F85*C85) -> 730.4 | H85: N/A | I85: 438.68 | J85: =L85-K85 -> 100.30767 | K85: =(F85/$G$92)*Costs!$B$23 -> 270.0627 | L85: =N85/1.08 -> 370.37037 | M85: =L85*0.08 -> 29.62963 | N85: 400 | O85: =Table1[[#This Row],[Total Selling Price / Unit (MVR)]]*Table1[[#This Row],[Qty (NOS)]] -> 1600 | Q85: 25 | R85: =Q85*22 -> 550 | S85: N/A | T85: 25.94 | U85: 8.3 | V85: 182.6 | W85: 438.68 | X85: 400 | Y85: =T85*15.42 -> 399.9948 | Z85: =Y85*1.08 -> 431.99438 | AA85: =C85*Z85 -> 1727.9775 | AB85: =(T85+9)*15.42 -> 538.7748 | AC85: =AB85*1.08 -> 581.87678 | AD85: =C85*AC85 -> 2327.5071 | AE85: =T85*22 -> 570.68 | AF85: =AE85*1.08 -> 616.3344 | AG85: =C85*AF85 -> 2465.3376 | AH85: =(T85+9)*22 -> 768.68 | AI85: =AH85*1.08 -> 830.1744 | AJ85: =C85*AI85 -> 3320.6976 | AK85: =Table1[[#This Row],[Total Selling Price / Unit (MVR)]]/Table1[[#This Row],[CNF / Unit (MVR)]] -> 2.1905805 | AL85: =Table1[[#This Row],[Total Selling Price / Unit (MVR)]]-(Table1[[#This Row],[GST 8% (MVR)]]+Table1[[#This Row],[Weighted max expense (MVR)]]) -> 100.30767 | AM85: =Table1[[#This Row],[Profit / Unit (MVR)]]*Table1[[#This Row],[Qty (NOS)]] -> 401.23066
A86: COLLAGEN+GREEN TEA MOISTURE SKIN 150ml | B86: Toners & Emulsions | C86: 4 | D86: 6.12 | E86: 24.48 | F86: =D86*22 -> 134.64 | G86: =SUM(F86*C86) -> 538.56 | H86: 407.66 | I86: 375.76 | J86: =L86-K86 -> 124.9435 | K86: =(F86/$G$92)*Costs!$B$23 -> 199.13057 | L86: =N86/1.08 -> 324.07407 | M86: =L86*0.08 -> 25.925926 | N86: 350 | O86: =Table1[[#This Row],[Total Selling Price / Unit (MVR)]]*Table1[[#This Row],[Qty (NOS)]] -> 1400 | Q86: 7.14 | R86: =Q86*22 -> 157.08 | S86: 407.66 | T86: 18.53 | U86: 6.12 | V86: 134.64 | W86: 375.76 | X86: 350 | Y86: =T86*15.42 -> 285.7326 | Z86: =Y86*1.08 -> 308.59121 | AA86: =C86*Z86 -> 1234.3648 | AB86: =(T86+9)*15.42 -> 424.5126 | AC86: =AB86*1.08 -> 458.47361 | AD86: =C86*AC86 -> 1833.8944 | AE86: =T86*22 -> 407.66 | AF86: =AE86*1.08 -> 440.2728 | AG86: =C86*AF86 -> 1761.0912 | AH86: =(T86+9)*22 -> 605.66 | AI86: =AH86*1.08 -> 654.1128 | AJ86: =C86*AI86 -> 2616.4512 | AK86: =Table1[[#This Row],[Total Selling Price / Unit (MVR)]]/Table1[[#This Row],[CNF / Unit (MVR)]] -> 2.5995247 | AL86: =Table1[[#This Row],[Total Selling Price / Unit (MVR)]]-(Table1[[#This Row],[GST 8% (MVR)]]+Table1[[#This Row],[Weighted max expense (MVR)]]) -> 124.9435 | AM86: =Table1[[#This Row],[Profit / Unit (MVR)]]*Table1[[#This Row],[Qty (NOS)]] -> 499.77401
A87: Hyaluronic Derma Lotion 200ml | B87: Toners & Emulsions | C87: 4 | D87: 6.78 | E87: 27.12 | F87: =D87*22 -> 149.16 | G87: =SUM(F87*C87) -> 596.64 | H87: N/A | I87: 331.54 | J87: =L87-K87 -> 149.76493 | K87: =(F87/$G$92)*Costs!$B$23 -> 220.60544 | L87: =N87/1.08 -> 370.37037 | M87: =L87*0.08 -> 29.62963 | N87: 400 | O87: =Table1[[#This Row],[Total Selling Price / Unit (MVR)]]*Table1[[#This Row],[Qty (NOS)]] -> 1600 | Q87: 55.71 | R87: =Q87*22 -> 1225.62 | S87: N/A | T87: 57.8 | U87: 6.78 | V87: 149.16 | W87: 331.54 | X87: 400 | Y87: =T87*15.42 -> 891.276 | Z87: =Y87*1.08 -> 962.57808 | AA87: =C87*Z87 -> 3850.3123 | AB87: =(T87+9)*15.42 -> 1030.056 | AC87: =AB87*1.08 -> 1112.4605 | AD87: =C87*AC87 -> 4449.8419 | AE87: =T87*22 -> 1271.6 | AF87: =AE87*1.08 -> 1373.328 | AG87: =C87*AF87 -> 5493.312 | AH87: =(T87+9)*22 -> 1469.6 | AI87: =AH87*1.08 -> 1587.168 | AJ87: =C87*AI87 -> 6348.672 | AK87: =Table1[[#This Row],[Total Selling Price / Unit (MVR)]]/Table1[[#This Row],[CNF / Unit (MVR)]] -> 2.6816841 | AL87: =Table1[[#This Row],[Total Selling Price / Unit (MVR)]]-(Table1[[#This Row],[GST 8% (MVR)]]+Table1[[#This Row],[Weighted max expense (MVR)]]) -> 149.76493 | AM87: =Table1[[#This Row],[Profit / Unit (MVR)]]*Table1[[#This Row],[Qty (NOS)]] -> 599.05973
A88: Tea Tree Derma Lotion 210ml | B88: Toners & Emulsions | C88: 4 | D88: 6.78 | E88: 27.12 | F88: =D88*22 -> 149.16 | G88: =SUM(F88*C88) -> 596.64 | H88: N/A | I88: 331.54 | J88: =L88-K88 -> 149.76493 | K88: =(F88/$G$92)*Costs!$B$23 -> 220.60544 | L88: =N88/1.08 -> 370.37037 | M88: =L88*0.08 -> 29.62963 | N88: 400 | O88: =Table1[[#This Row],[Total Selling Price / Unit (MVR)]]*Table1[[#This Row],[Qty (NOS)]] -> 1600 | Q88: 55.71 | R88: =Q88*22 -> 1225.62 | S88: N/A | T88: 57.8 | U88: 6.78 | V88: 149.16 | W88: 331.54 | X88: 400 | Y88: =T88*15.42 -> 891.276 | Z88: =Y88*1.08 -> 962.57808 | AA88: =C88*Z88 -> 3850.3123 | AB88: =(T88+9)*15.42 -> 1030.056 | AC88: =AB88*1.08 -> 1112.4605 | AD88: =C88*AC88 -> 4449.8419 | AE88: =T88*22 -> 1271.6 | AF88: =AE88*1.08 -> 1373.328 | AG88: =C88*AF88 -> 5493.312 | AH88: =(T88+9)*22 -> 1469.6 | AI88: =AH88*1.08 -> 1587.168 | AJ88: =C88*AI88 -> 6348.672 | AK88: =Table1[[#This Row],[Total Selling Price / Unit (MVR)]]/Table1[[#This Row],[CNF / Unit (MVR)]] -> 2.6816841 | AL88: =Table1[[#This Row],[Total Selling Price / Unit (MVR)]]-(Table1[[#This Row],[GST 8% (MVR)]]+Table1[[#This Row],[Weighted max expense (MVR)]]) -> 149.76493 | AM88: =Table1[[#This Row],[Profit / Unit (MVR)]]*Table1[[#This Row],[Qty (NOS)]] -> 599.05973
A89: Tea Tree Derma Skin 210ml | B89: Toners & Emulsions | C89: 7 | D89: 6.78 | E89: 47.46 | F89: =D89*22 -> 149.16 | G89: =SUM(F89*C89) -> 1044.12 | H89: N/A | I89: 339.9 | J89: =L89-K89 -> 334.95012 | K89: =(F89/$G$92)*Costs!$B$23 -> 220.60544 | L89: =N89/1.08 -> 555.55556 | M89: =L89*0.08 -> 44.444444 | N89: 600 | O89: =Table1[[#This Row],[Total Selling Price / Unit (MVR)]]*Table1[[#This Row],[Qty (NOS)]] -> 4200 | Q89: 55.71 | R89: =Q89*22 -> 1225.62 | S89: N/A | T89: 57.8 | U89: 6.78 | V89: 149.16 | W89: 339.9 | X89: 600 | Y89: =T89*15.42 -> 891.276 | Z89: =Y89*1.08 -> 962.57808 | AA89: =C89*Z89 -> 6738.0466 | AB89: =(T89+9)*15.42 -> 1030.056 | AC89: =AB89*1.08 -> 1112.4605 | AD89: =C89*AC89 -> 7787.2234 | AE89: =T89*22 -> 1271.6 | AF89: =AE89*1.08 -> 1373.328 | AG89: =C89*AF89 -> 9613.296 | AH89: =(T89+9)*22 -> 1469.6 | AI89: =AH89*1.08 -> 1587.168 | AJ89: =C89*AI89 -> 11110.176 | AK89: =Table1[[#This Row],[Total Selling Price / Unit (MVR)]]/Table1[[#This Row],[CNF / Unit (MVR)]] -> 4.0225261 | AL89: =Table1[[#This Row],[Total Selling Price / Unit (MVR)]]-(Table1[[#This Row],[GST 8% (MVR)]]+Table1[[#This Row],[Weighted max expense (MVR)]]) -> 334.95012 | AM89: =Table1[[#This Row],[Profit / Unit (MVR)]]*Table1[[#This Row],[Qty (NOS)]] -> 2344.6508
A90: Vitamin C Pure Emulsion 120ml | B90: Toners & Emulsions | C90: 4 | D90: 8.98 | E90: 35.92 | F90: =D90*22 -> 197.56 | G90: =SUM(F90*C90) -> 790.24 | H90: 1271.6 | I90: 358.16 | J90: =L90-K90 -> 124.47834 | K90: =(F90/$G$92)*Costs!$B$23 -> 292.18832 | L90: =N90/1.08 -> 416.66667 | M90: =L90*0.08 -> 33.333333 | N90: 450 | O90: =Table1[[#This Row],[Total Selling Price / Unit (MVR)]]*Table1[[#This Row],[Qty (NOS)]] -> 1800 | Q90: 55.71 | R90: =Q90*22 -> 1225.62 | S90: 1271.6 | T90: 57.8 | U90: 8.98 | V90: 197.56 | W90: 358.16 | X90: 450 | Y90: =T90*15.42 -> 891.276 | Z90: =Y90*1.08 -> 962.57808 | AA90: =C90*Z90 -> 3850.3123 | AB90: =(T90+9)*15.42 -> 1030.056 | AC90: =AB90*1.08 -> 1112.4605 | AD90: =C90*AC90 -> 4449.8419 | AE90: =T90*22 -> 1271.6 | AF90: =AE90*1.08 -> 1373.328 | AG90: =C90*AF90 -> 5493.312 | AH90: =(T90+9)*22 -> 1469.6 | AI90: =AH90*1.08 -> 1587.168 | AJ90: =C90*AI90 -> 6348.672 | AK90: =Table1[[#This Row],[Total Selling Price / Unit (MVR)]]/Table1[[#This Row],[CNF / Unit (MVR)]] -> 2.277789 | AL90: =Table1[[#This Row],[Total Selling Price / Unit (MVR)]]-(Table1[[#This Row],[GST 8% (MVR)]]+Table1[[#This Row],[Weighted max expense (MVR)]]) -> 124.47834 | AM90: =Table1[[#This Row],[Profit / Unit (MVR)]]*Table1[[#This Row],[Qty (NOS)]] -> 497.91337
A91: Vitamin C Pure Toner 120ml | B91: Toners & Emulsions | C91: 4 | D91: 8.98 | E91: 35.92 | F91: =D91*22 -> 197.56 | G91: =SUM(F91*C91) -> 790.24 | H91: 1271.6 | I91: 426.14 | J91: =L91-K91 -> 170.77464 | K91: =(F91/$G$92)*Costs!$B$23 -> 292.18832 | L91: =N91/1.08 -> 462.96296 | M91: =L91*0.08 -> 37.037037 | N91: 500 | O91: =Table1[[#This Row],[Total Selling Price / Unit (MVR)]]*Table1[[#This Row],[Qty (NOS)]] -> 2000 | Q91: 55.71 | R91: =Q91*22 -> 1225.62 | S91: 1271.6 | T91: 57.8 | U91: 8.98 | V91: 197.56 | W91: 426.14 | X91: 500 | Y91: =T91*15.42 -> 891.276 | Z91: =Y91*1.08 -> 962.57808 | AA91: =C91*Z91 -> 3850.3123 | AB91: =(T91+9)*15.42 -> 1030.056 | AC91: =AB91*1.08 -> 1112.4605 | AD91: =C91*AC91 -> 4449.8419 | AE91: =T91*22 -> 1271.6 | AF91: =AE91*1.08 -> 1373.328 | AG91: =C91*AF91 -> 5493.312 | AH91: =(T91+9)*22 -> 1469.6 | AI91: =AH91*1.08 -> 1587.168 | AJ91: =C91*AI91 -> 6348.672 | AK91: =Table1[[#This Row],[Total Selling Price / Unit (MVR)]]/Table1[[#This Row],[CNF / Unit (MVR)]] -> 2.5308767 | AL91: =Table1[[#This Row],[Total Selling Price / Unit (MVR)]]-(Table1[[#This Row],[GST 8% (MVR)]]+Table1[[#This Row],[Weighted max expense (MVR)]]) -> 170.77464 | AM91: =Table1[[#This Row],[Profit / Unit (MVR)]]*Table1[[#This Row],[Qty (NOS)]] -> 683.09856
A92: TOTAL - 89 line items | C92: 422 | D92: =SUM(D3:D91) -> 460.45 | E92: 2136.63 | F92: =SUM(F3:F91) -> 10129.9 | G92: =SUM(G3:G91) -> 46834.7 | J92: =L92-K92 -> 12124.509 | K92: =SUM(K3:K91) -> 14981.973 | L92: =SUM(L3:L91) -> 27106.481 | M92: =SUM(M3:M91) -> 2168.5185 | N92: =SUM(N3:N91) -> 29275 | O92: =SUM(O3:O91) -> 136161 | P92: =SUM(P3:P91) -> 0 | Q92: =SUM(Q3:Q91) -> 2099.9 | R92: =SUM(R3:R91) -> 46197.8 | ... U92: =SUM(U3:U91) -> 460.45 | V92: 10129.9 | W92: =SUM(W3:W91) -> 21941.4 | X92: =SUM(X3:X91) -> 29275 | Y92: =SUM(Y3:Y91) -> 34993.531 | Z92: =SUM(Z3:Z91) -> 37793.014 | AA92: =SUM(AA3:AA91) -> 170851.78 | AB92: =SUM(AB3:AB91) -> 47344.951 | AC92: =SUM(AC3:AC91) -> 51132.547 | AD92: =SUM(AD3:AD91) -> 233802.39 | ... AJ92: =SUM(AJ3:AJ91) -> 333570.2 | AK92: =(SUM(AK3:AK91)/89) -> 3.2987643 | AL92: =SUM(AL3:AL91) -> 12124.509 | AM92: =SUM(AM3:AM91) -> 56807.17
N93: Current Price | O93: Current Expected Revenue on 100% sales | P93: Final Price | R93: Kim Big List | S93: Lebelage Website Price w/o Shipping | V93: CNF | W93: Yesstyle Price w/o Shipping | Y93: (Lebelage selling price)*15.42 | Z93: Per Product | AA93: "Minimum Selling Price" Revenue on 100% sales | AB93: (Lebelage selling price + 9 usd shipping)*15.42 | AC93: Per Product | AD93: "Alt 1 Median Selling Price" Revenue on 100% sales | AE93: (Lebelage selling price)*22 | AF93: Per Product | AG93: "Alt 2 Median Selling Price" Revenue on 100% sales | AH93: (Lebelage selling price + 9usd shipping)*22 | AI93: Per Product | AJ93: "Maximum Selling Price" Revenue on 100% sales

Sheet Final Pricing Sheet
A1: Product Name (as invoiced) | B1: Category | C1: Qty (NOS) | D1: CNF / Unit (invoiced USD) | E1: CNF / Total Units (invoiced USD) | F1: CNF / Unit (MVR) | G1: CNF / Total Units (MVR) | H1: Lebelage Price w/o Shipping (MVR) | I1: Yesstyle Prices w/o Shipping (MVR) | J1: Base Profit / Unit (MVR) | K1: Weighted max expense (MVR) | L1: Selling price w/o GST (MVR) | M1: GST 8% (MVR) | N1: Total Selling Price / Unit (MVR) | O1: Total Selling Price / Total Units (MVR) | P1: Proposed New Listing Price Total Units (MVR) | Q1: Proposed New Listing Price / Unit (MVR)2 | R1: Proposed New Discounting Price / Unit (MVR) | S1: Lebelage Retail Price as per Kim's Catalogue (USD) | T1: Lebelage Retail Price as per Kim's Catalogue (MVR) | U1: Lebelage Price w/o Shipping (MVR)2 | V1: Lebelage Retail Price (USD) | W1: CNF / Unit (invoiced USD)2 | X1: CNF*2*Qty (MVR) | Y1: CNF*2 Rounded Off (MVR) | Z1: CNF*2 (MVR) | AA1: CNF / Unit (MVR)2 | AB1: Yesstyle Prices w/o Shipping (MVR)2 | AC1: Total Selling Price / Unit (MVR)2 | AD1: Minimum Selling Price w/o GST (MVR) | AE1: Minimum Selling Price w/ GST (MVR) | AF1: Minimum Selling Price w/ GST for Total Units (MVR) | AG1: Alt 1 Median Selling Price w/o GST (MVR) | AH1: Alt 1 Median Selling Price w/ GST (MVR) | AI1: Alt 1 Median Selling Price w/ GST for Total Units (MVR) | AJ1: Alt 2 Median Selling Price w/o GST (MVR)2 | AK1: Alt 2 Median Selling Price w/ GST (MVR)2 | AL1: Alt 2 Median Selling Price w/ GST for Total Units (MVR) | AM1: Maximum Selling Price w/o GST (MVR) | AN1: Maximum Selling Price w/ GST (MVR) | AO1: Maximum Selling Price w/ GST for Total Units (MVR)2 | AP1: Revenue to CNF ratio (%) | AQ1: Profit / Unit (MVR) | AR1: Total Profit (MVR)
N2: Current Price | O2: Current Expected Revenue on 100% sales | P2: Listing Price Total Products | Q2: Listing Price | R2: Discount Price | T2: Kim's Lebelage Catalogue | U2: Lebelage Website Price w/o Shipping | X2: Miniestmum Total Selling Price | Y2: Miniestmum Selling Price Rounded Off | Z2: Miniestmum Selling Price | AA2: CNF | AB2: Yesstyle Price w/o Shipping | AD2: (Lebelage selling price)*15.42 | AE2: Per Product | AF2: "Minimum Selling Price" Revenue on 100% sales | AG2: (Lebelage selling price + 9 usd shipping)*15.42 | AH2: Per Product | AI2: "Alt 1 Median Selling Price" Revenue on 100% sales | AJ2: (Lebelage selling price)*22 | AK2: Per Product | AL2: "Alt 2 Median Selling Price" Revenue on 100% sales | AM2: (Lebelage selling price + 9usd shipping)*22 | AN2: Per Product | AO2: "Maximum Selling Price" Revenue on 100% sales
A3: Aloe Bubble Chewy Foam 200ml | B3: Cleansing & Peeling | C3: 4 | D3: 7.06 | E3: 28.24 | F3: =D3*22 -> 155.32 | G3: =SUM(F3*C3) -> 621.28 | H3: 487.52 | I3: 322.74 | J3: =L3-K3 -> 140.65438 | K3: =(F3/$G$92)*Costs!$B$23 -> 229.71599 | L3: =N3/1.08 -> 370.37037 | M3: =L3*0.08 -> 29.62963 | N3: 400 | O3: =Table13[[#This Row],[Total Selling Price / Unit (MVR)]]*Table13[[#This Row],[Qty (NOS)]] -> 1600 | P3: =Q3*C3 -> 1600 | Q3: 400 | R3: =Q3*0.8 -> 320 | S3: 21.36 | T3: =S3*22 -> 469.92 | U3: 487.52 | V3: 22.16 | W3: 7.06 | X3: =Z3*C3 -> 1242.56 | Y3: 315 | Z3: =AA3*2 -> 310.64 | AA3: 155.32 | AB3: 322.74 | AC3: 400 | AD3: =V3*15.42 -> 341.7072 | AE3: =AD3*1.08 -> 369.04378 | AF3: =C3*AE3 -> 1476.1751 | AG3: =(V3+9)*15.42 -> 480.4872 | AH3: =AG3*1.08 -> 518.92618 | AI3: =C3*AH3 -> 2075.7047 | AJ3: =V3*22 -> 487.52 | AK3: =AJ3*1.08 -> 526.5216 | AL3: =C3*AK3 -> 2106.0864 | AM3: =(V3+9)*22 -> 685.52 | AN3: =AM3*1.08 -> 740.3616 | AO3: =C3*AN3 -> 2961.4464 | AP3: =Table13[[#This Row],[Total Selling Price / Unit (MVR)]]/Table13[[#This Row],[CNF / Unit (MVR)]] -> 2.5753284 | AQ3: =Table13[[#This Row],[Total Selling Price / Unit (MVR)]]-(Table13[[#This Row],[GST 8% (MVR)]]+Table13[[#This Row],[Weighted max expense (MVR)]]) -> 140.65438 | AR3: =Table13[[#This Row],[Profit / Unit (MVR)]]*Table13[[#This Row],[Qty (NOS)]] -> 562.61753
A4: AVOCADO REVITAL CLEANSING FOAM 180ml | B4: Cleansing & Peeling | C4: 4 | D4: 3.9 | E4: 15.6 | F4: =D4*22 -> 85.8 | G4: =SUM(F4*C4) -> 343.2 | H4: 119.02 | I4: 176.22 | J4: =L4-K4 -> 39.769733 | K4: =(F4/$G$92)*Costs!$B$23 -> 126.89693 | L4: =N4/1.08 -> 166.66667 | M4: =L4*0.08 -> 13.333333 | N4: 180 | O4: =Table13[[#This Row],[Total Selling Price / Unit (MVR)]]*Table13[[#This Row],[Qty (NOS)]] -> 720 | P4: =Q4*C4 -> 720 | Q4: 180 | R4: =Q4*0.8 -> 144 | S4: 5.21 | T4: =S4*22 -> 114.62 | U4: 119.02 | V4: 5.41 | W4: 3.9 | X4: =Z4*C4 -> 686.4 | Y4: 175 | Z4: =AA4*2 -> 171.6 | AA4: 85.8 | AB4: 176.22 | AC4: 180 | AD4: =V4*15.42 -> 83.4222 | AE4: =AD4*1.08 -> 90.095976 | AF4: =C4*AE4 -> 360.3839 | AG4: =(V4+9)*15.42 -> 222.2022 | AH4: =AG4*1.08 -> 239.97838 | AI4: =C4*AH4 -> 959.9135 | AJ4: =V4*22 -> 119.02 | AK4: =AJ4*1.08 -> 128.5416 | AL4: =C4*AK4 -> 514.1664 | AM4: =(V4+9)*22 -> 317.02 | AN4: =AM4*1.08 -> 342.3816 | AO4: =C4*AN4 -> 1369.5264 | AP4: =Table13[[#This Row],[Total Selling Price / Unit (MVR)]]/Table13[[#This Row],[CNF / Unit (MVR)]] -> 2.0979021 | AQ4: =Table13[[#This Row],[Total Selling Price / Unit (MVR)]]-(Table13[[#This Row],[GST 8% (MVR)]]+Table13[[#This Row],[Weighted max expense (MVR)]]) -> 39.769733 | AR4: =Table13[[#This Row],[Profit / Unit (MVR)]]*Table13[[#This Row],[Qty (NOS)]] -> 159.07893 | AT4: Total Revenue | AU4: =O92 -> 136161
A5: Centella Bubble Chewy Foam 200ml | B5: Cleansing & Peeling | C5: 7 | D5: 7.06 | E5: 49.42 | F5: =D5*22 -> 155.32 | G5: =SUM(F5*C5) -> 1087.24 | H5: 487.52 | I5: 322.74 | J5: =L5-K5 -> 140.65438 | K5: =(F5/$G$92)*Costs!$B$23 -> 229.71599 | L5: =N5/1.08 -> 370.37037 | M5: =L5*0.08 -> 29.62963 | N5: 400 | O5: =Table13[[#This Row],[Total Selling Price / Unit (MVR)]]*Table13[[#This Row],[Qty (NOS)]] -> 2800 | P5: =Q5*C5 -> 2800 | Q5: 400 | R5: =Q5*0.8 -> 320 | S5: 21.36 | T5: =S5*22 -> 469.92 | U5: 487.52 | V5: 22.16 | W5: 7.06 | X5: =Z5*C5 -> 2174.48 | Y5: 315 | Z5: =AA5*2 -> 310.64 | AA5: 155.32 | AB5: 322.74 | AC5: 400 | AD5: =V5*15.42 -> 341.7072 | AE5: =AD5*1.08 -> 369.04378 | AF5: =C5*AE5 -> 2583.3064 | AG5: =(V5+9)*15.42 -> 480.4872 | AH5: =AG5*1.08 -> 518.92618 | AI5: =C5*AH5 -> 3632.4832 | AJ5: =V5*22 -> 487.52 | AK5: =AJ5*1.08 -> 526.5216 | AL5: =C5*AK5 -> 3685.6512 | AM5: =(V5+9)*22 -> 685.52 | AN5: =AM5*1.08 -> 740.3616 | AO5: =C5*AN5 -> 5182.5312 | AP5: =Table13[[#This Row],[Total Selling Price / Unit (MVR)]]/Table13[[#This Row],[CNF / Unit (MVR)]] -> 2.5753284 | AQ5: =Table13[[#This Row],[Total Selling Price / Unit (MVR)]]-(Table13[[#This Row],[GST 8% (MVR)]]+Table13[[#This Row],[Weighted max expense (MVR)]]) -> 140.65438 | AR5: =Table13[[#This Row],[Profit / Unit (MVR)]]*Table13[[#This Row],[Qty (NOS)]] -> 984.58068 | AT5: Total Cost | AU5: =Costs!B23 -> 69267.83
A6: Charcoal Clay 2in1 Pack Foam 120ml | B6: Cleansing & Peeling | C6: 7 | D6: 4.24 | E6: 29.68 | F6: =D6*22 -> 93.28 | G6: =SUM(F6*C6) -> 652.96 | H6: 407.66 | I6: 162.36 | J6: =L6-K6 -> 186.11433 | K6: =(F6/$G$92)*Costs!$B$23 -> 137.95974 | L6: =N6/1.08 -> 324.07407 | M6: =L6*0.08 -> 25.925926 | N6: 350 | O6: =Table13[[#This Row],[Total Selling Price / Unit (MVR)]]*Table13[[#This Row],[Qty (NOS)]] -> 2450 | P6: =Q6*C6 -> 2240 | Q6: 320 | R6: =Q6*0.8 -> 256 | S6: 17.86 | T6: =S6*22 -> 392.92 | U6: 407.66 | V6: 18.53 | W6: 4.24 | X6: =Z6*C6 -> 1305.92 | Y6: 190 | Z6: =AA6*2 -> 186.56 | AA6: 93.28 | AB6: 162.36 | AC6: 350 | AD6: =V6*15.42 -> 285.7326 | AE6: =AD6*1.08 -> 308.59121 | AF6: =C6*AE6 -> 2160.1385 | AG6: =(V6+9)*15.42 -> 424.5126 | AH6: =AG6*1.08 -> 458.47361 | AI6: =C6*AH6 -> 3209.3153 | AJ6: =V6*22 -> 407.66 | AK6: =AJ6*1.08 -> 440.2728 | AL6: =C6*AK6 -> 3081.9096 | AM6: =(V6+9)*22 -> 605.66 | AN6: =AM6*1.08 -> 654.1128 | AO6: =C6*AN6 -> 4578.7896 | AP6: =Table13[[#This Row],[Total Selling Price / Unit (MVR)]]/Table13[[#This Row],[CNF / Unit (MVR)]] -> 3.7521441 | AQ6: =Table13[[#This Row],[Total Selling Price / Unit (MVR)]]-(Table13[[#This Row],[GST 8% (MVR)]]+Table13[[#This Row],[Weighted max expense (MVR)]]) -> 186.11433 | AR6: =Table13[[#This Row],[Profit / Unit (MVR)]]*Table13[[#This Row],[Qty (NOS)]] -> 1302.8003 | AT6: Total Profit | AU6: =AU4-AU5 -> 66893.17
A7: Charcoal Pore Clay Cleansing Foam 180ml | B7: Cleansing & Peeling | C7: 7 | D7: 3.9 | E7: 27.3 | F7: =D7*22 -> 85.8 | G7: =SUM(F7*C7) -> 600.6 | H7: 119.02 | I7: 176.22 | J7: =L7-K7 -> 39.769733 | K7: =(F7/$G$92)*Costs!$B$23 -> 126.89693 | L7: =N7/1.08 -> 166.66667 | M7: =L7*0.08 -> 13.333333 | N7: 180 | O7: =Table13[[#This Row],[Total Selling Price / Unit (MVR)]]*Table13[[#This Row],[Qty (NOS)]] -> 1260 | P7: =Q7*C7 -> 1260 | Q7: 180 | R7: =Q7*0.8 -> 144 | S7: 5.21 | T7: =S7*22 -> 114.62 | U7: 119.02 | V7: 5.41 | W7: 3.9 | X7: =Z7*C7 -> 1201.2 | Y7: 175 | Z7: =AA7*2 -> 171.6 | AA7: 85.8 | AB7: 176.22 | AC7: 180 | AD7: =V7*15.42 -> 83.4222 | AE7: =AD7*1.08 -> 90.095976 | AF7: =C7*AE7 -> 630.67183 | AG7: =(V7+9)*15.42 -> 222.2022 | AH7: =AG7*1.08 -> 239.97838 | AI7: =C7*AH7 -> 1679.8486 | AJ7: =V7*22 -> 119.02 | AK7: =AJ7*1.08 -> 128.5416 | AL7: =C7*AK7 -> 899.7912 | AM7: =(V7+9)*22 -> 317.02 | AN7: =AM7*1.08 -> 342.3816 | AO7: =C7*AN7 -> 2396.6712 | AP7: =Table13[[#This Row],[Total Selling Price / Unit (MVR)]]/Table13[[#This Row],[CNF / Unit (MVR)]] -> 2.0979021 | AQ7: =Table13[[#This Row],[Total Selling Price / Unit (MVR)]]-(Table13[[#This Row],[GST 8% (MVR)]]+Table13[[#This Row],[Weighted max expense (MVR)]]) -> 39.769733 | AR7: =Table13[[#This Row],[Profit / Unit (MVR)]]*Table13[[#This Row],[Qty (NOS)]] -> 278.38813 | AT7: Shipment Target Sales 60% | AU7: =AU4*60% -> 81696.6
A8: FRUIT PEACH&APPLE MANGO CLEANSING FOAM 100ml | B8: Cleansing & Peeling | C8: 8 | D8: 2.02 | E8: 16.16 | F8: =D8*22 -> 44.44 | G8: =SUM(F8*C8) -> 355.52 | H8: 63.58 | I8: 161.7 | J8: =L8-K8 -> 54.644266 | K8: =(F8/$G$92)*Costs!$B$23 -> 65.726104 | L8: =N8/1.08 -> 120.37037 | M8: =L8*0.08 -> 9.6296296 | N8: 130 | O8: =Table13[[#This Row],[Total Selling Price / Unit (MVR)]]*Table13[[#This Row],[Qty (NOS)]] -> 1040 | P8: =Q8*C8 -> 1280 | Q8: 160 | R8: =Q8*0.8 -> 128 | S8: 2.79 | T8: =S8*22 -> 61.38 | U8: 63.58 | V8: 2.89 | W8: 2.02 | X8: =Z8*C8 -> 711.04 | Y8: 90 | Z8: =AA8*2 -> 88.88 | AA8: 44.44 | AB8: 161.7 | AC8: 130 | AD8: =V8*15.42 -> 44.5638 | AE8: =AD8*1.08 -> 48.128904 | AF8: =C8*AE8 -> 385.03123 | AG8: =(V8+9)*15.42 -> 183.3438 | AH8: =AG8*1.08 -> 198.0113 | AI8: =C8*AH8 -> 1584.0904 | AJ8: =V8*22 -> 63.58 | AK8: =AJ8*1.08 -> 68.6664 | AL8: =C8*AK8 -> 549.3312 | AM8: =(V8+9)*22 -> 261.58 | AN8: =AM8*1.08 -> 282.5064 | AO8: =C8*AN8 -> 2260.0512 | AP8: =Table13[[#This Row],[Total Selling Price / Unit (MVR)]]/Table13[[#This Row],[CNF / Unit (MVR)]] -> 2.9252925 | AQ8: =Table13[[#This Row],[Total Selling Price / Unit (MVR)]]-(Table13[[#This Row],[GST 8% (MVR)]]+Table13[[#This Row],[Weighted max expense (MVR)]]) -> 54.644266 | AR8: =Table13[[#This Row],[Profit / Unit (MVR)]]*Table13[[#This Row],[Qty (NOS)]] -> 437.15413
A9: Glutathione Bubble Chewy Foam 200ml | B9: Cleansing & Peeling | C9: 4 | D9: 7.06 | E9: 28.24 | F9: =D9*22 -> 155.32 | G9: =SUM(F9*C9) -> 621.28 | H9: 487.52 | I9: 322.74 | J9: =L9-K9 -> 140.65438 | K9: =(F9/$G$92)*Costs!$B$23 -> 229.71599 | L9: =N9/1.08 -> 370.37037 | M9: =L9*0.08 -> 29.62963 | N9: 400 | O9: =Table13[[#This Row],[Total Selling Price / Unit (MVR)]]*Table13[[#This Row],[Qty (NOS)]] -> 1600 | P9: =Q9*C9 -> 1600 | Q9: 400 | R9: =Q9*0.8 -> 320 | S9: 21.36 | T9: =S9*22 -> 469.92 | U9: 487.52 | V9: 22.16 | W9: 7.06 | X9: =Z9*C9 -> 1242.56 | Y9: 315 | Z9: =AA9*2 -> 310.64 | AA9: 155.32 | AB9: 322.74 | AC9: 400 | AD9: =V9*15.42 -> 341.7072 | AE9: =AD9*1.08 -> 369.04378 | AF9: =C9*AE9 -> 1476.1751 | AG9: =(V9+9)*15.42 -> 480.4872 | AH9: =AG9*1.08 -> 518.92618 | AI9: =C9*AH9 -> 2075.7047 | AJ9: =V9*22 -> 487.52 | AK9: =AJ9*1.08 -> 526.5216 | AL9: =C9*AK9 -> 2106.0864 | AM9: =(V9+9)*22 -> 685.52 | AN9: =AM9*1.08 -> 740.3616 | AO9: =C9*AN9 -> 2961.4464 | AP9: =Table13[[#This Row],[Total Selling Price / Unit (MVR)]]/Table13[[#This Row],[CNF / Unit (MVR)]] -> 2.5753284 | AQ9: =Table13[[#This Row],[Total Selling Price / Unit (MVR)]]-(Table13[[#This Row],[GST 8% (MVR)]]+Table13[[#This Row],[Weighted max expense (MVR)]]) -> 140.65438 | AR9: =Table13[[#This Row],[Profit / Unit (MVR)]]*Table13[[#This Row],[Qty (NOS)]] -> 562.61753
A10: Glutinous Rice Clay 2in1 Pack Foam 120ml | B10: Cleansing & Peeling | C10: 4 | D10: 4.24 | E10: 16.96 | F10: =D10*22 -> 93.28 | G10: =SUM(F10*C10) -> 373.12 | H10: 407.66 | I10: 162.36 | J10: =L10-K10 -> 186.11433 | K10: =(F10/$G$92)*Costs!$B$23 -> 137.95974 | L10: =N10/1.08 -> 324.07407 | M10: =L10*0.08 -> 25.925926 | N10: 350 | O10: =Table13[[#This Row],[Total Selling Price / Unit (MVR)]]*Table13[[#This Row],[Qty (NOS)]] -> 1400 | P10: =Q10*C10 -> 1280 | Q10: 320 | R10: =Q10*0.8 -> 256 | S10: 17.86 | T10: =S10*22 -> 392.92 | U10: 407.66 | V10: 18.53 | W10: 4.24 | X10: =Z10*C10 -> 746.24 | Y10: 190 | Z10: =AA10*2 -> 186.56 | AA10: 93.28 | AB10: 162.36 | AC10: 350 | AD10: =V10*15.42 -> 285.7326 | AE10: =AD10*1.08 -> 308.59121 | AF10: =C10*AE10 -> 1234.3648 | AG10: =(V10+9)*15.42 -> 424.5126 | AH10: =AG10*1.08 -> 458.47361 | AI10: =C10*AH10 -> 1833.8944 | AJ10: =V10*22 -> 407.66 | AK10: =AJ10*1.08 -> 440.2728 | AL10: =C10*AK10 -> 1761.0912 | AM10: =(V10+9)*22 -> 605.66 | AN10: =AM10*1.08 -> 654.1128 | AO10: =C10*AN10 -> 2616.4512 | AP10: =Table13[[#This Row],[Total Selling Price / Unit (MVR)]]/Table13[[#This Row],[CNF / Unit (MVR)]] -> 3.7521441 | AQ10: =Table13[[#This Row],[Total Selling Price / Unit (MVR)]]-(Table13[[#This Row],[GST 8% (MVR)]]+Table13[[#This Row],[Weighted max expense (MVR)]]) -> 186.11433 | AR10: =Table13[[#This Row],[Profit / Unit (MVR)]]*Table13[[#This Row],[Qty (NOS)]] -> 744.45732
A11: Lemon Brightening Cleansing Foam 180ml | B11: Cleansing & Peeling | C11: 4 | D11: 3.9 | E11: 15.6 | F11: =D11*22 -> 85.8 | G11: =SUM(F11*C11) -> 343.2 | H11: 119.02 | I11: 176.22 | J11: =L11-K11 -> 39.769733 | K11: =(F11/$G$92)*Costs!$B$23 -> 126.89693 | L11: =N11/1.08 -> 166.66667 | M11: =L11*0.08 -> 13.333333 | N11: 180 | O11: =Table13[[#This Row],[Total Selling Price / Unit (MVR)]]*Table13[[#This Row],[Qty (NOS)]] -> 720 | P11: =Q11*C11 -> 720 | Q11: 180 | R11: =Q11*0.8 -> 144 | S11: 5.21 | T11: =S11*22 -> 114.62 | U11: 119.02 | V11: 5.41 | W11: 3.9 | X11: =Z11*C11 -> 686.4 | Y11: 175 | Z11: =AA11*2 -> 171.6 | AA11: 85.8 | AB11: 176.22 | AC11: 180 | AD11: =V11*15.42 -> 83.4222 | AE11: =AD11*1.08 -> 90.095976 | AF11: =C11*AE11 -> 360.3839 | AG11: =(V11+9)*15.42 -> 222.2022 | AH11: =AG11*1.08 -> 239.97838 | AI11: =C11*AH11 -> 959.9135 | AJ11: =V11*22 -> 119.02 | AK11: =AJ11*1.08 -> 128.5416 | AL11: =C11*AK11 -> 514.1664 | AM11: =(V11+9)*22 -> 317.02 | AN11: =AM11*1.08 -> 342.3816 | AO11: =C11*AN11 -> 1369.5264 | AP11: =Table13[[#This Row],[Total Selling Price / Unit (MVR)]]/Table13[[#This Row],[CNF / Unit (MVR)]] -> 2.0979021 | AQ11: =Table13[[#This Row],[Total Selling Price / Unit (MVR)]]-(Table13[[#This Row],[GST 8% (MVR)]]+Table13[[#This Row],[Weighted max expense (MVR)]]) -> 39.769733 | AR11: =Table13[[#This Row],[Profit / Unit (MVR)]]*Table13[[#This Row],[Qty (NOS)]] -> 159.07893
A12: Panthenol Bubble Chewy Foam 200ml | B12: Cleansing & Peeling | C12: 4 | D12: 7.06 | E12: 28.24 | F12: =D12*22 -> 155.32 | G12: =SUM(F12*C12) -> 621.28 | H12: 487.52 | I12: 322.74 | J12: =L12-K12 -> 140.65438 | K12: =(F12/$G$92)*Costs!$B$23 -> 229.71599 | L12: =N12/1.08 -> 370.37037 | M12: =L12*0.08 -> 29.62963 | N12: 400 | O12: =Table13[[#This Row],[Total Selling Price / Unit (MVR)]]*Table13[[#This Row],[Qty (NOS)]] -> 1600 | P12: =Q12*C12 -> 1600 | Q12: 400 | R12: =Q12*0.8 -> 320 | S12: 21.36 | T12: =S12*22 -> 469.92 | U12: 487.52 | V12: 22.16 | W12: 7.06 | X12: =Z12*C12 -> 1242.56 | Y12: 315 | Z12: =AA12*2 -> 310.64 | AA12: 155.32 | AB12: 322.74 | AC12: 400 | AD12: =V12*15.42 -> 341.7072 | AE12: =AD12*1.08 -> 369.04378 | AF12: =C12*AE12 -> 1476.1751 | AG12: =(V12+9)*15.42 -> 480.4872 | AH12: =AG12*1.08 -> 518.92618 | AI12: =C12*AH12 -> 2075.7047 | AJ12: =V12*22 -> 487.52 | AK12: =AJ12*1.08 -> 526.5216 | AL12: =C12*AK12 -> 2106.0864 | AM12: =(V12+9)*22 -> 685.52 | AN12: =AM12*1.08 -> 740.3616 | AO12: =C12*AN12 -> 2961.4464 | AP12: =Table13[[#This Row],[Total Selling Price / Unit (MVR)]]/Table13[[#This Row],[CNF / Unit (MVR)]] -> 2.5753284 | AQ12: =Table13[[#This Row],[Total Selling Price / Unit (MVR)]]-(Table13[[#This Row],[GST 8% (MVR)]]+Table13[[#This Row],[Weighted max expense (MVR)]]) -> 140.65438 | AR12: =Table13[[#This Row],[Profit / Unit (MVR)]]*Table13[[#This Row],[Qty (NOS)]] -> 562.61753
A13: PDRN Bubble Chewy Foam 200ml | B13: Cleansing & Peeling | C13: 4 | D13: 7.06 | E13: 28.24 | F13: =D13*22 -> 155.32 | G13: =SUM(F13*C13) -> 621.28 | H13: 487.52 | I13: 322.74 | J13: =L13-K13 -> 140.65438 | K13: =(F13/$G$92)*Costs!$B$23 -> 229.71599 | L13: =N13/1.08 -> 370.37037 | M13: =L13*0.08 -> 29.62963 | N13: 400 | O13: =Table13[[#This Row],[Total Selling Price / Unit (MVR)]]*Table13[[#This Row],[Qty (NOS)]] -> 1600 | P13: =Q13*C13 -> 1600 | Q13: 400 | R13: =Q13*0.8 -> 320 | S13: 21.36 | T13: =S13*22 -> 469.92 | U13: 487.52 | V13: 22.16 | W13: 7.06 | X13: =Z13*C13 -> 1242.56 | Y13: 315 | Z13: =AA13*2 -> 310.64 | AA13: 155.32 | AB13: 322.74 | AC13: 400 | AD13: =V13*15.42 -> 341.7072 | AE13: =AD13*1.08 -> 369.04378 | AF13: =C13*AE13 -> 1476.1751 | AG13: =(V13+9)*15.42 -> 480.4872 | AH13: =AG13*1.08 -> 518.92618 | AI13: =C13*AH13 -> 2075.7047 | AJ13: =V13*22 -> 487.52 | AK13: =AJ13*1.08 -> 526.5216 | AL13: =C13*AK13 -> 2106.0864 | AM13: =(V13+9)*22 -> 685.52 | AN13: =AM13*1.08 -> 740.3616 | AO13: =C13*AN13 -> 2961.4464 | AP13: =Table13[[#This Row],[Total Selling Price / Unit (MVR)]]/Table13[[#This Row],[CNF / Unit (MVR)]] -> 2.5753284 | AQ13: =Table13[[#This Row],[Total Selling Price / Unit (MVR)]]-(Table13[[#This Row],[GST 8% (MVR)]]+Table13[[#This Row],[Weighted max expense (MVR)]]) -> 140.65438 | AR13: =Table13[[#This Row],[Profit / Unit (MVR)]]*Table13[[#This Row],[Qty (NOS)]] -> 562.61753
A14: Real Sensation Blemish Cleansing Foam 1+1 150ml x 2 | B14: Cleansing & Peeling | C14: 8 | D14: 6.84 | E14: 54.72 | F14: =D14*22 -> 150.48 | G14: =SUM(F14*C14) -> 1203.84 | H14: N/A | I14: 403.04 | J14: =L14-K14 -> 180.22008 | K14: =(F14/$G$92)*Costs!$B$23 -> 222.5577 | L14: =N14/1.08 -> 402.77778 | M14: =L14*0.08 -> 32.222222 | N14: 435 | O14: =Table13[[#This Row],[Total Selling Price / Unit (MVR)]]*Table13[[#This Row],[Qty (NOS)]] -> 3480 | P14: =Q14*C14 -> 3480 | Q14: 435 | R14: =Q14*0.8 -> 348 | S14: 21.36 | T14: =S14*22 -> 469.92 | U14: N/A | V14: 22.16 | W14: 6.84 | X14: =Z14*C14 -> 2407.68 | Y14: 305 | Z14: =AA14*2 -> 300.96 | AA14: 150.48 | AB14: 403.04 | AC14: 435 | AD14: =V14*15.42 -> 341.7072 | AE14: =AD14*1.08 -> 369.04378 | AF14: =C14*AE14 -> 2952.3502 | AG14: =(V14+9)*15.42 -> 480.4872 | AH14: =AG14*1.08 -> 518.92618 | AI14: =C14*AH14 -> 4151.4094 | AJ14: =V14*22 -> 487.52 | AK14: =AJ14*1.08 -> 526.5216 | AL14: =C14*AK14 -> 4212.1728 | AM14: =(V14+9)*22 -> 685.52 | AN14: =AM14*1.08 -> 740.3616 | AO14: =C14*AN14 -> 5922.8928 | AP14: =Table13[[#This Row],[Total Selling Price / Unit (MVR)]]/Table13[[#This Row],[CNF / Unit (MVR)]] -> 2.8907496 | AQ14: =Table13[[#This Row],[Total Selling Price / Unit (MVR)]]-(Table13[[#This Row],[GST 8% (MVR)]]+Table13[[#This Row],[Weighted max expense (MVR)]]) -> 180.22008 | AR14: =Table13[[#This Row],[Profit / Unit (MVR)]]*Table13[[#This Row],[Qty (NOS)]] -> 1441.7606
A15: Real Sensation Pore Cleansing Foam 1+1 150ml x 2 | B15: Cleansing & Peeling | C15: 6 | D15: 6.84 | E15: 41.04 | F15: =D15*22 -> 150.48 | G15: =SUM(F15*C15) -> 902.88 | H15: N/A | I15: 403.04 | J15: =L15-K15 -> 180.22008 | K15: =(F15/$G$92)*Costs!$B$23 -> 222.5577 | L15: =N15/1.08 -> 402.77778 | M15: =L15*0.08 -> 32.222222 | N15: 435 | O15: =Table13[[#This Row],[Total Selling Price / Unit (MVR)]]*Table13[[#This Row],[Qty (NOS)]] -> 2610 | P15: =Q15*C15 -> 2610 | Q15: 435 | R15: =Q15*0.8 -> 348 | S15: 21.36 | T15: =S15*22 -> 469.92 | U15: N/A | V15: 22.16 | W15: 6.84 | X15: =Z15*C15 -> 1805.76 | Y15: 305 | Z15: =AA15*2 -> 300.96 | AA15: 150.48 | AB15: 403.04 | AC15: 435 | AD15: =V15*15.42 -> 341.7072 | AE15: =AD15*1.08 -> 369.04378 | AF15: =C15*AE15 -> 2214.2627 | AG15: =(V15+9)*15.42 -> 480.4872 | AH15: =AG15*1.08 -> 518.92618 | AI15: =C15*AH15 -> 3113.5571 | AJ15: =V15*22 -> 487.52 | AK15: =AJ15*1.08 -> 526.5216 | AL15: =C15*AK15 -> 3159.1296 | AM15: =(V15+9)*22 -> 685.52 | AN15: =AM15*1.08 -> 740.3616 | AO15: =C15*AN15 -> 4442.1696 | AP15: =Table13[[#This Row],[Total Selling Price / Unit (MVR)]]/Table13[[#This Row],[CNF / Unit (MVR)]] -> 2.8907496 | AQ15: =Table13[[#This Row],[Total Selling Price / Unit (MVR)]]-(Table13[[#This Row],[GST 8% (MVR)]]+Table13[[#This Row],[Weighted max expense (MVR)]]) -> 180.22008 | AR15: =Table13[[#This Row],[Profit / Unit (MVR)]]*Table13[[#This Row],[Qty (NOS)]] -> 1081.3205
A16: Retinol Bubble Chewy Foam 200ml | B16: Cleansing & Peeling | C16: 4 | D16: 7.06 | E16: 28.24 | F16: =D16*22 -> 155.32 | G16: =SUM(F16*C16) -> 621.28 | H16: 487.52 | I16: 322.74 | J16: =L16-K16 -> 140.65438 | K16: =(F16/$G$92)*Costs!$B$23 -> 229.71599 | L16: =N16/1.08 -> 370.37037 | M16: =L16*0.08 -> 29.62963 | N16: 400 | O16: =Table13[[#This Row],[Total Selling Price / Unit (MVR)]]*Table13[[#This Row],[Qty (NOS)]] -> 1600 | P16: =Q16*C16 -> 1600 | Q16: 400 | R16: =Q16*0.8 -> 320 | S16: 21.36 | T16: =S16*22 -> 469.92 | U16: 487.52 | V16: 22.16 | W16: 7.06 | X16: =Z16*C16 -> 1242.56 | Y16: 315 | Z16: =AA16*2 -> 310.64 | AA16: 155.32 | AB16: 322.74 | AC16: 400 | AD16: =V16*15.42 -> 341.7072 | AE16: =AD16*1.08 -> 369.04378 | AF16: =C16*AE16 -> 1476.1751 | AG16: =(V16+9)*15.42 -> 480.4872 | AH16: =AG16*1.08 -> 518.92618 | AI16: =C16*AH16 -> 2075.7047 | AJ16: =V16*22 -> 487.52 | AK16: =AJ16*1.08 -> 526.5216 | AL16: =C16*AK16 -> 2106.0864 | AM16: =(V16+9)*22 -> 685.52 | AN16: =AM16*1.08 -> 740.3616 | AO16: =C16*AN16 -> 2961.4464 | AP16: =Table13[[#This Row],[Total Selling Price / Unit (MVR)]]/Table13[[#This Row],[CNF / Unit (MVR)]] -> 2.5753284 | AQ16: =Table13[[#This Row],[Total Selling Price / Unit (MVR)]]-(Table13[[#This Row],[GST 8% (MVR)]]+Table13[[#This Row],[Weighted max expense (MVR)]]) -> 140.65438 | AR16: =Table13[[#This Row],[Profit / Unit (MVR)]]*Table13[[#This Row],[Qty (NOS)]] -> 562.61753
A17: Soybean Clay 2in1 Pack Foam 120ml | B17: Cleansing & Peeling | C17: 4 | D17: 4.24 | E17: 16.96 | F17: =D17*22 -> 93.28 | G17: =SUM(F17*C17) -> 373.12 | H17: 407.66 | I17: 162.36 | J17: =L17-K17 -> 186.11433 | K17: =(F17/$G$92)*Costs!$B$23 -> 137.95974 | L17: =N17/1.08 -> 324.07407 | M17: =L17*0.08 -> 25.925926 | N17: 350 | O17: =Table13[[#This Row],[Total Selling Price / Unit (MVR)]]*Table13[[#This Row],[Qty (NOS)]] -> 1400 | P17: =Q17*C17 -> 1280 | Q17: 320 | R17: =Q17*0.8 -> 256 | S17: 17.86 | T17: =S17*22 -> 392.92 | U17: 407.66 | V17: 18.53 | W17: 4.24 | X17: =Z17*C17 -> 746.24 | Y17: 190 | Z17: =AA17*2 -> 186.56 | AA17: 93.28 | AB17: 162.36 | AC17: 350 | AD17: =V17*15.42 -> 285.7326 | AE17: =AD17*1.08 -> 308.59121 | AF17: =C17*AE17 -> 1234.3648 | AG17: =(V17+9)*15.42 -> 424.5126 | AH17: =AG17*1.08 -> 458.47361 | AI17: =C17*AH17 -> 1833.8944 | AJ17: =V17*22 -> 407.66 | AK17: =AJ17*1.08 -> 440.2728 | AL17: =C17*AK17 -> 1761.0912 | AM17: =(V17+9)*22 -> 605.66 | AN17: =AM17*1.08 -> 654.1128 | AO17: =C17*AN17 -> 2616.4512 | AP17: =Table13[[#This Row],[Total Selling Price / Unit (MVR)]]/Table13[[#This Row],[CNF / Unit (MVR)]] -> 3.7521441 | AQ17: =Table13[[#This Row],[Total Selling Price / Unit (MVR)]]-(Table13[[#This Row],[GST 8% (MVR)]]+Table13[[#This Row],[Weighted max expense (MVR)]]) -> 186.11433 | AR17: =Table13[[#This Row],[Profit / Unit (MVR)]]*Table13[[#This Row],[Qty (NOS)]] -> 744.45732
A18: Ssook/Mugwort Clay 2in1 Pack Foam 120ml | B18: Cleansing & Peeling | C18: 4 | D18: 4.24 | E18: 16.96 | F18: =D18*22 -> 93.28 | G18: =SUM(F18*C18) -> 373.12 | H18: 407.66 | I18: 162.36 | J18: =L18-K18 -> 186.11433 | K18: =(F18/$G$92)*Costs!$B$23 -> 137.95974 | L18: =N18/1.08 -> 324.07407 | M18: =L18*0.08 -> 25.925926 | N18: 350 | O18: =Table13[[#This Row],[Total Selling Price / Unit (MVR)]]*Table13[[#This Row],[Qty (NOS)]] -> 1400 | P18: =Q18*C18 -> 1280 | Q18: 320 | R18: =Q18*0.8 -> 256 | S18: 17.86 | T18: =S18*22 -> 392.92 | U18: 407.66 | V18: 18.53 | W18: 4.24 | X18: =Z18*C18 -> 746.24 | Y18: 190 | Z18: =AA18*2 -> 186.56 | AA18: 93.28 | AB18: 162.36 | AC18: 350 | AD18: =V18*15.42 -> 285.7326 | AE18: =AD18*1.08 -> 308.59121 | AF18: =C18*AE18 -> 1234.3648 | AG18: =(V18+9)*15.42 -> 424.5126 | AH18: =AG18*1.08 -> 458.47361 | AI18: =C18*AH18 -> 1833.8944 | AJ18: =V18*22 -> 407.66 | AK18: =AJ18*1.08 -> 440.2728 | AL18: =C18*AK18 -> 1761.0912 | AM18: =(V18+9)*22 -> 605.66 | AN18: =AM18*1.08 -> 654.1128 | AO18: =C18*AN18 -> 2616.4512 | AP18: =Table13[[#This Row],[Total Selling Price / Unit (MVR)]]/Table13[[#This Row],[CNF / Unit (MVR)]] -> 3.7521441 | AQ18: =Table13[[#This Row],[Total Selling Price / Unit (MVR)]]-(Table13[[#This Row],[GST 8% (MVR)]]+Table13[[#This Row],[Weighted max expense (MVR)]]) -> 186.11433 | AR18: =Table13[[#This Row],[Profit / Unit (MVR)]]*Table13[[#This Row],[Qty (NOS)]] -> 744.45732
A19: Vitamin C + Turmeric Bubble Chewy Foam 200ml | B19: Cleansing & Peeling | C19: 4 | D19: 7.06 | E19: 28.24 | F19: =D19*22 -> 155.32 | G19: =SUM(F19*C19) -> 621.28 | H19: 487.52 | I19: 322.74 | J19: =L19-K19 -> 140.65438 | K19: =(F19/$G$92)*Costs!$B$23 -> 229.71599 | L19: =N19/1.08 -> 370.37037 | M19: =L19*0.08 -> 29.62963 | N19: 400 | O19: =Table13[[#This Row],[Total Selling Price / Unit (MVR)]]*Table13[[#This Row],[Qty (NOS)]] -> 1600 | P19: =Q19*C19 -> 1600 | Q19: 400 | R19: =Q19*0.8 -> 320 | S19: 21.36 | T19: =S19*22 -> 469.92 | U19: 487.52 | V19: 22.16 | W19: 7.06 | X19: =Z19*C19 -> 1242.56 | Y19: 315 | Z19: =AA19*2 -> 310.64 | AA19: 155.32 | AB19: 322.74 | AC19: 400 | AD19: =V19*15.42 -> 341.7072 | AE19: =AD19*1.08 -> 369.04378 | AF19: =C19*AE19 -> 1476.1751 | AG19: =(V19+9)*15.42 -> 480.4872 | AH19: =AG19*1.08 -> 518.92618 | AI19: =C19*AH19 -> 2075.7047 | AJ19: =V19*22 -> 487.52 | AK19: =AJ19*1.08 -> 526.5216 | AL19: =C19*AK19 -> 2106.0864 | AM19: =(V19+9)*22 -> 685.52 | AN19: =AM19*1.08 -> 740.3616 | AO19: =C19*AN19 -> 2961.4464 | AP19: =Table13[[#This Row],[Total Selling Price / Unit (MVR)]]/Table13[[#This Row],[CNF / Unit (MVR)]] -> 2.5753284 | AQ19: =Table13[[#This Row],[Total Selling Price / Unit (MVR)]]-(Table13[[#This Row],[GST 8% (MVR)]]+Table13[[#This Row],[Weighted max expense (MVR)]]) -> 140.65438 | AR19: =Table13[[#This Row],[Profit / Unit (MVR)]]*Table13[[#This Row],[Qty (NOS)]] -> 562.61753
A20: Collagen + Green Tea Moisture Cream 70ml | B20: Creams & Moisturizers | C20: 4 | D20: 4.57 | E20: 18.28 | F20: =D20*22 -> 100.54 | G20: =SUM(F20*C20) -> 402.16 | H20: 407.66 | I20: 275 | J20: =L20-K20 -> 156.85838 | K20: =(F20/$G$92)*Costs!$B$23 -> 148.69718 | L20: =N20/1.08 -> 305.55556 | M20: =L20*0.08 -> 24.444444 | N20: 330 | O20: =Table13[[#This Row],[Total Selling Price / Unit (MVR)]]*Table13[[#This Row],[Qty (NOS)]] -> 1320 | P20: =Q20*C20 -> 1200 | Q20: 300 | R20: =Q20*0.8 -> 240 | S20: 7.14 | T20: =S20*22 -> 157.08 | U20: 407.66 | V20: 18.53 | W20: 4.57 | X20: =Z20*C20 -> 804.32 | Y20: 205 | Z20: =AA20*2 -> 201.08 | AA20: 100.54 | AB20: 275 | AC20: 330 | AD20: =V20*15.42 -> 285.7326 | AE20: =AD20*1.08 -> 308.59121 | AF20: =C20*AE20 -> 1234.3648 | AG20: =(V20+9)*15.42 -> 424.5126 | AH20: =AG20*1.08 -> 458.47361 | AI20: =C20*AH20 -> 1833.8944 | AJ20: =V20*22 -> 407.66 | AK20: =AJ20*1.08 -> 440.2728 | AL20: =C20*AK20 -> 1761.0912 | AM20: =(V20+9)*22 -> 605.66 | AN20: =AM20*1.08 -> 654.1128 | AO20: =C20*AN20 -> 2616.4512 | AP20: =Table13[[#This Row],[Total Selling Price / Unit (MVR)]]/Table13[[#This Row],[CNF / Unit (MVR)]] -> 3.2822757 | AQ20: =Table13[[#This Row],[Total Selling Price / Unit (MVR)]]-(Table13[[#This Row],[GST 8% (MVR)]]+Table13[[#This Row],[Weighted max expense (MVR)]]) -> 156.85838 | AR20: =Table13[[#This Row],[Profit / Unit (MVR)]]*Table13[[#This Row],[Qty (NOS)]] -> 627.43352
A21: Dr. AQUA CURE CREAM 70ml | B21: Creams & Moisturizers | C21: 4 | D21: 4.66 | E21: 18.64 | F21: =D21*22 -> 102.52 | G21: =SUM(F21*C21) -> 410.08 | H21: 211.86 | I21: 242.44 | J21: =L21-K21 -> 56.707767 | K21: =(F21/$G$92)*Costs!$B$23 -> 151.62557 | L21: =N21/1.08 -> 208.33333 | M21: =L21*0.08 -> 16.666667 | N21: 225 | O21: =Table13[[#This Row],[Total Selling Price / Unit (MVR)]]*Table13[[#This Row],[Qty (NOS)]] -> 900 | P21: =Q21*C21 -> 1200 | Q21: 300 | R21: =Q21*0.8 -> 240 | S21: 17.86 | T21: =S21*22 -> 392.92 | U21: 211.86 | V21: 9.63 | W21: 4.66 | X21: =Z21*C21 -> 820.16 | Y21: 205 | Z21: =AA21*2 -> 205.04 | AA21: 102.52 | AB21: 242.44 | AC21: 225 | AD21: =V21*15.42 -> 148.4946 | AE21: =AD21*1.08 -> 160.37417 | AF21: =C21*AE21 -> 641.49667 | AG21: =(V21+9)*15.42 -> 287.2746 | AH21: =AG21*1.08 -> 310.25657 | AI21: =C21*AH21 -> 1241.0263 | AJ21: =V21*22 -> 211.86 | AK21: =AJ21*1.08 -> 228.8088 | AL21: =C21*AK21 -> 915.2352 | AM21: =(V21+9)*22 -> 409.86 | AN21: =AM21*1.08 -> 442.6488 | AO21: =C21*AN21 -> 1770.5952 | AP21: =Table13[[#This Row],[Total Selling Price / Unit (MVR)]]/Table13[[#This Row],[CNF / Unit (MVR)]] -> 2.1946937 | AQ21: =Table13[[#This Row],[Total Selling Price / Unit (MVR)]]-(Table13[[#This Row],[GST 8% (MVR)]]+Table13[[#This Row],[Weighted max expense (MVR)]]) -> 56.707767 | AR21: =Table13[[#This Row],[Profit / Unit (MVR)]]*Table13[[#This Row],[Qty (NOS)]] -> 226.83107
A22: Dr. Madecassoside Cure Cream 70ml | B22: Creams & Moisturizers | C22: 7 | D22: 4.66 | E22: 32.62 | F22: =D22*22 -> 102.52 | G22: =SUM(F22*C22) -> 717.64 | H22: 211.86 | I22: 242.44 | J22: =L22-K22 -> 56.707767 | K22: =(F22/$G$92)*Costs!$B$23 -> 151.62557 | L22: =N22/1.08 -> 208.33333 | M22: =L22*0.08 -> 16.666667 | N22: 225 | O22: =Table13[[#This Row],[Total Selling Price / Unit (MVR)]]*Table13[[#This Row],[Qty (NOS)]] -> 1575 | P22: =Q22*C22 -> 2100 | Q22: 300 | R22: =Q22*0.8 -> 240 | S22: 17.86 | T22: =S22*22 -> 392.92 | U22: 211.86 | V22: 9.63 | W22: 4.66 | X22: =Z22*C22 -> 1435.28 | Y22: 205 | Z22: =AA22*2 -> 205.04 | AA22: 102.52 | AB22: 242.44 | AC22: 225 | AD22: =V22*15.42 -> 148.4946 | AE22: =AD22*1.08 -> 160.37417 | AF22: =C22*AE22 -> 1122.6192 | AG22: =(V22+9)*15.42 -> 287.2746 | AH22: =AG22*1.08 -> 310.25657 | AI22: =C22*AH22 -> 2171.796 | AJ22: =V22*22 -> 211.86 | AK22: =AJ22*1.08 -> 228.8088 | AL22: =C22*AK22 -> 1601.6616 | AM22: =(V22+9)*22 -> 409.86 | AN22: =AM22*1.08 -> 442.6488 | AO22: =C22*AN22 -> 3098.5416 | AP22: =Table13[[#This Row],[Total Selling Price / Unit (MVR)]]/Table13[[#This Row],[CNF / Unit (MVR)]] -> 2.1946937 | AQ22: =Table13[[#This Row],[Total Selling Price / Unit (MVR)]]-(Table13[[#This Row],[GST 8% (MVR)]]+Table13[[#This Row],[Weighted max expense (MVR)]]) -> 56.707767 | AR22: =Table13[[#This Row],[Profit / Unit (MVR)]]*Table13[[#This Row],[Qty (NOS)]] -> 396.95437
A23: Dr. Peptide Cure Cream 70ml | B23: Creams & Moisturizers | C23: 4 | D23: 4.66 | E23: 18.64 | F23: =D23*22 -> 102.52 | G23: =SUM(F23*C23) -> 410.08 | H23: 211.86 | I23: 242.44 | J23: =L23-K23 -> 56.707767 | K23: =(F23/$G$92)*Costs!$B$23 -> 151.62557 | L23: =N23/1.08 -> 208.33333 | M23: =L23*0.08 -> 16.666667 | N23: 225 | O23: =Table13[[#This Row],[Total Selling Price / Unit (MVR)]]*Table13[[#This Row],[Qty (NOS)]] -> 900 | P23: =Q23*C23 -> 1200 | Q23: 300 | R23: =Q23*0.8 -> 240 | S23: 17.86 | T23: =S23*22 -> 392.92 | U23: 211.86 | V23: 9.63 | W23: 4.66 | X23: =Z23*C23 -> 820.16 | Y23: 205 | Z23: =AA23*2 -> 205.04 | AA23: 102.52 | AB23: 242.44 | AC23: 225 | AD23: =V23*15.42 -> 148.4946 | AE23: =AD23*1.08 -> 160.37417 | AF23: =C23*AE23 -> 641.49667 | AG23: =(V23+9)*15.42 -> 287.2746 | AH23: =AG23*1.08 -> 310.25657 | AI23: =C23*AH23 -> 1241.0263 | AJ23: =V23*22 -> 211.86 | AK23: =AJ23*1.08 -> 228.8088 | AL23: =C23*AK23 -> 915.2352 | AM23: =(V23+9)*22 -> 409.86 | AN23: =AM23*1.08 -> 442.6488 | AO23: =C23*AN23 -> 1770.5952 | AP23: =Table13[[#This Row],[Total Selling Price / Unit (MVR)]]/Table13[[#This Row],[CNF / Unit (MVR)]] -> 2.1946937 | AQ23: =Table13[[#This Row],[Total Selling Price / Unit (MVR)]]-(Table13[[#This Row],[GST 8% (MVR)]]+Table13[[#This Row],[Weighted max expense (MVR)]]) -> 56.707767 | AR23: =Table13[[#This Row],[Profit / Unit (MVR)]]*Table13[[#This Row],[Qty (NOS)]] -> 226.83107
A24: Dr. Vitamin C Cure Cream 70ml | B24: Creams & Moisturizers | C24: 4 | D24: 4.66 | E24: 18.64 | F24: =D24*22 -> 102.52 | G24: =SUM(F24*C24) -> 410.08 | H24: 211.86 | I24: 242.44 | J24: =L24-K24 -> 56.707767 | K24: =(F24/$G$92)*Costs!$B$23 -> 151.62557 | L24: =N24/1.08 -> 208.33333 | M24: =L24*0.08 -> 16.666667 | N24: 225 | O24: =Table13[[#This Row],[Total Selling Price / Unit (MVR)]]*Table13[[#This Row],[Qty (NOS)]] -> 900 | P24: =Q24*C24 -> 1200 | Q24: 300 | R24: =Q24*0.8 -> 240 | S24: 17.86 | T24: =S24*22 -> 392.92 | U24: 211.86 | V24: 9.63 | W24: 4.66 | X24: =Z24*C24 -> 820.16 | Y24: 205 | Z24: =AA24*2 -> 205.04 | AA24: 102.52 | AB24: 242.44 | AC24: 225 | AD24: =V24*15.42 -> 148.4946 | AE24: =AD24*1.08 -> 160.37417 | AF24: =C24*AE24 -> 641.49667 | AG24: =(V24+9)*15.42 -> 287.2746 | AH24: =AG24*1.08 -> 310.25657 | AI24: =C24*AH24 -> 1241.0263 | AJ24: =V24*22 -> 211.86 | AK24: =AJ24*1.08 -> 228.8088 | AL24: =C24*AK24 -> 915.2352 | AM24: =(V24+9)*22 -> 409.86 | AN24: =AM24*1.08 -> 442.6488 | AO24: =C24*AN24 -> 1770.5952 | AP24: =Table13[[#This Row],[Total Selling Price / Unit (MVR)]]/Table13[[#This Row],[CNF / Unit (MVR)]] -> 2.1946937 | AQ24: =Table13[[#This Row],[Total Selling Price / Unit (MVR)]]-(Table13[[#This Row],[GST 8% (MVR)]]+Table13[[#This Row],[Weighted max expense (MVR)]]) -> 56.707767 | AR24: =Table13[[#This Row],[Profit / Unit (MVR)]]*Table13[[#This Row],[Qty (NOS)]] -> 226.83107
A25: Gold Caviar Ampoule Cream 70ml | B25: Creams & Moisturizers | C25: 3 | D25: 4.82 | E25: 14.46 | F25: =D25*22 -> 106.04 | G25: =SUM(F25*C25) -> 318.12 | H25: 407.66 | I25: 272.8 | J25: =L25-K25 -> 167.24248 | K25: =(F25/$G$92)*Costs!$B$23 -> 156.83159 | L25: =N25/1.08 -> 324.07407 | M25: =L25*0.08 -> 25.925926 | N25: 350 | O25: =Table13[[#This Row],[Total Selling Price / Unit (MVR)]]*Table13[[#This Row],[Qty (NOS)]] -> 1050 | P25: =Q25*C25 -> 1050 | Q25: 350 | R25: =Q25*0.8 -> 280 | S25: 17.86 | T25: =S25*22 -> 392.92 | U25: 407.66 | V25: 18.53 | W25: 4.82 | X25: =Z25*C25 -> 636.24 | Y25: 215 | Z25: =AA25*2 -> 212.08 | AA25: 106.04 | AB25: 272.8 | AC25: 350 | AD25: =V25*15.42 -> 285.7326 | AE25: =AD25*1.08 -> 308.59121 | AF25: =C25*AE25 -> 925.77362 | AG25: =(V25+9)*15.42 -> 424.5126 | AH25: =AG25*1.08 -> 458.47361 | AI25: =C25*AH25 -> 1375.4208 | AJ25: =V25*22 -> 407.66 | AK25: =AJ25*1.08 -> 440.2728 | AL25: =C25*AK25 -> 1320.8184 | AM25: =(V25+9)*22 -> 605.66 | AN25: =AM25*1.08 -> 654.1128 | AO25: =C25*AN25 -> 1962.3384 | AP25: =Table13[[#This Row],[Total Selling Price / Unit (MVR)]]/Table13[[#This Row],[CNF / Unit (MVR)]] -> 3.3006413 | AQ25: =Table13[[#This Row],[Total Selling Price / Unit (MVR)]]-(Table13[[#This Row],[GST 8% (MVR)]]+Table13[[#This Row],[Weighted max expense (MVR)]]) -> 167.24248 | AR25: =Table13[[#This Row],[Profit / Unit (MVR)]]*Table13[[#This Row],[Qty (NOS)]] -> 501.72744
A26: Real Sensation Blemish Cream 55g | B26: Creams & Moisturizers | C26: 4 | D26: 11 | E26: 44 | F26: =D26*22 -> 242 | G26: =SUM(F26*C26) -> 968 | H26: 1613.92 | I26: 436.48 | J26: =L26-K26 -> 86.530016 | K26: =(F26/$G$92)*Costs!$B$23 -> 357.91443 | L26: =N26/1.08 -> 444.44444 | M26: =L26*0.08 -> 35.555556 | N26: 480 | O26: =Table13[[#This Row],[Total Selling Price / Unit (MVR)]]*Table13[[#This Row],[Qty (NOS)]] -> 1920 | P26: =Q26*C26 -> 2400 | Q26: 600 | R26: =Q26*0.8 -> 480 | S26: 70.71 | T26: =S26*22 -> 1555.62 | U26: 1613.92 | V26: 73.36 | W26: 11 | X26: =Z26*C26 -> 1936 | Y26: 485 | Z26: =AA26*2 -> 484 | AA26: 242 | AB26: 436.48 | AC26: 480 | AD26: =V26*15.42 -> 1131.2112 | AE26: =AD26*1.08 -> 1221.7081 | AF26: =C26*AE26 -> 4886.8324 | AG26: =(V26+9)*15.42 -> 1269.9912 | AH26: =AG26*1.08 -> 1371.5905 | AI26: =C26*AH26 -> 5486.362 | AJ26: =V26*22 -> 1613.92 | AK26: =AJ26*1.08 -> 1743.0336 | AL26: =C26*AK26 -> 6972.1344 | AM26: =(V26+9)*22 -> 1811.92 | AN26: =AM26*1.08 -> 1956.8736 | AO26: =C26*AN26 -> 7827.4944 | AP26: =Table13[[#This Row],[Total Selling Price / Unit (MVR)]]/Table13[[#This Row],[CNF / Unit (MVR)]] -> 1.9834711 | AQ26: =Table13[[#This Row],[Total Selling Price / Unit (MVR)]]-(Table13[[#This Row],[GST 8% (MVR)]]+Table13[[#This Row],[Weighted max expense (MVR)]]) -> 86.530016 | AR26: =Table13[[#This Row],[Profit / Unit (MVR)]]*Table13[[#This Row],[Qty (NOS)]] -> 346.12007
A27: Real Sensation Pore Cream 55g | B27: Creams & Moisturizers | C27: 4 | D27: 11 | E27: 44 | F27: =D27*22 -> 242 | G27: =SUM(F27*C27) -> 968 | H27: 1613.92 | I27: 436.48 | J27: =L27-K27 -> 86.530016 | K27: =(F27/$G$92)*Costs!$B$23 -> 357.91443 | L27: =N27/1.08 -> 444.44444 | M27: =L27*0.08 -> 35.555556 | N27: 480 | O27: =Table13[[#This Row],[Total Selling Price / Unit (MVR)]]*Table13[[#This Row],[Qty (NOS)]] -> 1920 | P27: =Q27*C27 -> 2400 | Q27: 600 | R27: =Q27*0.8 -> 480 | S27: 70.71 | T27: =S27*22 -> 1555.62 | U27: 1613.92 | V27: 73.36 | W27: 11 | X27: =Z27*C27 -> 1936 | Y27: 485 | Z27: =AA27*2 -> 484 | AA27: 242 | AB27: 436.48 | AC27: 480 | AD27: =V27*15.42 -> 1131.2112 | AE27: =AD27*1.08 -> 1221.7081 | AF27: =C27*AE27 -> 4886.8324 | AG27: =(V27+9)*15.42 -> 1269.9912 | AH27: =AG27*1.08 -> 1371.5905 | AI27: =C27*AH27 -> 5486.362 | AJ27: =V27*22 -> 1613.92 | AK27: =AJ27*1.08 -> 1743.0336 | AL27: =C27*AK27 -> 6972.1344 | AM27: =(V27+9)*22 -> 1811.92 | AN27: =AM27*1.08 -> 1956.8736 | AO27: =C27*AN27 -> 7827.4944 | AP27: =Table13[[#This Row],[Total Selling Price / Unit (MVR)]]/Table13[[#This Row],[CNF / Unit (MVR)]] -> 1.9834711 | AQ27: =Table13[[#This Row],[Total Selling Price / Unit (MVR)]]-(Table13[[#This Row],[GST 8% (MVR)]]+Table13[[#This Row],[Weighted max expense (MVR)]]) -> 86.530016 | AR27: =Table13[[#This Row],[Profit / Unit (MVR)]]*Table13[[#This Row],[Qty (NOS)]] -> 346.12007
... A29: Wrinkle Collagen Ampoule Cream 70ml | B29: Creams & Moisturizers | C29: 4 | D29: 4.82 | E29: 19.28 | F29: =D29*22 -> 106.04 | G29: =SUM(F29*C29) -> 424.16 | H29: 407.66 | I29: 272.8 | J29: =L29-K29 -> 157.98322 | K29: =(F29/$G$92)*Costs!$B$23 -> 156.83159 | L29: =N29/1.08 -> 314.81481 | M29: =L29*0.08 -> 25.185185 | N29: 340 | O29: =Table13[[#This Row],[Total Selling Price / Unit (MVR)]]*Table13[[#This Row],[Qty (NOS)]] -> 1360 | P29: =Q29*C29 -> 1360 | Q29: 340 | R29: =Q29*0.8 -> 272 | S29: 17.86 | T29: =S29*22 -> 392.92 | U29: 407.66 | V29: 18.53 | W29: 4.82 | X29: =Z29*C29 -> 848.32 | Y29: 215 | Z29: =AA29*2 -> 212.08 | AA29: 106.04 | AB29: 272.8 | AC29: 340 | AD29: =V29*15.42 -> 285.7326 | AE29: =AD29*1.08 -> 308.59121 | AF29: =C29*AE29 -> 1234.3648 | AG29: =(V29+9)*15.42 -> 424.5126 | AH29: =AG29*1.08 -> 458.47361 | AI29: =C29*AH29 -> 1833.8944 | AJ29: =V29*22 -> 407.66 | AK29: =AJ29*1.08 -> 440.2728 | AL29: =C29*AK29 -> 1761.0912 | AM29: =(V29+9)*22 -> 605.66 | AN29: =AM29*1.08 -> 654.1128 | AO29: =C29*AN29 -> 2616.4512 | AP29: =Table13[[#This Row],[Total Selling Price / Unit (MVR)]]/Table13[[#This Row],[CNF / Unit (MVR)]] -> 3.2063372 | AQ29: =Table13[[#This Row],[Total Selling Price / Unit (MVR)]]-(Table13[[#This Row],[GST 8% (MVR)]]+Table13[[#This Row],[Weighted max expense (MVR)]]) -> 157.98322 | AR29: =Table13[[#This Row],[Profit / Unit (MVR)]]*Table13[[#This Row],[Qty (NOS)]] -> 631.93288
A30: YUJA DERMA CREAM 50ml | B30: Creams & Moisturizers | C30: 4 | D30: 5.84 | E30: 23.36 | F30: =D30*22 -> 128.48 | G30: =SUM(F30*C30) -> 513.92 | H30: N/A | I30: 240.68 | J30: =L30-K30 -> 32.202199 | K30: =(F30/$G$92)*Costs!$B$23 -> 190.02002 | L30: =N30/1.08 -> 222.22222 | M30: =L30*0.08 -> 17.777778 | N30: 240 | O30: =Table13[[#This Row],[Total Selling Price / Unit (MVR)]]*Table13[[#This Row],[Qty (NOS)]] -> 960 | P30: =Q30*C30 -> 1200 | Q30: 300 | R30: =Q30*0.8 -> 240 | S30: 55.71 | T30: =S30*22 -> 1225.62 | U30: N/A | V30: 57.8 | W30: 5.84 | X30: =Z30*C30 -> 1027.84 | Y30: 260 | Z30: =AA30*2 -> 256.96 | AA30: 128.48 | AB30: 240.68 | AC30: 240 | AD30: =V30*15.42 -> 891.276 | AE30: =AD30*1.08 -> 962.57808 | AF30: =C30*AE30 -> 3850.3123 | AG30: =(V30+9)*15.42 -> 1030.056 | AH30: =AG30*1.08 -> 1112.4605 | AI30: =C30*AH30 -> 4449.8419 | AJ30: =V30*22 -> 1271.6 | AK30: =AJ30*1.08 -> 1373.328 | AL30: =C30*AK30 -> 5493.312 | AM30: =(V30+9)*22 -> 1469.6 | AN30: =AM30*1.08 -> 1587.168 | AO30: =C30*AN30 -> 6348.672 | AP30: =Table13[[#This Row],[Total Selling Price / Unit (MVR)]]/Table13[[#This Row],[CNF / Unit (MVR)]] -> 1.867995 | AQ30: =Table13[[#This Row],[Total Selling Price / Unit (MVR)]]-(Table13[[#This Row],[GST 8% (MVR)]]+Table13[[#This Row],[Weighted max expense (MVR)]]) -> 32.202199 | AR30: =Table13[[#This Row],[Profit / Unit (MVR)]]*Table13[[#This Row],[Qty (NOS)]] -> 128.80879
A31: YUJA DERMA CREAM 50ml | B31: Creams & Moisturizers | C31: 4 | D31: 5.84 | E31: 23.36 | F31: =D31*22 -> 128.48 | G31: =SUM(F31*C31) -> 513.92 | H31: N/A | I31: 240.68 | J31: =L31-K31 -> 32.202199 | K31: =(F31/$G$92)*Costs!$B$23 -> 190.02002 | L31: =N31/1.08 -> 222.22222 | M31: =L31*0.08 -> 17.777778 | N31: 240 | O31: =Table13[[#This Row],[Total Selling Price / Unit (MVR)]]*Table13[[#This Row],[Qty (NOS)]] -> 960 | P31: =Q31*C31 -> 1200 | Q31: 300 | R31: =Q31*0.8 -> 240 | S31: 55.71 | T31: =S31*22 -> 1225.62 | U31: N/A | V31: 57.8 | W31: 5.84 | X31: =Z31*C31 -> 1027.84 | Y31: 260 | Z31: =AA31*2 -> 256.96 | AA31: 128.48 | AB31: 240.68 | AC31: 240 | AD31: =V31*15.42 -> 891.276 | AE31: =AD31*1.08 -> 962.57808 | AF31: =C31*AE31 -> 3850.3123 | AG31: =(V31+9)*15.42 -> 1030.056 | AH31: =AG31*1.08 -> 1112.4605 | AI31: =C31*AH31 -> 4449.8419 | AJ31: =V31*22 -> 1271.6 | AK31: =AJ31*1.08 -> 1373.328 | AL31: =C31*AK31 -> 5493.312 | AM31: =(V31+9)*22 -> 1469.6 | AN31: =AM31*1.08 -> 1587.168 | AO31: =C31*AN31 -> 6348.672 | AP31: =Table13[[#This Row],[Total Selling Price / Unit (MVR)]]/Table13[[#This Row],[CNF / Unit (MVR)]] -> 1.867995 | AQ31: =Table13[[#This Row],[Total Selling Price / Unit (MVR)]]-(Table13[[#This Row],[GST 8% (MVR)]]+Table13[[#This Row],[Weighted max expense (MVR)]]) -> 32.202199 | AR31: =Table13[[#This Row],[Profit / Unit (MVR)]]*Table13[[#This Row],[Qty (NOS)]] -> 128.80879
A32: Black Snail Eye Cream EX 40ml | B32: Eye Care | C32: 4 | D32: 1.96 | E32: 7.84 | F32: =D32*22 -> 43.12 | G32: =SUM(F32*C32) -> 172.48 | H32: 407.66 | I32: 134.42 | J32: =L32-K32 -> 241.78171 | K32: =(F32/$G$92)*Costs!$B$23 -> 63.773844 | L32: =N32/1.08 -> 305.55556 | M32: =L32*0.08 -> 24.444444 | N32: 330 | O32: =Table13[[#This Row],[Total Selling Price / Unit (MVR)]]*Table13[[#This Row],[Qty (NOS)]] -> 1320 | P32: =Q32*C32 -> 1000 | Q32: 250 | R32: =Q32*0.8 -> 200 | S32: 17.86 | T32: =S32*22 -> 392.92 | U32: 407.66 | V32: 18.53 | W32: 1.96 | X32: =Z32*C32 -> 344.96 | Y32: 90 | Z32: =AA32*2 -> 86.24 | AA32: 43.12 | AB32: 134.42 | AC32: 330 | AD32: =V32*15.42 -> 285.7326 | AE32: =AD32*1.08 -> 308.59121 | AF32: =C32*AE32 -> 1234.3648 | AG32: =(V32+9)*15.42 -> 424.5126 | AH32: =AG32*1.08 -> 458.47361 | AI32: =C32*AH32 -> 1833.8944 | AJ32: =V32*22 -> 407.66 | AK32: =AJ32*1.08 -> 440.2728 | AL32: =C32*AK32 -> 1761.0912 | AM32: =(V32+9)*22 -> 605.66 | AN32: =AM32*1.08 -> 654.1128 | AO32: =C32*AN32 -> 2616.4512 | AP32: =Table13[[#This Row],[Total Selling Price / Unit (MVR)]]/Table13[[#This Row],[CNF / Unit (MVR)]] -> 7.6530612 | AQ32: =Table13[[#This Row],[Total Selling Price / Unit (MVR)]]-(Table13[[#This Row],[GST 8% (MVR)]]+Table13[[#This Row],[Weighted max expense (MVR)]]) -> 241.78171 | AR32: =Table13[[#This Row],[Profit / Unit (MVR)]]*Table13[[#This Row],[Qty (NOS)]] -> 967.12685
A33: Collagen Hydrogel Eye Patch 90g / 60 sheets | B33: Eye Care | C33: 4 | D33: 6.33 | E33: 25.32 | F33: =D33*22 -> 139.26 | G33: =SUM(F33*C33) -> 557.04 | H33: 407.66 | I33: 298.1 | J33: =L33-K33 -> 71.814293 | K33: =(F33/$G$92)*Costs!$B$23 -> 205.96348 | L33: =N33/1.08 -> 277.77778 | M33: =L33*0.08 -> 22.222222 | N33: 300 | O33: =Table13[[#This Row],[Total Selling Price / Unit (MVR)]]*Table13[[#This Row],[Qty (NOS)]] -> 1200 | P33: =Q33*C33 -> 1400 | Q33: 350 | R33: =Q33*0.8 -> 280 | S33: 17.86 | T33: =S33*22 -> 392.92 | U33: 407.66 | V33: 18.53 | W33: 6.33 | X33: =Z33*C33 -> 1114.08 | Y33: 280 | Z33: =AA33*2 -> 278.52 | AA33: 139.26 | AB33: 298.1 | AC33: 300 | AD33: =V33*15.42 -> 285.7326 | AE33: =AD33*1.08 -> 308.59121 | AF33: =C33*AE33 -> 1234.3648 | AG33: =(V33+9)*15.42 -> 424.5126 | AH33: =AG33*1.08 -> 458.47361 | AI33: =C33*AH33 -> 1833.8944 | AJ33: =V33*22 -> 407.66 | AK33: =AJ33*1.08 -> 440.2728 | AL33: =C33*AK33 -> 1761.0912 | AM33: =(V33+9)*22 -> 605.66 | AN33: =AM33*1.08 -> 654.1128 | AO33: =C33*AN33 -> 2616.4512 | AP33: =Table13[[#This Row],[Total Selling Price / Unit (MVR)]]/Table13[[#This Row],[CNF / Unit (MVR)]] -> 2.1542439 | AQ33: =Table13[[#This Row],[Total Selling Price / Unit (MVR)]]-(Table13[[#This Row],[GST 8% (MVR)]]+Table13[[#This Row],[Weighted max expense (MVR)]]) -> 71.814293 | AR33: =Table13[[#This Row],[Profit / Unit (MVR)]]*Table13[[#This Row],[Qty (NOS)]] -> 287.25717
A34: Heeyul 24K Gold Eye Cream 40ml | B34: Eye Care | C34: 4 | D34: 1.96 | E34: 7.84 | F34: =D34*22 -> 43.12 | G34: =SUM(F34*C34) -> 172.48 | H34: 407.66 | I34: 300 | J34: =L34-K34 -> 241.78171 | K34: =(F34/$G$92)*Costs!$B$23 -> 63.773844 | L34: =N34/1.08 -> 305.55556 | M34: =L34*0.08 -> 24.444444 | N34: 330 | O34: =Table13[[#This Row],[Total Selling Price / Unit (MVR)]]*Table13[[#This Row],[Qty (NOS)]] -> 1320 | P34: =Q34*C34 -> 1520 | Q34: 380 | R34: =Q34*0.8 -> 304 | S34: 17.86 | T34: =S34*22 -> 392.92 | U34: 407.66 | V34: 18.53 | W34: 1.96 | X34: =Z34*C34 -> 344.96 | Y34: 90 | Z34: =AA34*2 -> 86.24 | AA34: 43.12 | AB34: 300 | AC34: 330 | AD34: =V34*15.42 -> 285.7326 | AE34: =AD34*1.08 -> 308.59121 | AF34: =C34*AE34 -> 1234.3648 | AG34: =(V34+9)*15.42 -> 424.5126 | AH34: =AG34*1.08 -> 458.47361 | AI34: =C34*AH34 -> 1833.8944 | AJ34: =V34*22 -> 407.66 | AK34: =AJ34*1.08 -> 440.2728 | AL34: =C34*AK34 -> 1761.0912 | AM34: =(V34+9)*22 -> 605.66 | AN34: =AM34*1.08 -> 654.1128 | AO34: =C34*AN34 -> 2616.4512 | AP34: =Table13[[#This Row],[Total Selling Price / Unit (MVR)]]/Table13[[#This Row],[CNF / Unit (MVR)]] -> 7.6530612 | AQ34: =Table13[[#This Row],[Total Selling Price / Unit (MVR)]]-(Table13[[#This Row],[GST 8% (MVR)]]+Table13[[#This Row],[Weighted max expense (MVR)]]) -> 241.78171 | AR34: =Table13[[#This Row],[Profit / Unit (MVR)]]*Table13[[#This Row],[Qty (NOS)]] -> 967.12685
A35: Vitamin Hydrogel Eye Patch 90g / 60 sheets | B35: Eye Care | C35: 4 | D35: 6.33 | E35: 25.32 | F35: =D35*22 -> 139.26 | G35: =SUM(F35*C35) -> 557.04 | H35: N/A | I35: 298.1 | J35: =L35-K35 -> 71.814293 | K35: =(F35/$G$92)*Costs!$B$23 -> 205.96348 | L35: =N35/1.08 -> 277.77778 | M35: =L35*0.08 -> 22.222222 | N35: 300 | O35: =Table13[[#This Row],[Total Selling Price / Unit (MVR)]]*Table13[[#This Row],[Qty (NOS)]] -> 1200 | P35: =Q35*C35 -> 1400 | Q35: 350 | R35: =Q35*0.8 -> 280 | S35: 17.86 | T35: =S35*22 -> 392.92 | U35: N/A | V35: 18.53 | W35: 6.33 | X35: =Z35*C35 -> 1114.08 | Y35: 280 | Z35: =AA35*2 -> 278.52 | AA35: 139.26 | AB35: 298.1 | AC35: 300 | AD35: =V35*15.42 -> 285.7326 | AE35: =AD35*1.08 -> 308.59121 | AF35: =C35*AE35 -> 1234.3648 | AG35: =(V35+9)*15.42 -> 424.5126 | AH35: =AG35*1.08 -> 458.47361 | AI35: =C35*AH35 -> 1833.8944 | AJ35: =V35*22 -> 407.66 | AK35: =AJ35*1.08 -> 440.2728 | AL35: =C35*AK35 -> 1761.0912 | AM35: =(V35+9)*22 -> 605.66 | AN35: =AM35*1.08 -> 654.1128 | AO35: =C35*AN35 -> 2616.4512 | AP35: =Table13[[#This Row],[Total Selling Price / Unit (MVR)]]/Table13[[#This Row],[CNF / Unit (MVR)]] -> 2.1542439 | AQ35: =Table13[[#This Row],[Total Selling Price / Unit (MVR)]]-(Table13[[#This Row],[GST 8% (MVR)]]+Table13[[#This Row],[Weighted max expense (MVR)]]) -> 71.814293 | AR35: =Table13[[#This Row],[Profit / Unit (MVR)]]*Table13[[#This Row],[Qty (NOS)]] -> 287.25717
A36: The Glow Color Lip Balm #102 Smoothie Pink 3.6g | B36: Lips & Makeup | C36: 4 | D36: 3.34 | E36: 13.36 | F36: =D36*22 -> 73.48 | G36: =SUM(F36*C36) -> 293.92 | H36: N/A | I36: 125.84 | J36: =L36-K36 -> 67.250091 | K36: =(F36/$G$92)*Costs!$B$23 -> 108.67584 | L36: =N36/1.08 -> 175.92593 | M36: =L36*0.08 -> 14.074074 | N36: 190 | O36: =Table13[[#This Row],[Total Selling Price / Unit (MVR)]]*Table13[[#This Row],[Qty (NOS)]] -> 760 | P36: =Q36*C36 -> 760 | Q36: 190 | R36: =Q36*0.8 -> 152 | S36: 10.71 | T36: =S36*22 -> 235.62 | U36: N/A | V36: 10 | W36: 3.34 | X36: =Z36*C36 -> 587.84 | Y36: 150 | Z36: =AA36*2 -> 146.96 | AA36: 73.48 | AB36: 125.84 | AC36: 190 | AD36: =V36*15.42 -> 154.2 | AE36: =AD36*1.08 -> 166.536 | AF36: =C36*AE36 -> 666.144 | AG36: =(V36+9)*15.42 -> 292.98 | AH36: =AG36*1.08 -> 316.4184 | AI36: =C36*AH36 -> 1265.6736 | AJ36: =V36*22 -> 220 | AK36: =AJ36*1.08 -> 237.6 | AL36: =C36*AK36 -> 950.4 | AM36: =(V36+9)*22 -> 418 | AN36: =AM36*1.08 -> 451.44 | AO36: =C36*AN36 -> 1805.76 | AP36: =Table13[[#This Row],[Total Selling Price / Unit (MVR)]]/Table13[[#This Row],[CNF / Unit (MVR)]] -> 2.5857376 | AQ36: =Table13[[#This Row],[Total Selling Price / Unit (MVR)]]-(Table13[[#This Row],[GST 8% (MVR)]]+Table13[[#This Row],[Weighted max expense (MVR)]]) -> 67.250091 | AR36: =Table13[[#This Row],[Profit / Unit (MVR)]]*Table13[[#This Row],[Qty (NOS)]] -> 269.00036
A37: The Glow Color Lip Balm #103 Raspberry 3.6g | B37: Lips & Makeup | C37: 4 | D37: 3.34 | E37: 13.36 | F37: =D37*22 -> 73.48 | G37: =SUM(F37*C37) -> 293.92 | H37: N/A | I37: 125.84 | J37: =L37-K37 -> 67.250091 | K37: =(F37/$G$92)*Costs!$B$23 -> 108.67584 | L37: =N37/1.08 -> 175.92593 | M37: =L37*0.08 -> 14.074074 | N37: 190 | O37: =Table13[[#This Row],[Total Selling Price / Unit (MVR)]]*Table13[[#This Row],[Qty (NOS)]] -> 760 | P37: =Q37*C37 -> 760 | Q37: 190 | R37: =Q37*0.8 -> 152 | S37: 10.71 | T37: =S37*22 -> 235.62 | U37: N/A | V37: 10 | W37: 3.34 | X37: =Z37*C37 -> 587.84 | Y37: 150 | Z37: =AA37*2 -> 146.96 | AA37: 73.48 | AB37: 125.84 | AC37: 190 | AD37: =V37*15.42 -> 154.2 | AE37: =AD37*1.08 -> 166.536 | AF37: =C37*AE37 -> 666.144 | AG37: =(V37+9)*15.42 -> 292.98 | AH37: =AG37*1.08 -> 316.4184 | AI37: =C37*AH37 -> 1265.6736 | AJ37: =V37*22 -> 220 | AK37: =AJ37*1.08 -> 237.6 | AL37: =C37*AK37 -> 950.4 | AM37: =(V37+9)*22 -> 418 | AN37: =AM37*1.08 -> 451.44 | AO37: =C37*AN37 -> 1805.76 | AP37: =Table13[[#This Row],[Total Selling Price / Unit (MVR)]]/Table13[[#This Row],[CNF / Unit (MVR)]] -> 2.5857376 | AQ37: =Table13[[#This Row],[Total Selling Price / Unit (MVR)]]-(Table13[[#This Row],[GST 8% (MVR)]]+Table13[[#This Row],[Weighted max expense (MVR)]]) -> 67.250091 | AR37: =Table13[[#This Row],[Profit / Unit (MVR)]]*Table13[[#This Row],[Qty (NOS)]] -> 269.00036
A38: The Glow Color Lip Balm #104 Rosewood 3.6g | B38: Lips & Makeup | C38: 4 | D38: 3.34 | E38: 13.36 | F38: =D38*22 -> 73.48 | G38: =SUM(F38*C38) -> 293.92 | H38: N/A | I38: 125.84 | J38: =L38-K38 -> 67.250091 | K38: =(F38/$G$92)*Costs!$B$23 -> 108.67584 | L38: =N38/1.08 -> 175.92593 | M38: =L38*0.08 -> 14.074074 | N38: 190 | O38: =Table13[[#This Row],[Total Selling Price / Unit (MVR)]]*Table13[[#This Row],[Qty (NOS)]] -> 760 | P38: =Q38*C38 -> 760 | Q38: 190 | R38: =Q38*0.8 -> 152 | S38: 10.71 | T38: =S38*22 -> 235.62 | U38: N/A | V38: 10 | W38: 3.34 | X38: =Z38*C38 -> 587.84 | Y38: 150 | Z38: =AA38*2 -> 146.96 | AA38: 73.48 | AB38: 125.84 | AC38: 190 | AD38: =V38*15.42 -> 154.2 | AE38: =AD38*1.08 -> 166.536 | AF38: =C38*AE38 -> 666.144 | AG38: =(V38+9)*15.42 -> 292.98 | AH38: =AG38*1.08 -> 316.4184 | AI38: =C38*AH38 -> 1265.6736 | AJ38: =V38*22 -> 220 | AK38: =AJ38*1.08 -> 237.6 | AL38: =C38*AK38 -> 950.4 | AM38: =(V38+9)*22 -> 418 | AN38: =AM38*1.08 -> 451.44 | AO38: =C38*AN38 -> 1805.76 | AP38: =Table13[[#This Row],[Total Selling Price / Unit (MVR)]]/Table13[[#This Row],[CNF / Unit (MVR)]] -> 2.5857376 | AQ38: =Table13[[#This Row],[Total Selling Price / Unit (MVR)]]-(Table13[[#This Row],[GST 8% (MVR)]]+Table13[[#This Row],[Weighted max expense (MVR)]]) -> 67.250091 | AR38: =Table13[[#This Row],[Profit / Unit (MVR)]]*Table13[[#This Row],[Qty (NOS)]] -> 269.00036
A39: Aloe Solution Mask Pack 25g x 10pcs | B39: Mask Packs | C39: 4 | D39: 2.13 | E39: 8.52 | F39: =D39*22 -> 46.86 | G39: =SUM(F39*C39) -> 187.44 | H39: 440 | I39: 47.74 | J39: =L39-K39 -> 143.65771 | K39: =(F39/$G$92)*Costs!$B$23 -> 69.305248 | L39: =N39/1.08 -> 212.96296 | M39: =L39*0.08 -> 17.037037 | N39: 230 | O39: =Table13[[#This Row],[Total Selling Price / Unit (MVR)]]*Table13[[#This Row],[Qty (NOS)]] -> 920 | P39: =Q39*C39 -> 920 | Q39: 230 | R39: =Q39*0.8 -> 184 | S39: 7.14 | T39: =S39*22 -> 157.08 | U39: 440 | V39: 20 | W39: 2.13 | X39: =Z39*C39 -> 374.88 | Y39: 95 | Z39: =AA39*2 -> 93.72 | AA39: 46.86 | AB39: 47.74 | AC39: 230 | AD39: =V39*15.42 -> 308.4 | AE39: =AD39*1.08 -> 333.072 | AF39: =C39*AE39 -> 1332.288 | AG39: =(V39+9)*15.42 -> 447.18 | AH39: =AG39*1.08 -> 482.9544 | AI39: =C39*AH39 -> 1931.8176 | AJ39: =V39*22 -> 440 | AK39: =AJ39*1.08 -> 475.2 | AL39: =C39*AK39 -> 1900.8 | AM39: =(V39+9)*22 -> 638 | AN39: =AM39*1.08 -> 689.04 | AO39: =C39*AN39 -> 2756.16 | AP39: =Table13[[#This Row],[Total Selling Price / Unit (MVR)]]/Table13[[#This Row],[CNF / Unit (MVR)]] -> 4.9082373 | AQ39: =Table13[[#This Row],[Total Selling Price / Unit (MVR)]]-(Table13[[#This Row],[GST 8% (MVR)]]+Table13[[#This Row],[Weighted max expense (MVR)]]) -> 143.65771 | AR39: =Table13[[#This Row],[Profit / Unit (MVR)]]*Table13[[#This Row],[Qty (NOS)]] -> 574.63086
A40: Cica Solution Mask Pack 25g x 10pcs | B40: Mask Packs | C40: 4 | D40: 2.13 | E40: 8.52 | F40: =D40*22 -> 46.86 | G40: =SUM(F40*C40) -> 187.44 | H40: 440 | I40: 47.74 | J40: =L40-K40 -> 143.65771 | K40: =(F40/$G$92)*Costs!$B$23 -> 69.305248 | L40: =N40/1.08 -> 212.96296 | M40: =L40*0.08 -> 17.037037 | N40: 230 | O40: =Table13[[#This Row],[Total Selling Price / Unit (MVR)]]*Table13[[#This Row],[Qty (NOS)]] -> 920 | P40: =Q40*C40 -> 920 | Q40: 230 | R40: =Q40*0.8 -> 184 | S40: 7.14 | T40: =S40*22 -> 157.08 | U40: 440 | V40: 20 | W40: 2.13 | X40: =Z40*C40 -> 374.88 | Y40: 95 | Z40: =AA40*2 -> 93.72 | AA40: 46.86 | AB40: 47.74 | AC40: 230 | AD40: =V40*15.42 -> 308.4 | AE40: =AD40*1.08 -> 333.072 | AF40: =C40*AE40 -> 1332.288 | AG40: =(V40+9)*15.42 -> 447.18 | AH40: =AG40*1.08 -> 482.9544 | AI40: =C40*AH40 -> 1931.8176 | AJ40: =V40*22 -> 440 | AK40: =AJ40*1.08 -> 475.2 | AL40: =C40*AK40 -> 1900.8 | AM40: =(V40+9)*22 -> 638 | AN40: =AM40*1.08 -> 689.04 | AO40: =C40*AN40 -> 2756.16 | AP40: =Table13[[#This Row],[Total Selling Price / Unit (MVR)]]/Table13[[#This Row],[CNF / Unit (MVR)]] -> 4.9082373 | AQ40: =Table13[[#This Row],[Total Selling Price / Unit (MVR)]]-(Table13[[#This Row],[GST 8% (MVR)]]+Table13[[#This Row],[Weighted max expense (MVR)]]) -> 143.65771 | AR40: =Table13[[#This Row],[Profit / Unit (MVR)]]*Table13[[#This Row],[Qty (NOS)]] -> 574.63086
A41: Hyaluronic Collagen Solution Mask Pack 25g x 10pcs | B41: Mask Packs | C41: 4 | D41: 2.13 | E41: 8.52 | F41: =D41*22 -> 46.86 | G41: =SUM(F41*C41) -> 187.44 | H41: 440 | I41: 47.74 | J41: =L41-K41 -> 143.65771 | K41: =(F41/$G$92)*Costs!$B$23 -> 69.305248 | L41: =N41/1.08 -> 212.96296 | M41: =L41*0.08 -> 17.037037 | N41: 230 | O41: =Table13[[#This Row],[Total Selling Price / Unit (MVR)]]*Table13[[#This Row],[Qty (NOS)]] -> 920 | P41: =Q41*C41 -> 920 | Q41: 230 | R41: =Q41*0.8 -> 184 | S41: 7.14 | T41: =S41*22 -> 157.08 | U41: 440 | V41: 20 | W41: 2.13 | X41: =Z41*C41 -> 374.88 | Y41: 95 | Z41: =AA41*2 -> 93.72 | AA41: 46.86 | AB41: 47.74 | AC41: 230 | AD41: =V41*15.42 -> 308.4 | AE41: =AD41*1.08 -> 333.072 | AF41: =C41*AE41 -> 1332.288 | AG41: =(V41+9)*15.42 -> 447.18 | AH41: =AG41*1.08 -> 482.9544 | AI41: =C41*AH41 -> 1931.8176 | AJ41: =V41*22 -> 440 | AK41: =AJ41*1.08 -> 475.2 | AL41: =C41*AK41 -> 1900.8 | AM41: =(V41+9)*22 -> 638 | AN41: =AM41*1.08 -> 689.04 | AO41: =C41*AN41 -> 2756.16 | AP41: =Table13[[#This Row],[Total Selling Price / Unit (MVR)]]/Table13[[#This Row],[CNF / Unit (MVR)]] -> 4.9082373 | AQ41: =Table13[[#This Row],[Total Selling Price / Unit (MVR)]]-(Table13[[#This Row],[GST 8% (MVR)]]+Table13[[#This Row],[Weighted max expense (MVR)]]) -> 143.65771 | AR41: =Table13[[#This Row],[Profit / Unit (MVR)]]*Table13[[#This Row],[Qty (NOS)]] -> 574.63086
A42: Snail Solution Mask Pack 25g x 10pcs | B42: Mask Packs | C42: 4 | D42: 2.13 | E42: 8.52 | F42: =D42*22 -> 46.86 | G42: =SUM(F42*C42) -> 187.44 | H42: 440 | I42: 47.74 | J42: =L42-K42 -> 143.65771 | K42: =(F42/$G$92)*Costs!$B$23 -> 69.305248 | L42: =N42/1.08 -> 212.96296 | M42: =L42*0.08 -> 17.037037 | N42: 230 | O42: =Table13[[#This Row],[Total Selling Price / Unit (MVR)]]*Table13[[#This Row],[Qty (NOS)]] -> 920 | P42: =Q42*C42 -> 920 | Q42: 230 | R42: =Q42*0.8 -> 184 | S42: 7.14 | T42: =S42*22 -> 157.08 | U42: 440 | V42: 20 | W42: 2.13 | X42: =Z42*C42 -> 374.88 | Y42: 95 | Z42: =AA42*2 -> 93.72 | AA42: 46.86 | AB42: 47.74 | AC42: 230 | AD42: =V42*15.42 -> 308.4 | AE42: =AD42*1.08 -> 333.072 | AF42: =C42*AE42 -> 1332.288 | AG42: =(V42+9)*15.42 -> 447.18 | AH42: =AG42*1.08 -> 482.9544 | AI42: =C42*AH42 -> 1931.8176 | AJ42: =V42*22 -> 440 | AK42: =AJ42*1.08 -> 475.2 | AL42: =C42*AK42 -> 1900.8 | AM42: =(V42+9)*22 -> 638 | AN42: =AM42*1.08 -> 689.04 | AO42: =C42*AN42 -> 2756.16 | AP42: =Table13[[#This Row],[Total Selling Price / Unit (MVR)]]/Table13[[#This Row],[CNF / Unit (MVR)]] -> 4.9082373 | AQ42: =Table13[[#This Row],[Total Selling Price / Unit (MVR)]]-(Table13[[#This Row],[GST 8% (MVR)]]+Table13[[#This Row],[Weighted max expense (MVR)]]) -> 143.65771 | AR42: =Table13[[#This Row],[Profit / Unit (MVR)]]*Table13[[#This Row],[Qty (NOS)]] -> 574.63086
A43: Vitamin Solution Mask Pack 25g x 10pcs | B43: Mask Packs | C43: 4 | D43: 2.13 | E43: 8.52 | F43: =D43*22 -> 46.86 | G43: =SUM(F43*C43) -> 187.44 | H43: 440 | I43: 47.74 | J43: =L43-K43 -> 143.65771 | K43: =(F43/$G$92)*Costs!$B$23 -> 69.305248 | L43: =N43/1.08 -> 212.96296 | M43: =L43*0.08 -> 17.037037 | N43: 230 | O43: =Table13[[#This Row],[Total Selling Price / Unit (MVR)]]*Table13[[#This Row],[Qty (NOS)]] -> 920 | P43: =Q43*C43 -> 920 | Q43: 230 | R43: =Q43*0.8 -> 184 | S43: 7.14 | T43: =S43*22 -> 157.08 | U43: 440 | V43: 20 | W43: 2.13 | X43: =Z43*C43 -> 374.88 | Y43: 95 | Z43: =AA43*2 -> 93.72 | AA43: 46.86 | AB43: 47.74 | AC43: 230 | AD43: =V43*15.42 -> 308.4 | AE43: =AD43*1.08 -> 333.072 | AF43: =C43*AE43 -> 1332.288 | AG43: =(V43+9)*15.42 -> 447.18 | AH43: =AG43*1.08 -> 482.9544 | AI43: =C43*AH43 -> 1931.8176 | AJ43: =V43*22 -> 440 | AK43: =AJ43*1.08 -> 475.2 | AL43: =C43*AK43 -> 1900.8 | AM43: =(V43+9)*22 -> 638 | AN43: =AM43*1.08 -> 689.04 | AO43: =C43*AN43 -> 2756.16 | AP43: =Table13[[#This Row],[Total Selling Price / Unit (MVR)]]/Table13[[#This Row],[CNF / Unit (MVR)]] -> 4.9082373 | AQ43: =Table13[[#This Row],[Total Selling Price / Unit (MVR)]]-(Table13[[#This Row],[GST 8% (MVR)]]+Table13[[#This Row],[Weighted max expense (MVR)]]) -> 143.65771 | AR43: =Table13[[#This Row],[Profit / Unit (MVR)]]*Table13[[#This Row],[Qty (NOS)]] -> 574.63086
A44: 24K Gold Perfect Ampoule 50g | B44: Serums & Ampoules | C44: 4 | D44: 12.18 | E44: 48.72 | F44: =D44*22 -> 267.96 | G44: =SUM(F44*C44) -> 1071.84 | H44: 1956.24 | I44: 459.58 | J44: =L44-K44 -> 85.172597 | K44: =(F44/$G$92)*Costs!$B$23 -> 396.30888 | L44: =N44/1.08 -> 481.48148 | M44: =L44*0.08 -> 38.518519 | N44: 520 | O44: =Table13[[#This Row],[Total Selling Price / Unit (MVR)]]*Table13[[#This Row],[Qty (NOS)]] -> 2080 | P44: =Q44*C44 -> 3000 | Q44: 750 | R44: =Q44*0.8 -> 600 | S44: 53.57 | T44: =S44*22 -> 1178.54 | U44: 1956.24 | V44: 88.92 | W44: 12.18 | X44: =Z44*C44 -> 2143.68 | Y44: 540 | Z44: =AA44*2 -> 535.92 | AA44: 267.96 | AB44: 459.58 | AC44: 520 | AD44: =V44*15.42 -> 1371.1464 | AE44: =AD44*1.08 -> 1480.8381 | AF44: =C44*AE44 -> 5923.3524 | AG44: =(V44+9)*15.42 -> 1509.9264 | AH44: =AG44*1.08 -> 1630.7205 | AI44: =C44*AH44 -> 6522.882 | AJ44: =V44*22 -> 1956.24 | AK44: =AJ44*1.08 -> 2112.7392 | AL44: =C44*AK44 -> 8450.9568 | AM44: =(V44+9)*22 -> 2154.24 | AN44: =AM44*1.08 -> 2326.5792 | AO44: =C44*AN44 -> 9306.3168 | AP44: =Table13[[#This Row],[Total Selling Price / Unit (MVR)]]/Table13[[#This Row],[CNF / Unit (MVR)]] -> 1.9405881 | AQ44: =Table13[[#This Row],[Total Selling Price / Unit (MVR)]]-(Table13[[#This Row],[GST 8% (MVR)]]+Table13[[#This Row],[Weighted max expense (MVR)]]) -> 85.172597 | AR44: =Table13[[#This Row],[Profit / Unit (MVR)]]*Table13[[#This Row],[Qty (NOS)]] -> 340.69039
A45: Cica Propolis Myrrh Ampoule 15ml | B45: Serums & Ampoules | C45: 4 | D45: 2.58 | E45: 10.32 | F45: =D45*22 -> 56.76 | G45: =SUM(F45*C45) -> 227.04 | H45: 391.16 | I45: 153.12 | J45: =L45-K45 -> 192.90465 | K45: =(F45/$G$92)*Costs!$B$23 -> 83.947202 | L45: =N45/1.08 -> 276.85185 | M45: =L45*0.08 -> 22.148148 | N45: 299 | O45: =Table13[[#This Row],[Total Selling Price / Unit (MVR)]]*Table13[[#This Row],[Qty (NOS)]] -> 1196 | P45: =Q45*C45 -> 1000 | Q45: 250 | R45: =Q45*0.8 -> 200 | S45: 17.14 | T45: =S45*22 -> 377.08 | U45: 391.16 | V45: 17.78 | W45: 2.58 | X45: =Z45*C45 -> 454.08 | Y45: 115 | Z45: =AA45*2 -> 113.52 | AA45: 56.76 | AB45: 153.12 | AC45: 299 | AD45: =V45*15.42 -> 274.1676 | AE45: =AD45*1.08 -> 296.10101 | AF45: =C45*AE45 -> 1184.404 | AG45: =(V45+9)*15.42 -> 412.9476 | AH45: =AG45*1.08 -> 445.98341 | AI45: =C45*AH45 -> 1783.9336 | AJ45: =V45*22 -> 391.16 | AK45: =AJ45*1.08 -> 422.4528 | AL45: =C45*AK45 -> 1689.8112 | AM45: =(V45+9)*22 -> 589.16 | AN45: =AM45*1.08 -> 636.2928 | AO45: =C45*AN45 -> 2545.1712 | AP45: =Table13[[#This Row],[Total Selling Price / Unit (MVR)]]/Table13[[#This Row],[CNF / Unit (MVR)]] -> 5.2677942 | AQ45: =Table13[[#This Row],[Total Selling Price / Unit (MVR)]]-(Table13[[#This Row],[GST 8% (MVR)]]+Table13[[#This Row],[Weighted max expense (MVR)]]) -> 192.90465 | AR45: =Table13[[#This Row],[Profit / Unit (MVR)]]*Table13[[#This Row],[Qty (NOS)]] -> 771.6186
A46: Dr. Ceramide Derma Ampoule 30ml | B46: Serums & Ampoules | C46: 4 | D46: 3.89 | E46: 15.56 | F46: =D46*22 -> 85.58 | G46: =SUM(F46*C46) -> 342.32 | H46: 619.52 | I46: 181.06 | J46: =L46-K46 -> 243.79881 | K46: =(F46/$G$92)*Costs!$B$23 -> 126.57156 | L46: =N46/1.08 -> 370.37037 | M46: =L46*0.08 -> 29.62963 | N46: 400 | O46: =Table13[[#This Row],[Total Selling Price / Unit (MVR)]]*Table13[[#This Row],[Qty (NOS)]] -> 1600 | P46: =Q46*C46 -> 1160 | Q46: 290 | R46: =Q46*0.8 -> 232 | S46: 27.14 | T46: =S46*22 -> 597.08 | U46: 619.52 | V46: 28.16 | W46: 3.89 | X46: =Z46*C46 -> 684.64 | Y46: 175 | Z46: =AA46*2 -> 171.16 | AA46: 85.58 | AB46: 181.06 | AC46: 400 | AD46: =V46*15.42 -> 434.2272 | AE46: =AD46*1.08 -> 468.96538 | AF46: =C46*AE46 -> 1875.8615 | AG46: =(V46+9)*15.42 -> 573.0072 | AH46: =AG46*1.08 -> 618.84778 | AI46: =C46*AH46 -> 2475.3911 | AJ46: =V46*22 -> 619.52 | AK46: =AJ46*1.08 -> 669.0816 | AL46: =C46*AK46 -> 2676.3264 | AM46: =(V46+9)*22 -> 817.52 | AN46: =AM46*1.08 -> 882.9216 | AO46: =C46*AN46 -> 3531.6864 | AP46: =Table13[[#This Row],[Total Selling Price / Unit (MVR)]]/Table13[[#This Row],[CNF / Unit (MVR)]] -> 4.6739892 | AQ46: =Table13[[#This Row],[Total Selling Price / Unit (MVR)]]-(Table13[[#This Row],[GST 8% (MVR)]]+Table13[[#This Row],[Weighted max expense (MVR)]]) -> 243.79881 | AR46: =Table13[[#This Row],[Profit / Unit (MVR)]]*Table13[[#This Row],[Qty (NOS)]] -> 975.19525
A47: Dr. Cica Derma Ampoule 30ml | B47: Serums & Ampoules | C47: 5 | D47: 3.89 | E47: 27.23 | F47: =D47*22 -> 85.58 | G47: =SUM(F47*C47) -> 427.9 | H47: 619.52 | I47: 181.06 | J47: =L47-K47 -> 206.76178 | K47: =(F47/$G$92)*Costs!$B$23 -> 126.57156 | L47: =N47/1.08 -> 333.33333 | M47: =L47*0.08 -> 26.666667 | N47: 360 | O47: =Table13[[#This Row],[Total Selling Price / Unit (MVR)]]*Table13[[#This Row],[Qty (NOS)]] -> 1800 | P47: =Q47*C47 -> 1450 | Q47: 290 | R47: =Q47*0.8 -> 232 | S47: 27.14 | T47: =S47*22 -> 597.08 | U47: 619.52 | V47: 28.16 | W47: 3.89 | X47: =Z47*C47 -> 855.8 | Y47: 175 | Z47: =AA47*2 -> 171.16 | AA47: 85.58 | AB47: 181.06 | AC47: 360 | AD47: =V47*15.42 -> 434.2272 | AE47: =AD47*1.08 -> 468.96538 | AF47: =C47*AE47 -> 2344.8269 | AG47: =(V47+9)*15.42 -> 573.0072 | AH47: =AG47*1.08 -> 618.84778 | AI47: =C47*AH47 -> 3094.2389 | AJ47: =V47*22 -> 619.52 | AK47: =AJ47*1.08 -> 669.0816 | AL47: =C47*AK47 -> 3345.408 | AM47: =(V47+9)*22 -> 817.52 | AN47: =AM47*1.08 -> 882.9216 | AO47: =C47*AN47 -> 4414.608 | AP47: =Table13[[#This Row],[Total Selling Price / Unit (MVR)]]/Table13[[#This Row],[CNF / Unit (MVR)]] -> 4.2065903 | AQ47: =Table13[[#This Row],[Total Selling Price / Unit (MVR)]]-(Table13[[#This Row],[GST 8% (MVR)]]+Table13[[#This Row],[Weighted max expense (MVR)]]) -> 206.76178 | AR47: =Table13[[#This Row],[Profit / Unit (MVR)]]*Table13[[#This Row],[Qty (NOS)]] -> 1033.8089
A48: Dr. Collagen Derma Ampoule 30ml | B48: Serums & Ampoules | C48: 4 | D48: 3.89 | E48: 15.56 | F48: =D48*22 -> 85.58 | G48: =SUM(F48*C48) -> 342.32 | H48: 619.52 | I48: 181.06 | J48: =L48-K48 -> 294.72474 | K48: =(F48/$G$92)*Costs!$B$23 -> 126.57156 | L48: =N48/1.08 -> 421.2963 | M48: =L48*0.08 -> 33.703704 | N48: 455 | O48: =Table13[[#This Row],[Total Selling Price / Unit (MVR)]]*Table13[[#This Row],[Qty (NOS)]] -> 1820 | P48: =Q48*C48 -> 1160 | Q48: 290 | R48: =Q48*0.8 -> 232 | S48: 27.14 | T48: =S48*22 -> 597.08 | U48: 619.52 | V48: 28.16 | W48: 3.89 | X48: =Z48*C48 -> 684.64 | Y48: 175 | Z48: =AA48*2 -> 171.16 | AA48: 85.58 | AB48: 181.06 | AC48: 455 | AD48: =V48*15.42 -> 434.2272 | AE48: =AD48*1.08 -> 468.96538 | AF48: =C48*AE48 -> 1875.8615 | AG48: =(V48+9)*15.42 -> 573.0072 | AH48: =AG48*1.08 -> 618.84778 | AI48: =C48*AH48 -> 2475.3911 | AJ48: =V48*22 -> 619.52 | AK48: =AJ48*1.08 -> 669.0816 | AL48: =C48*AK48 -> 2676.3264 | AM48: =(V48+9)*22 -> 817.52 | AN48: =AM48*1.08 -> 882.9216 | AO48: =C48*AN48 -> 3531.6864 | AP48: =Table13[[#This Row],[Total Selling Price / Unit (MVR)]]/Table13[[#This Row],[CNF / Unit (MVR)]] -> 5.3166628 | AQ48: =Table13[[#This Row],[Total Selling Price / Unit (MVR)]]-(Table13[[#This Row],[GST 8% (MVR)]]+Table13[[#This Row],[Weighted max expense (MVR)]]) -> 294.72474 | AR48: =Table13[[#This Row],[Profit / Unit (MVR)]]*Table13[[#This Row],[Qty (NOS)]] -> 1178.899
A49: Dr. Vitamin C Derma Ampoule 30ml | B49: Serums & Ampoules | C49: 7 | D49: 3.89 | E49: 27.23 | F49: =D49*22 -> 85.58 | G49: =SUM(F49*C49) -> 599.06 | H49: 619.52 | I49: 181.06 | J49: =L49-K49 -> 206.76178 | K49: =(F49/$G$92)*Costs!$B$23 -> 126.57156 | L49: =N49/1.08 -> 333.33333 | M49: =L49*0.08 -> 26.666667 | N49: 360 | O49: =Table13[[#This Row],[Total Selling Price / Unit (MVR)]]*Table13[[#This Row],[Qty (NOS)]] -> 2520 | P49: =Q49*C49 -> 2030 | Q49: 290 | R49: =Q49*0.8 -> 232 | S49: 27.14 | T49: =S49*22 -> 597.08 | U49: 619.52 | V49: 28.16 | W49: 3.89 | X49: =Z49*C49 -> 1198.12 | Y49: 175 | Z49: =AA49*2 -> 171.16 | AA49: 85.58 | AB49: 181.06 | AC49: 360 | AD49: =V49*15.42 -> 434.2272 | AE49: =AD49*1.08 -> 468.96538 | AF49: =C49*AE49 -> 3282.7576 | AG49: =(V49+9)*15.42 -> 573.0072 | AH49: =AG49*1.08 -> 618.84778 | AI49: =C49*AH49 -> 4331.9344 | AJ49: =V49*22 -> 619.52 | AK49: =AJ49*1.08 -> 669.0816 | AL49: =C49*AK49 -> 4683.5712 | AM49: =(V49+9)*22 -> 817.52 | AN49: =AM49*1.08 -> 882.9216 | AO49: =C49*AN49 -> 6180.4512 | AP49: =Table13[[#This Row],[Total Selling Price / Unit (MVR)]]/Table13[[#This Row],[CNF / Unit (MVR)]] -> 4.2065903 | AQ49: =Table13[[#This Row],[Total Selling Price / Unit (MVR)]]-(Table13[[#This Row],[GST 8% (MVR)]]+Table13[[#This Row],[Weighted max expense (MVR)]]) -> 206.76178 | AR49: =Table13[[#This Row],[Profit / Unit (MVR)]]*Table13[[#This Row],[Qty (NOS)]] -> 1447.3324
A50: Heeyul Premium 24K Gold Essence 130ml | B50: Serums & Ampoules | C50: 4 | D50: 9.04 | E50: 36.16 | F50: =D50*22 -> 198.88 | G50: =SUM(F50*C50) -> 795.52 | H50: 570.68 | I50: 453.42 | J50: =L50-K50 -> 150.30386 | K50: =(F50/$G$92)*Costs!$B$23 -> 294.14058 | L50: =N50/1.08 -> 444.44444 | M50: =L50*0.08 -> 35.555556 | N50: 480 | O50: =Table13[[#This Row],[Total Selling Price / Unit (MVR)]]*Table13[[#This Row],[Qty (NOS)]] -> 1920 | P50: =Q50*C50 -> 1920 | Q50: 480 | R50: =Q50*0.8 -> 384 | S50: 25 | T50: =S50*22 -> 550 | U50: 570.68 | V50: 25.94 | W50: 9.04 | X50: =Z50*C50 -> 1591.04 | Y50: 400 | Z50: =AA50*2 -> 397.76 | AA50: 198.88 | AB50: 453.42 | AC50: 480 | AD50: =V50*15.42 -> 399.9948 | AE50: =AD50*1.08 -> 431.99438 | AF50: =C50*AE50 -> 1727.9775 | AG50: =(V50+9)*15.42 -> 538.7748 | AH50: =AG50*1.08 -> 581.87678 | AI50: =C50*AH50 -> 2327.5071 | AJ50: =V50*22 -> 570.68 | AK50: =AJ50*1.08 -> 616.3344 | AL50: =C50*AK50 -> 2465.3376 | AM50: =(V50+9)*22 -> 768.68 | AN50: =AM50*1.08 -> 830.1744 | AO50: =C50*AN50 -> 3320.6976 | AP50: =Table13[[#This Row],[Total Selling Price / Unit (MVR)]]/Table13[[#This Row],[CNF / Unit (MVR)]] -> 2.4135157 | AQ50: =Table13[[#This Row],[Total Selling Price / Unit (MVR)]]-(Table13[[#This Row],[GST 8% (MVR)]]+Table13[[#This Row],[Weighted max expense (MVR)]]) -> 150.30386 | AR50: =Table13[[#This Row],[Profit / Unit (MVR)]]*Table13[[#This Row],[Qty (NOS)]] -> 601.21544
... A75: UV Sun Ultra Shield Sun Stick 20g | B75: Sun Care | C75: 4 | D75: 6.85 | E75: 27.4 | F75: =D75*22 -> 150.7 | G75: =SUM(F75*C75) -> 602.8 | H75: 652.08 | I75: 247.72 | J75: =L75-K75 -> 100.26507 | K75: =(F75/$G$92)*Costs!$B$23 -> 222.88308 | L75: =N75/1.08 -> 323.14815 | M75: =L75*0.08 -> 25.851852 | N75: 349 | O75: =Table13[[#This Row],[Total Selling Price / Unit (MVR)]]*Table13[[#This Row],[Qty (NOS)]] -> 1396 | P75: =Q75*C75 -> 1360 | Q75: 340 | R75: =Q75*0.8 -> 272 | S75: 28.57 | T75: =S75*22 -> 628.54 | U75: 652.08 | V75: 29.64 | W75: 6.85 | X75: =Z75*C75 -> 1205.6 | Y75: 305 | Z75: =AA75*2 -> 301.4 | AA75: 150.7 | AB75: 247.72 | AC75: 349 | AD75: =V75*15.42 -> 457.0488 | AE75: =AD75*1.08 -> 493.6127 | AF75: =C75*AE75 -> 1974.4508 | AG75: =(V75+9)*15.42 -> 595.8288 | AH75: =AG75*1.08 -> 643.4951 | AI75: =C75*AH75 -> 2573.9804 | AJ75: =V75*22 -> 652.08 | AK75: =AJ75*1.08 -> 704.2464 | AL75: =C75*AK75 -> 2816.9856 | AM75: =(V75+9)*22 -> 850.08 | AN75: =AM75*1.08 -> 918.0864 | AO75: =C75*AN75 -> 3672.3456 | AP75: =Table13[[#This Row],[Total Selling Price / Unit (MVR)]]/Table13[[#This Row],[CNF / Unit (MVR)]] -> 2.3158593 | AQ75: =Table13[[#This Row],[Total Selling Price / Unit (MVR)]]-(Table13[[#This Row],[GST 8% (MVR)]]+Table13[[#This Row],[Weighted max expense (MVR)]]) -> 100.26507 | AR75: =Table13[[#This Row],[Profit / Unit (MVR)]]*Table13[[#This Row],[Qty (NOS)]] -> 401.06029
A76: Pore Peeling Pad 60pads | B76: Toner / Peeling Pads | C76: 4 | D76: 4.74 | E76: 18.96 | F76: =D76*22 -> 104.28 | G76: =SUM(F76*C76) -> 417.12 | H76: N/A | I76: 222.42 | J76: =L76-K76 -> 122.62327 | K76: =(F76/$G$92)*Costs!$B$23 -> 154.22858 | L76: =N76/1.08 -> 276.85185 | M76: =L76*0.08 -> 22.148148 | N76: 299 | O76: =Table13[[#This Row],[Total Selling Price / Unit (MVR)]]*Table13[[#This Row],[Qty (NOS)]] -> 1196 | P76: =Q76*C76 -> 1200 | Q76: 300 | R76: =Q76*0.8 -> 240 | S76: 14.29 | T76: =S76*22 -> 314.38 | U76: N/A | V76: 14.8 | W76: 4.74 | X76: =Z76*C76 -> 834.24 | Y76: 210 | Z76: =AA76*2 -> 208.56 | AA76: 104.28 | AB76: 222.42 | AC76: 299 | AD76: =V76*15.42 -> 228.216 | AE76: =AD76*1.08 -> 246.47328 | AF76: =C76*AE76 -> 985.89312 | AG76: =(V76+9)*15.42 -> 366.996 | AH76: =AG76*1.08 -> 396.35568 | AI76: =C76*AH76 -> 1585.4227 | AJ76: =V76*22 -> 325.6 | AK76: =AJ76*1.08 -> 351.648 | AL76: =C76*AK76 -> 1406.592 | AM76: =(V76+9)*22 -> 523.6 | AN76: =AM76*1.08 -> 565.488 | AO76: =C76*AN76 -> 2261.952 | AP76: =Table13[[#This Row],[Total Selling Price / Unit (MVR)]]/Table13[[#This Row],[CNF / Unit (MVR)]] -> 2.8672804 | AQ76: =Table13[[#This Row],[Total Selling Price / Unit (MVR)]]-(Table13[[#This Row],[GST 8% (MVR)]]+Table13[[#This Row],[Weighted max expense (MVR)]]) -> 122.62327 | AR76: =Table13[[#This Row],[Profit / Unit (MVR)]]*Table13[[#This Row],[Qty (NOS)]] -> 490.49308
A77: Truly Centella Toner Pad 60pads | B77: Toner / Peeling Pads | C77: 7 | D77: 6.92 | E77: 48.44 | F77: =D77*22 -> 152.24 | G77: =SUM(F77*C77) -> 1065.68 | H77: 407.66 | I77: 356.84 | J77: =L77-K77 -> 135.02447 | K77: =(F77/$G$92)*Costs!$B$23 -> 225.16071 | L77: =N77/1.08 -> 360.18519 | M77: =L77*0.08 -> 28.814815 | N77: 389 | O77: =Table13[[#This Row],[Total Selling Price / Unit (MVR)]]*Table13[[#This Row],[Qty (NOS)]] -> 2723 | P77: =Q77*C77 -> 2730 | Q77: 390 | R77: =Q77*0.8 -> 312 | S77: 17.86 | T77: =S77*22 -> 392.92 | U77: 407.66 | V77: 18.53 | W77: 6.92 | X77: =Z77*C77 -> 2131.36 | Y77: 305 | Z77: =AA77*2 -> 304.48 | AA77: 152.24 | AB77: 356.84 | AC77: 389 | AD77: =V77*15.42 -> 285.7326 | AE77: =AD77*1.08 -> 308.59121 | AF77: =C77*AE77 -> 2160.1385 | AG77: =(V77+9)*15.42 -> 424.5126 | AH77: =AG77*1.08 -> 458.47361 | AI77: =C77*AH77 -> 3209.3153 | AJ77: =V77*22 -> 407.66 | AK77: =AJ77*1.08 -> 440.2728 | AL77: =C77*AK77 -> 3081.9096 | AM77: =(V77+9)*22 -> 605.66 | AN77: =AM77*1.08 -> 654.1128 | AO77: =C77*AN77 -> 4578.7896 | AP77: =Table13[[#This Row],[Total Selling Price / Unit (MVR)]]/Table13[[#This Row],[CNF / Unit (MVR)]] -> 2.555176 | AQ77: =Table13[[#This Row],[Total Selling Price / Unit (MVR)]]-(Table13[[#This Row],[GST 8% (MVR)]]+Table13[[#This Row],[Weighted max expense (MVR)]]) -> 135.02447 | AR77: =Table13[[#This Row],[Profit / Unit (MVR)]]*Table13[[#This Row],[Qty (NOS)]] -> 945.17131
A78: Truly Glutathione Toner Pad 60pads | B78: Toner / Peeling Pads | C78: 7 | D78: 6.92 | E78: 48.44 | F78: =D78*22 -> 152.24 | G78: =SUM(F78*C78) -> 1065.68 | H78: 407.66 | I78: 356.84 | J78: =L78-K78 -> 135.02447 | K78: =(F78/$G$92)*Costs!$B$23 -> 225.16071 | L78: =N78/1.08 -> 360.18519 | M78: =L78*0.08 -> 28.814815 | N78: 389 | O78: =Table13[[#This Row],[Total Selling Price / Unit (MVR)]]*Table13[[#This Row],[Qty (NOS)]] -> 2723 | P78: =Q78*C78 -> 2730 | Q78: 390 | R78: =Q78*0.8 -> 312 | S78: 17.86 | T78: =S78*22 -> 392.92 | U78: 407.66 | V78: 18.53 | W78: 6.92 | X78: =Z78*C78 -> 2131.36 | Y78: 305 | Z78: =AA78*2 -> 304.48 | AA78: 152.24 | AB78: 356.84 | AC78: 389 | AD78: =V78*15.42 -> 285.7326 | AE78: =AD78*1.08 -> 308.59121 | AF78: =C78*AE78 -> 2160.1385 | AG78: =(V78+9)*15.42 -> 424.5126 | AH78: =AG78*1.08 -> 458.47361 | AI78: =C78*AH78 -> 3209.3153 | AJ78: =V78*22 -> 407.66 | AK78: =AJ78*1.08 -> 440.2728 | AL78: =C78*AK78 -> 3081.9096 | AM78: =(V78+9)*22 -> 605.66 | AN78: =AM78*1.08 -> 654.1128 | AO78: =C78*AN78 -> 4578.7896 | AP78: =Table13[[#This Row],[Total Selling Price / Unit (MVR)]]/Table13[[#This Row],[CNF / Unit (MVR)]] -> 2.555176 | AQ78: =Table13[[#This Row],[Total Selling Price / Unit (MVR)]]-(Table13[[#This Row],[GST 8% (MVR)]]+Table13[[#This Row],[Weighted max expense (MVR)]]) -> 135.02447 | AR78: =Table13[[#This Row],[Profit / Unit (MVR)]]*Table13[[#This Row],[Qty (NOS)]] -> 945.17131
A79: Truly PDRN Toner Pad 60pads | B79: Toner / Peeling Pads | C79: 4 | D79: 6.92 | E79: 27.68 | F79: =D79*22 -> 152.24 | G79: =SUM(F79*C79) -> 608.96 | H79: 407.66 | I79: 356.84 | J79: =L79-K79 -> 135.02447 | K79: =(F79/$G$92)*Costs!$B$23 -> 225.16071 | L79: =N79/1.08 -> 360.18519 | M79: =L79*0.08 -> 28.814815 | N79: 389 | O79: =Table13[[#This Row],[Total Selling Price / Unit (MVR)]]*Table13[[#This Row],[Qty (NOS)]] -> 1556 | P79: =Q79*C79 -> 1560 | Q79: 390 | R79: =Q79*0.8 -> 312 | S79: 17.86 | T79: =S79*22 -> 392.92 | U79: 407.66 | V79: 18.53 | W79: 6.92 | X79: =Z79*C79 -> 1217.92 | Y79: 305 | Z79: =AA79*2 -> 304.48 | AA79: 152.24 | AB79: 356.84 | AC79: 389 | AD79: =V79*15.42 -> 285.7326 | AE79: =AD79*1.08 -> 308.59121 | AF79: =C79*AE79 -> 1234.3648 | AG79: =(V79+9)*15.42 -> 424.5126 | AH79: =AG79*1.08 -> 458.47361 | AI79: =C79*AH79 -> 1833.8944 | AJ79: =V79*22 -> 407.66 | AK79: =AJ79*1.08 -> 440.2728 | AL79: =C79*AK79 -> 1761.0912 | AM79: =(V79+9)*22 -> 605.66 | AN79: =AM79*1.08 -> 654.1128 | AO79: =C79*AN79 -> 2616.4512 | AP79: =Table13[[#This Row],[Total Selling Price / Unit (MVR)]]/Table13[[#This Row],[CNF / Unit (MVR)]] -> 2.555176 | AQ79: =Table13[[#This Row],[Total Selling Price / Unit (MVR)]]-(Table13[[#This Row],[GST 8% (MVR)]]+Table13[[#This Row],[Weighted max expense (MVR)]]) -> 135.02447 | AR79: =Table13[[#This Row],[Profit / Unit (MVR)]]*Table13[[#This Row],[Qty (NOS)]] -> 540.09789
A80: Truly Retinol Toner Pad 60pads | B80: Toner / Peeling Pads | C80: 4 | D80: 6.92 | E80: 27.68 | F80: =D80*22 -> 152.24 | G80: =SUM(F80*C80) -> 608.96 | H80: 407.66 | I80: 356.84 | J80: =L80-K80 -> 135.02447 | K80: =(F80/$G$92)*Costs!$B$23 -> 225.16071 | L80: =N80/1.08 -> 360.18519 | M80: =L80*0.08 -> 28.814815 | N80: 389 | O80: =Table13[[#This Row],[Total Selling Price / Unit (MVR)]]*Table13[[#This Row],[Qty (NOS)]] -> 1556 | P80: =Q80*C80 -> 1560 | Q80: 390 | R80: =Q80*0.8 -> 312 | S80: 17.86 | T80: =S80*22 -> 392.92 | U80: 407.66 | V80: 18.53 | W80: 6.92 | X80: =Z80*C80 -> 1217.92 | Y80: 305 | Z80: =AA80*2 -> 304.48 | AA80: 152.24 | AB80: 356.84 | AC80: 389 | AD80: =V80*15.42 -> 285.7326 | AE80: =AD80*1.08 -> 308.59121 | AF80: =C80*AE80 -> 1234.3648 | AG80: =(V80+9)*15.42 -> 424.5126 | AH80: =AG80*1.08 -> 458.47361 | AI80: =C80*AH80 -> 1833.8944 | AJ80: =V80*22 -> 407.66 | AK80: =AJ80*1.08 -> 440.2728 | AL80: =C80*AK80 -> 1761.0912 | AM80: =(V80+9)*22 -> 605.66 | AN80: =AM80*1.08 -> 654.1128 | AO80: =C80*AN80 -> 2616.4512 | AP80: =Table13[[#This Row],[Total Selling Price / Unit (MVR)]]/Table13[[#This Row],[CNF / Unit (MVR)]] -> 2.555176 | AQ80: =Table13[[#This Row],[Total Selling Price / Unit (MVR)]]-(Table13[[#This Row],[GST 8% (MVR)]]+Table13[[#This Row],[Weighted max expense (MVR)]]) -> 135.02447 | AR80: =Table13[[#This Row],[Profit / Unit (MVR)]]*Table13[[#This Row],[Qty (NOS)]] -> 540.09789
A81: Centella Moisture Skin 150ml | B81: Toners & Emulsions | C81: 4 | D81: 5.8 | E81: 23.2 | F81: =D81*22 -> 127.6 | G81: =SUM(F81*C81) -> 510.4 | H81: 407.66 | I81: 292.16 | J81: =L81-K81 -> 135.35556 | K81: =(F81/$G$92)*Costs!$B$23 -> 188.71852 | L81: =N81/1.08 -> 324.07407 | M81: =L81*0.08 -> 25.925926 | N81: 350 | O81: =Table13[[#This Row],[Total Selling Price / Unit (MVR)]]*Table13[[#This Row],[Qty (NOS)]] -> 1400 | P81: =Q81*C81 -> 1400 | Q81: 350 | R81: =Q81*0.8 -> 280 | S81: 7.14 | T81: =S81*22 -> 157.08 | U81: 407.66 | V81: 18.53 | W81: 5.8 | X81: =Z81*C81 -> 1020.8 | Y81: 255 | Z81: =AA81*2 -> 255.2 | AA81: 127.6 | AB81: 292.16 | AC81: 350 | AD81: =V81*15.42 -> 285.7326 | AE81: =AD81*1.08 -> 308.59121 | AF81: =C81*AE81 -> 1234.3648 | AG81: =(V81+9)*15.42 -> 424.5126 | AH81: =AG81*1.08 -> 458.47361 | AI81: =C81*AH81 -> 1833.8944 | AJ81: =V81*22 -> 407.66 | AK81: =AJ81*1.08 -> 440.2728 | AL81: =C81*AK81 -> 1761.0912 | AM81: =(V81+9)*22 -> 605.66 | AN81: =AM81*1.08 -> 654.1128 | AO81: =C81*AN81 -> 2616.4512 | AP81: =Table13[[#This Row],[Total Selling Price / Unit (MVR)]]/Table13[[#This Row],[CNF / Unit (MVR)]] -> 2.7429467 | AQ81: =Table13[[#This Row],[Total Selling Price / Unit (MVR)]]-(Table13[[#This Row],[GST 8% (MVR)]]+Table13[[#This Row],[Weighted max expense (MVR)]]) -> 135.35556 | AR81: =Table13[[#This Row],[Profit / Unit (MVR)]]*Table13[[#This Row],[Qty (NOS)]] -> 541.42223
A82: Collagen + Green Tea Moisture Lotion 150ml | B82: Toners & Emulsions | C82: 4 | D82: 5.94 | E82: 23.76 | F82: =D82*22 -> 130.68 | G82: =SUM(F82*C82) -> 522.72 | H82: 407.66 | I82: 375.76 | J82: =L82-K82 -> 130.80028 | K82: =(F82/$G$92)*Costs!$B$23 -> 193.27379 | L82: =N82/1.08 -> 324.07407 | M82: =L82*0.08 -> 25.925926 | N82: 350 | O82: =Table13[[#This Row],[Total Selling Price / Unit (MVR)]]*Table13[[#This Row],[Qty (NOS)]] -> 1400 | P82: =Q82*C82 -> 1400 | Q82: 350 | R82: =Q82*0.8 -> 280 | S82: 7.14 | T82: =S82*22 -> 157.08 | U82: 407.66 | V82: 18.53 | W82: 5.94 | X82: =Z82*C82 -> 1045.44 | Y82: 265 | Z82: =AA82*2 -> 261.36 | AA82: 130.68 | AB82: 375.76 | AC82: 350 | AD82: =V82*15.42 -> 285.7326 | AE82: =AD82*1.08 -> 308.59121 | AF82: =C82*AE82 -> 1234.3648 | AG82: =(V82+9)*15.42 -> 424.5126 | AH82: =AG82*1.08 -> 458.47361 | AI82: =C82*AH82 -> 1833.8944 | AJ82: =V82*22 -> 407.66 | AK82: =AJ82*1.08 -> 440.2728 | AL82: =C82*AK82 -> 1761.0912 | AM82: =(V82+9)*22 -> 605.66 | AN82: =AM82*1.08 -> 654.1128 | AO82: =C82*AN82 -> 2616.4512 | AP82: =Table13[[#This Row],[Total Selling Price / Unit (MVR)]]/Table13[[#This Row],[CNF / Unit (MVR)]] -> 2.6782981 | AQ82: =Table13[[#This Row],[Total Selling Price / Unit (MVR)]]-(Table13[[#This Row],[GST 8% (MVR)]]+Table13[[#This Row],[Weighted max expense (MVR)]]) -> 130.80028 | AR82: =Table13[[#This Row],[Profit / Unit (MVR)]]*Table13[[#This Row],[Qty (NOS)]] -> 523.20113
A83: Collagen + Green Tea Moisture Skin 150ml | B83: Toners & Emulsions | C83: 4 | D83: 5.94 | E83: 23.76 | F83: =D83*22 -> 130.68 | G83: =SUM(F83*C83) -> 522.72 | H83: 407.66 | I83: 375.76 | J83: =L83-K83 -> 148.39288 | K83: =(F83/$G$92)*Costs!$B$23 -> 193.27379 | L83: =N83/1.08 -> 341.66667 | M83: =L83*0.08 -> 27.333333 | N83: 369 | O83: =Table13[[#This Row],[Total Selling Price / Unit (MVR)]]*Table13[[#This Row],[Qty (NOS)]] -> 1476 | P83: =Q83*C83 -> 1400 | Q83: 350 | R83: =Q83*0.8 -> 280 | S83: 7.14 | T83: =S83*22 -> 157.08 | U83: 407.66 | V83: 18.53 | W83: 5.94 | X83: =Z83*C83 -> 1045.44 | Y83: 265 | Z83: =AA83*2 -> 261.36 | AA83: 130.68 | AB83: 375.76 | AC83: 369 | AD83: =V83*15.42 -> 285.7326 | AE83: =AD83*1.08 -> 308.59121 | AF83: =C83*AE83 -> 1234.3648 | AG83: =(V83+9)*15.42 -> 424.5126 | AH83: =AG83*1.08 -> 458.47361 | AI83: =C83*AH83 -> 1833.8944 | AJ83: =V83*22 -> 407.66 | AK83: =AJ83*1.08 -> 440.2728 | AL83: =C83*AK83 -> 1761.0912 | AM83: =(V83+9)*22 -> 605.66 | AN83: =AM83*1.08 -> 654.1128 | AO83: =C83*AN83 -> 2616.4512 | AP83: =Table13[[#This Row],[Total Selling Price / Unit (MVR)]]/Table13[[#This Row],[CNF / Unit (MVR)]] -> 2.8236915 | AQ83: =Table13[[#This Row],[Total Selling Price / Unit (MVR)]]-(Table13[[#This Row],[GST 8% (MVR)]]+Table13[[#This Row],[Weighted max expense (MVR)]]) -> 148.39288 | AR83: =Table13[[#This Row],[Profit / Unit (MVR)]]*Table13[[#This Row],[Qty (NOS)]] -> 593.5715
A84: Collagen Derma Skin 200ml | B84: Toners & Emulsions | C84: 4 | D84: 6.64 | E84: 26.56 | F84: =D84*22 -> 146.08 | G84: =SUM(F84*C84) -> 584.32 | H84: 1271.6 | I84: 339.9 | J84: =L84-K84 -> 339.50539 | K84: =(F84/$G$92)*Costs!$B$23 -> 216.05016 | L84: =N84/1.08 -> 555.55556 | M84: =L84*0.08 -> 44.444444 | N84: 600 | O84: =Table13[[#This Row],[Total Selling Price / Unit (MVR)]]*Table13[[#This Row],[Qty (NOS)]] -> 2400 | P84: =Q84*C84 -> 1500 | Q84: 375 | R84: =Q84*0.8 -> 300 | S84: 55.71 | T84: =S84*22 -> 1225.62 | U84: 1271.6 | V84: 57.8 | W84: 6.64 | X84: =Z84*C84 -> 1168.64 | Y84: 295 | Z84: =AA84*2 -> 292.16 | AA84: 146.08 | AB84: 339.9 | AC84: 600 | AD84: =V84*15.42 -> 891.276 | AE84: =AD84*1.08 -> 962.57808 | AF84: =C84*AE84 -> 3850.3123 | AG84: =(V84+9)*15.42 -> 1030.056 | AH84: =AG84*1.08 -> 1112.4605 | AI84: =C84*AH84 -> 4449.8419 | AJ84: =V84*22 -> 1271.6 | AK84: =AJ84*1.08 -> 1373.328 | AL84: =C84*AK84 -> 5493.312 | AM84: =(V84+9)*22 -> 1469.6 | AN84: =AM84*1.08 -> 1587.168 | AO84: =C84*AN84 -> 6348.672 | AP84: =Table13[[#This Row],[Total Selling Price / Unit (MVR)]]/Table13[[#This Row],[CNF / Unit (MVR)]] -> 4.1073384 | AQ84: =Table13[[#This Row],[Total Selling Price / Unit (MVR)]]-(Table13[[#This Row],[GST 8% (MVR)]]+Table13[[#This Row],[Weighted max expense (MVR)]]) -> 339.50539 | AR84: =Table13[[#This Row],[Profit / Unit (MVR)]]*Table13[[#This Row],[Qty (NOS)]] -> 1358.0216
A85: Collagen Hyaluronic Toner 300ml | B85: Toners & Emulsions | C85: 4 | D85: 8.3 | E85: 33.2 | F85: =D85*22 -> 182.6 | G85: =SUM(F85*C85) -> 730.4 | H85: N/A | I85: 438.68 | J85: =L85-K85 -> 100.30767 | K85: =(F85/$G$92)*Costs!$B$23 -> 270.0627 | L85: =N85/1.08 -> 370.37037 | M85: =L85*0.08 -> 29.62963 | N85: 400 | O85: =Table13[[#This Row],[Total Selling Price / Unit (MVR)]]*Table13[[#This Row],[Qty (NOS)]] -> 1600 | P85: =Q85*C85 -> 1920 | Q85: 480 | R85: =Q85*0.8 -> 384 | S85: 25 | T85: =S85*22 -> 550 | U85: N/A | V85: 25.94 | W85: 8.3 | X85: =Z85*C85 -> 1460.8 | Y85: 365 | Z85: =AA85*2 -> 365.2 | AA85: 182.6 | AB85: 438.68 | AC85: 400 | AD85: =V85*15.42 -> 399.9948 | AE85: =AD85*1.08 -> 431.99438 | AF85: =C85*AE85 -> 1727.9775 | AG85: =(V85+9)*15.42 -> 538.7748 | AH85: =AG85*1.08 -> 581.87678 | AI85: =C85*AH85 -> 2327.5071 | AJ85: =V85*22 -> 570.68 | AK85: =AJ85*1.08 -> 616.3344 | AL85: =C85*AK85 -> 2465.3376 | AM85: =(V85+9)*22 -> 768.68 | AN85: =AM85*1.08 -> 830.1744 | AO85: =C85*AN85 -> 3320.6976 | AP85: =Table13[[#This Row],[Total Selling Price / Unit (MVR)]]/Table13[[#This Row],[CNF / Unit (MVR)]] -> 2.1905805 | AQ85: =Table13[[#This Row],[Total Selling Price / Unit (MVR)]]-(Table13[[#This Row],[GST 8% (MVR)]]+Table13[[#This Row],[Weighted max expense (MVR)]]) -> 100.30767 | AR85: =Table13[[#This Row],[Profit / Unit (MVR)]]*Table13[[#This Row],[Qty (NOS)]] -> 401.23066
A86: COLLAGEN+GREEN TEA MOISTURE SKIN 150ml | B86: Toners & Emulsions | C86: 4 | D86: 6.12 | E86: 24.48 | F86: =D86*22 -> 134.64 | G86: =SUM(F86*C86) -> 538.56 | H86: 407.66 | I86: 375.76 | J86: =L86-K86 -> 124.9435 | K86: =(F86/$G$92)*Costs!$B$23 -> 199.13057 | L86: =N86/1.08 -> 324.07407 | M86: =L86*0.08 -> 25.925926 | N86: 350 | O86: =Table13[[#This Row],[Total Selling Price / Unit (MVR)]]*Table13[[#This Row],[Qty (NOS)]] -> 1400 | P86: =Q86*C86 -> 1400 | Q86: 350 | R86: =Q86*0.8 -> 280 | S86: 7.14 | T86: =S86*22 -> 157.08 | U86: 407.66 | V86: 18.53 | W86: 6.12 | X86: =Z86*C86 -> 1077.12 | Y86: 270 | Z86: =AA86*2 -> 269.28 | AA86: 134.64 | AB86: 375.76 | AC86: 350 | AD86: =V86*15.42 -> 285.7326 | AE86: =AD86*1.08 -> 308.59121 | AF86: =C86*AE86 -> 1234.3648 | AG86: =(V86+9)*15.42 -> 424.5126 | AH86: =AG86*1.08 -> 458.47361 | AI86: =C86*AH86 -> 1833.8944 | AJ86: =V86*22 -> 407.66 | AK86: =AJ86*1.08 -> 440.2728 | AL86: =C86*AK86 -> 1761.0912 | AM86: =(V86+9)*22 -> 605.66 | AN86: =AM86*1.08 -> 654.1128 | AO86: =C86*AN86 -> 2616.4512 | AP86: =Table13[[#This Row],[Total Selling Price / Unit (MVR)]]/Table13[[#This Row],[CNF / Unit (MVR)]] -> 2.5995247 | AQ86: =Table13[[#This Row],[Total Selling Price / Unit (MVR)]]-(Table13[[#This Row],[GST 8% (MVR)]]+Table13[[#This Row],[Weighted max expense (MVR)]]) -> 124.9435 | AR86: =Table13[[#This Row],[Profit / Unit (MVR)]]*Table13[[#This Row],[Qty (NOS)]] -> 499.77401
A87: Hyaluronic Derma Lotion 200ml | B87: Toners & Emulsions | C87: 4 | D87: 6.78 | E87: 27.12 | F87: =D87*22 -> 149.16 | G87: =SUM(F87*C87) -> 596.64 | H87: N/A | I87: 331.54 | J87: =L87-K87 -> 149.76493 | K87: =(F87/$G$92)*Costs!$B$23 -> 220.60544 | L87: =N87/1.08 -> 370.37037 | M87: =L87*0.08 -> 29.62963 | N87: 400 | O87: =Table13[[#This Row],[Total Selling Price / Unit (MVR)]]*Table13[[#This Row],[Qty (NOS)]] -> 1600 | P87: =Q87*C87 -> 1500 | Q87: 375 | R87: =Q87*0.8 -> 300 | S87: 55.71 | T87: =S87*22 -> 1225.62 | U87: N/A | V87: 57.8 | W87: 6.78 | X87: =Z87*C87 -> 1193.28 | Y87: 300 | Z87: =AA87*2 -> 298.32 | AA87: 149.16 | AB87: 331.54 | AC87: 400 | AD87: =V87*15.42 -> 891.276 | AE87: =AD87*1.08 -> 962.57808 | AF87: =C87*AE87 -> 3850.3123 | AG87: =(V87+9)*15.42 -> 1030.056 | AH87: =AG87*1.08 -> 1112.4605 | AI87: =C87*AH87 -> 4449.8419 | AJ87: =V87*22 -> 1271.6 | AK87: =AJ87*1.08 -> 1373.328 | AL87: =C87*AK87 -> 5493.312 | AM87: =(V87+9)*22 -> 1469.6 | AN87: =AM87*1.08 -> 1587.168 | AO87: =C87*AN87 -> 6348.672 | AP87: =Table13[[#This Row],[Total Selling Price / Unit (MVR)]]/Table13[[#This Row],[CNF / Unit (MVR)]] -> 2.6816841 | AQ87: =Table13[[#This Row],[Total Selling Price / Unit (MVR)]]-(Table13[[#This Row],[GST 8% (MVR)]]+Table13[[#This Row],[Weighted max expense (MVR)]]) -> 149.76493 | AR87: =Table13[[#This Row],[Profit / Unit (MVR)]]*Table13[[#This Row],[Qty (NOS)]] -> 599.05973
A88: Tea Tree Derma Lotion 210ml | B88: Toners & Emulsions | C88: 4 | D88: 6.78 | E88: 27.12 | F88: =D88*22 -> 149.16 | G88: =SUM(F88*C88) -> 596.64 | H88: N/A | I88: 331.54 | J88: =L88-K88 -> 149.76493 | K88: =(F88/$G$92)*Costs!$B$23 -> 220.60544 | L88: =N88/1.08 -> 370.37037 | M88: =L88*0.08 -> 29.62963 | N88: 400 | O88: =Table13[[#This Row],[Total Selling Price / Unit (MVR)]]*Table13[[#This Row],[Qty (NOS)]] -> 1600 | P88: =Q88*C88 -> 1500 | Q88: 375 | R88: =Q88*0.8 -> 300 | S88: 55.71 | T88: =S88*22 -> 1225.62 | U88: N/A | V88: 57.8 | W88: 6.78 | X88: =Z88*C88 -> 1193.28 | Y88: 300 | Z88: =AA88*2 -> 298.32 | AA88: 149.16 | AB88: 331.54 | AC88: 400 | AD88: =V88*15.42 -> 891.276 | AE88: =AD88*1.08 -> 962.57808 | AF88: =C88*AE88 -> 3850.3123 | AG88: =(V88+9)*15.42 -> 1030.056 | AH88: =AG88*1.08 -> 1112.4605 | AI88: =C88*AH88 -> 4449.8419 | AJ88: =V88*22 -> 1271.6 | AK88: =AJ88*1.08 -> 1373.328 | AL88: =C88*AK88 -> 5493.312 | AM88: =(V88+9)*22 -> 1469.6 | AN88: =AM88*1.08 -> 1587.168 | AO88: =C88*AN88 -> 6348.672 | AP88: =Table13[[#This Row],[Total Selling Price / Unit (MVR)]]/Table13[[#This Row],[CNF / Unit (MVR)]] -> 2.6816841 | AQ88: =Table13[[#This Row],[Total Selling Price / Unit (MVR)]]-(Table13[[#This Row],[GST 8% (MVR)]]+Table13[[#This Row],[Weighted max expense (MVR)]]) -> 149.76493 | AR88: =Table13[[#This Row],[Profit / Unit (MVR)]]*Table13[[#This Row],[Qty (NOS)]] -> 599.05973
A89: Tea Tree Derma Skin 210ml | B89: Toners & Emulsions | C89: 7 | D89: 6.78 | E89: 47.46 | F89: =D89*22 -> 149.16 | G89: =SUM(F89*C89) -> 1044.12 | H89: N/A | I89: 339.9 | J89: =L89-K89 -> 334.95012 | K89: =(F89/$G$92)*Costs!$B$23 -> 220.60544 | L89: =N89/1.08 -> 555.55556 | M89: =L89*0.08 -> 44.444444 | N89: 600 | O89: =Table13[[#This Row],[Total Selling Price / Unit (MVR)]]*Table13[[#This Row],[Qty (NOS)]] -> 4200 | P89: =Q89*C89 -> 2625 | Q89: 375 | R89: =Q89*0.8 -> 300 | S89: 55.71 | T89: =S89*22 -> 1225.62 | U89: N/A | V89: 57.8 | W89: 6.78 | X89: =Z89*C89 -> 2088.24 | Y89: 300 | Z89: =AA89*2 -> 298.32 | AA89: 149.16 | AB89: 339.9 | AC89: 600 | AD89: =V89*15.42 -> 891.276 | AE89: =AD89*1.08 -> 962.57808 | AF89: =C89*AE89 -> 6738.0466 | AG89: =(V89+9)*15.42 -> 1030.056 | AH89: =AG89*1.08 -> 1112.4605 | AI89: =C89*AH89 -> 7787.2234 | AJ89: =V89*22 -> 1271.6 | AK89: =AJ89*1.08 -> 1373.328 | AL89: =C89*AK89 -> 9613.296 | AM89: =(V89+9)*22 -> 1469.6 | AN89: =AM89*1.08 -> 1587.168 | AO89: =C89*AN89 -> 11110.176 | AP89: =Table13[[#This Row],[Total Selling Price / Unit (MVR)]]/Table13[[#This Row],[CNF / Unit (MVR)]] -> 4.0225261 | AQ89: =Table13[[#This Row],[Total Selling Price / Unit (MVR)]]-(Table13[[#This Row],[GST 8% (MVR)]]+Table13[[#This Row],[Weighted max expense (MVR)]]) -> 334.95012 | AR89: =Table13[[#This Row],[Profit / Unit (MVR)]]*Table13[[#This Row],[Qty (NOS)]] -> 2344.6508
A90: Vitamin C Pure Emulsion 120ml | B90: Toners & Emulsions | C90: 4 | D90: 8.98 | E90: 35.92 | F90: =D90*22 -> 197.56 | G90: =SUM(F90*C90) -> 790.24 | H90: 1271.6 | I90: 358.16 | J90: =L90-K90 -> 124.47834 | K90: =(F90/$G$92)*Costs!$B$23 -> 292.18832 | L90: =N90/1.08 -> 416.66667 | M90: =L90*0.08 -> 33.333333 | N90: 450 | O90: =Table13[[#This Row],[Total Selling Price / Unit (MVR)]]*Table13[[#This Row],[Qty (NOS)]] -> 1800 | P90: =Q90*C90 -> 2000 | Q90: 500 | R90: =Q90*0.8 -> 400 | S90: 55.71 | T90: =S90*22 -> 1225.62 | U90: 1271.6 | V90: 57.8 | W90: 8.98 | X90: =Z90*C90 -> 1580.48 | Y90: 395 | Z90: =AA90*2 -> 395.12 | AA90: 197.56 | AB90: 358.16 | AC90: 450 | AD90: =V90*15.42 -> 891.276 | AE90: =AD90*1.08 -> 962.57808 | AF90: =C90*AE90 -> 3850.3123 | AG90: =(V90+9)*15.42 -> 1030.056 | AH90: =AG90*1.08 -> 1112.4605 | AI90: =C90*AH90 -> 4449.8419 | AJ90: =V90*22 -> 1271.6 | AK90: =AJ90*1.08 -> 1373.328 | AL90: =C90*AK90 -> 5493.312 | AM90: =(V90+9)*22 -> 1469.6 | AN90: =AM90*1.08 -> 1587.168 | AO90: =C90*AN90 -> 6348.672 | AP90: =Table13[[#This Row],[Total Selling Price / Unit (MVR)]]/Table13[[#This Row],[CNF / Unit (MVR)]] -> 2.277789 | AQ90: =Table13[[#This Row],[Total Selling Price / Unit (MVR)]]-(Table13[[#This Row],[GST 8% (MVR)]]+Table13[[#This Row],[Weighted max expense (MVR)]]) -> 124.47834 | AR90: =Table13[[#This Row],[Profit / Unit (MVR)]]*Table13[[#This Row],[Qty (NOS)]] -> 497.91337
A91: Vitamin C Pure Toner 120ml | B91: Toners & Emulsions | C91: 4 | D91: 8.98 | E91: 35.92 | F91: =D91*22 -> 197.56 | G91: =SUM(F91*C91) -> 790.24 | H91: 1271.6 | I91: 426.14 | J91: =L91-K91 -> 170.77464 | K91: =(F91/$G$92)*Costs!$B$23 -> 292.18832 | L91: =N91/1.08 -> 462.96296 | M91: =L91*0.08 -> 37.037037 | N91: 500 | O91: =Table13[[#This Row],[Total Selling Price / Unit (MVR)]]*Table13[[#This Row],[Qty (NOS)]] -> 2000 | P91: =Q91*C91 -> 2200 | Q91: 550 | R91: =Q91*0.8 -> 440 | S91: 55.71 | T91: =S91*22 -> 1225.62 | U91: 1271.6 | V91: 57.8 | W91: 8.98 | X91: =Z91*C91 -> 1580.48 | Y91: 395 | Z91: =AA91*2 -> 395.12 | AA91: 197.56 | AB91: 426.14 | AC91: 500 | AD91: =V91*15.42 -> 891.276 | AE91: =AD91*1.08 -> 962.57808 | AF91: =C91*AE91 -> 3850.3123 | AG91: =(V91+9)*15.42 -> 1030.056 | AH91: =AG91*1.08 -> 1112.4605 | AI91: =C91*AH91 -> 4449.8419 | AJ91: =V91*22 -> 1271.6 | AK91: =AJ91*1.08 -> 1373.328 | AL91: =C91*AK91 -> 5493.312 | AM91: =(V91+9)*22 -> 1469.6 | AN91: =AM91*1.08 -> 1587.168 | AO91: =C91*AN91 -> 6348.672 | AP91: =Table13[[#This Row],[Total Selling Price / Unit (MVR)]]/Table13[[#This Row],[CNF / Unit (MVR)]] -> 2.5308767 | AQ91: =Table13[[#This Row],[Total Selling Price / Unit (MVR)]]-(Table13[[#This Row],[GST 8% (MVR)]]+Table13[[#This Row],[Weighted max expense (MVR)]]) -> 170.77464 | AR91: =Table13[[#This Row],[Profit / Unit (MVR)]]*Table13[[#This Row],[Qty (NOS)]] -> 683.09856
A92: TOTAL - 89 line items | C92: 422 | D92: =SUM(D3:D91) -> 460.45 | E92: 2136.63 | F92: =SUM(F3:F91) -> 10129.9 | G92: =SUM(G3:G91) -> 46834.7 | J92: =L92-K92 -> 12124.509 | K92: =SUM(K3:K91) -> 14981.973 | L92: =SUM(L3:L91) -> 27106.481 | M92: =SUM(M3:M91) -> 2168.5185 | N92: =SUM(N3:N91) -> 29275 | O92: =SUM(O3:O91) -> 136161 | P92: =SUM(P3:P91) -> 137115 | Q92: =SUM(Q3:Q91) -> 29570 | R92: =SUM(R3:R91) -> 23656 | ... Z92: =SUM(Z3:Z91) -> 20259.8 | AA92: 10129.9 | AB92: =SUM(AB3:AB91) -> 21941.4 | AC92: =SUM(AC3:AC91) -> 29275 | AD92: =SUM(AD3:AD91) -> 34993.531 | AE92: =SUM(AE3:AE91) -> 37793.014 | AF92: =SUM(AF3:AF91) -> 170851.78 | AG92: =SUM(AG3:AG91) -> 47344.951 | AH92: =SUM(AH3:AH91) -> 51132.547 | AI92: =SUM(AI3:AI91) -> 233802.39 | ... AO92: =SUM(AO3:AO91) -> 333570.2 | AP92: =(SUM(AP3:AP91)/89) -> 3.2987643 | AQ92: =SUM(AQ3:AQ91) -> 12124.509 | AR92: =SUM(AR3:AR91) -> 56807.17
N93: Current Price | O93: Current Expected Revenue on 100% sales | Q93: Final Price | T93: Kim Big List | U93: Lebelage Website Price w/o Shipping | AA93: CNF | AB93: Yesstyle Price w/o Shipping | AD93: (Lebelage selling price)*15.42 | AE93: Per Product | AF93: "Minimum Selling Price" Revenue on 100% sales | AG93: (Lebelage selling price + 9 usd shipping)*15.42 | AH93: Per Product | AI93: "Alt 1 Median Selling Price" Revenue on 100% sales | AJ93: (Lebelage selling price)*22 | AK93: Per Product | AL93: "Alt 2 Median Selling Price" Revenue on 100% sales | AM93: (Lebelage selling price + 9usd shipping)*22 | AN93: Per Product | AO93: "Maximum Selling Price" Revenue on 100% sales
